Workbook

Sheet README
A1: Sinochem Holdings - sector peer comparison (Energy, Agriculture, Rubber)
A2: Prepared 12 Oct 2026. Basis: fiscal year ended 31 Dec 2025 (audited / filed), with H1 2026 momentum where available.
A4: How to read this workbook
A5: Scorecard - rank of each Sinochem entity against its peer group on nine headline metrics (live formulas).
A6: Energy / Agriculture / Rubber - full ratio matrices, peer median/high/low, sub-group medians, and anchor-minus-median row (green = better, red = worse).
A7: H1-2026 momentum - first-half 2026 vs first-half 2025 revenue and net income.
A8: Group context - disclosed Sinochem-level data (Sinochem Corp, Sinochem Energy segments, Syngenta Group, Pirelli).
A9: Data - standardised inputs (blue) with the FY2024 comparatives used for growth and averages; FX - editable USD translation rates.
A11: What 'Sinochem' means here
A12: Sinochem Holdings (中国中化控股) is a state-owned, unlisted group; it publishes no consolidated sector split. Each sector is therefore anchored on the group's operating entities that DO disclose full financials:
A13: Energy: Sinochem Energy (中化能源), the petrochemical segment's operating company (trading + 15 mt/y refining capacity centred on Quanzhou + retail).
A14: Agriculture: Syngenta AG (global crop protection + seeds) with ADAMA, Yangnong and Sinofert as additional group entities; Syngenta Group headline sales/EBITDA in 'Group context'.
... A30: 6) Interim read-through (H1 2026) is limited to companies that filed H1 reports; the 2026 oil-price spike materially lifts refining profits.

Sheet Scorecard
A1: Scorecard - where each Sinochem entity ranks against its peer group (FY2025)
A2: Rank 1 = best among the entity plus its peers (n shown). Tier: top third / mid / bottom third by rank. All values are live formulas pulling from the sector sheets. Syngenta AG, ADAMA and Yangnong are compared with crop-protection & seeds peers; Sinofert with crop-nutrition peers.
A4: Sinochem entity | B4: Peer group | C4: Metric | D4: Entity | E4: Peer median | F4: Entity - median | G4: Rank | H4: of n | I4: Tier
A5: Sinochem Energy (中化能源) | B5: All listed peers | C5: Revenue growth FY25 | D5: =Energy!F8 -> -0.076815097 | E5: =IFERROR(MEDIAN(Energy!F9:F13),"n/a") -> -0.094640798 | F5: =IFERROR(D5-E5,"n/a") -> 0.017825701 | G5: =IF(ISNUMBER(D5),1+COUNTIF(Energy!F9:F13,">"&D5),"n/a") -> 3 | H5: =IF(ISNUMBER(D5),1+COUNT(Energy!F9:F13),"n/a") -> 6 | I5: =IF(ISNUMBER(G5),IF((H5-G5)/(H5-1)>=0.67,"Top third",IF((H5-G5)/(H5-1)<=0.33,"Bottom third","Mid-pack")),IF(D5="n.m.","Bottom third (n.m.)","n/a")) -> Mid-pack
C6: EBITDA margin | D6: =Energy!J8 -> 0.012682565 | E6: =IFERROR(MEDIAN(Energy!J9:J13),"n/a") -> 0.085277705 | F6: =IFERROR(D6-E6,"n/a") -> -0.07259514 | G6: =IF(ISNUMBER(D6),1+COUNTIF(Energy!J9:J13,">"&D6),"n/a") -> 6 | H6: =IF(ISNUMBER(D6),1+COUNT(Energy!J9:J13),"n/a") -> 6 | I6: =IF(ISNUMBER(G6),IF((H6-G6)/(H6-1)>=0.67,"Top third",IF((H6-G6)/(H6-1)<=0.33,"Bottom third","Mid-pack")),IF(D6="n.m.","Bottom third (n.m.)","n/a")) -> Bottom third
C7: Net margin | D7: =Energy!L8 -> -0.0042697433 | E7: =IFERROR(MEDIAN(Energy!L9:L13),"n/a") -> 0.012663535 | F7: =IFERROR(D7-E7,"n/a") -> -0.016933278 | G7: =IF(ISNUMBER(D7),1+COUNTIF(Energy!L9:L13,">"&D7),"n/a") -> 5 | H7: =IF(ISNUMBER(D7),1+COUNT(Energy!L9:L13),"n/a") -> 6 | I7: =IF(ISNUMBER(G7),IF((H7-G7)/(H7-1)>=0.67,"Top third",IF((H7-G7)/(H7-1)<=0.33,"Bottom third","Mid-pack")),IF(D7="n.m.","Bottom third (n.m.)","n/a")) -> Bottom third
C8: ROE (NI / avg equity) | D8: =Energy!N8 -> -0.045469204 | E8: =IFERROR(MEDIAN(Energy!N9:N13),"n/a") -> 0.035858428 | F8: =IFERROR(D8-E8,"n/a") -> -0.081327632 | G8: =IF(ISNUMBER(D8),1+COUNTIF(Energy!N9:N13,">"&D8),"n/a") -> 5 | H8: =IF(ISNUMBER(D8),1+COUNT(Energy!N9:N13),"n/a") -> 6 | I8: =IF(ISNUMBER(G8),IF((H8-G8)/(H8-1)>=0.67,"Top third",IF((H8-G8)/(H8-1)<=0.33,"Bottom third","Mid-pack")),IF(D8="n.m.","Bottom third (n.m.)","n/a")) -> Bottom third
C9: EBITDA / avg assets | D9: =Energy!M8 -> 0.048118216 | E9: =IFERROR(MEDIAN(Energy!M9:M13),"n/a") -> 0.080882693 | F9: =IFERROR(D9-E9,"n/a") -> -0.032764477 | G9: =IF(ISNUMBER(D9),1+COUNTIF(Energy!M9:M13,">"&D9),"n/a") -> 6 | H9: =IF(ISNUMBER(D9),1+COUNT(Energy!M9:M13),"n/a") -> 6 | I9: =IF(ISNUMBER(G9),IF((H9-G9)/(H9-1)>=0.67,"Top third",IF((H9-G9)/(H9-1)<=0.33,"Bottom third","Mid-pack")),IF(D9="n.m.","Bottom third (n.m.)","n/a")) -> Bottom third
C10: Net debt / EBITDA (x) | D10: =Energy!S8 -> 4.4530793 | E10: =IFERROR(MEDIAN(Energy!S9:S13),"n/a") -> 2.2180399 | F10: =IFERROR(D10-E10,"n/a") -> 2.2350395 | G10: =IF(ISNUMBER(D10),1+COUNTIF(Energy!S9:S13,"<"&D10),"n/a") -> 4 | H10: =IF(ISNUMBER(D10),1+COUNT(Energy!S9:S13),"n/a") -> 6 | I10: =IF(ISNUMBER(G10),IF((H10-G10)/(H10-1)>=0.67,"Top third",IF((H10-G10)/(H10-1)<=0.33,"Bottom third","Mid-pack")),IF(D10="n.m.","Bottom third (n.m.)","n/a")) -> Mid-pack
C11: Interest cover (EBIT / interest, x) | D11: =Energy!T8 -> -0.38309722 | E11: =IFERROR(MEDIAN(Energy!T9:T13),"n/a") -> 2.8640308 | F11: =IFERROR(D11-E11,"n/a") -> -3.247128 | G11: =IF(ISNUMBER(D11),1+COUNTIF(Energy!T9:T13,">"&D11),"n/a") -> 5 | H11: =IF(ISNUMBER(D11),1+COUNT(Energy!T9:T13),"n/a") -> 6 | I11: =IF(ISNUMBER(G11),IF((H11-G11)/(H11-1)>=0.67,"Top third",IF((H11-G11)/(H11-1)<=0.33,"Bottom third","Mid-pack")),IF(D11="n.m.","Bottom third (n.m.)","n/a")) -> Bottom third
C12: OCF / EBITDA (cash conversion) | D12: =Energy!W8 -> 1.3367685 | E12: =IFERROR(MEDIAN(Energy!W9:W13),"n/a") -> 0.94757037 | F12: =IFERROR(D12-E12,"n/a") -> 0.38919811 | G12: =IF(ISNUMBER(D12),1+COUNTIF(Energy!W9:W13,">"&D12),"n/a") -> 2 | H12: =IF(ISNUMBER(D12),1+COUNT(Energy!W9:W13),"n/a") -> 6 | I12: =IF(ISNUMBER(G12),IF((H12-G12)/(H12-1)>=0.67,"Top third",IF((H12-G12)/(H12-1)<=0.33,"Bottom third","Mid-pack")),IF(D12="n.m.","Bottom third (n.m.)","n/a")) -> Top third
C13: FCF margin | D13: =Energy!Y8 -> 0.013079256 | E13: =IFERROR(MEDIAN(Energy!Y9:Y13),"n/a") -> 0.010371884 | F13: =IFERROR(D13-E13,"n/a") -> 0.0027073719 | G13: =IF(ISNUMBER(D13),1+COUNTIF(Energy!Y9:Y13,">"&D13),"n/a") -> 3 | H13: =IF(ISNUMBER(D13),1+COUNT(Energy!Y9:Y13),"n/a") -> 6 | I13: =IF(ISNUMBER(G13),IF((H13-G13)/(H13-1)>=0.67,"Top third",IF((H13-G13)/(H13-1)<=0.33,"Bottom third","Mid-pack")),IF(D13="n.m.","Bottom third (n.m.)","n/a")) -> Mid-pack
A14: Syngenta AG (global CP + Seeds) | B14: Crop-protection & seeds peers | C14: Revenue growth FY25 | D14: =Agriculture!F8 -> 0.0010600082 | E14: =IFERROR(MEDIAN(Agriculture!F12:F15),"n/a") -> 0.049982705 | F14: =IFERROR(D14-E14,"n/a") -> -0.048922696 | G14: =IF(ISNUMBER(D14),1+COUNTIF(Agriculture!F12:F15,">"&D14),"n/a") -> 4 | H14: =IF(ISNUMBER(D14),1+COUNT(Agriculture!F12:F15),"n/a") -> 5 | I14: =IF(ISNUMBER(G14),IF((H14-G14)/(H14-1)>=0.67,"Top third",IF((H14-G14)/(H14-1)<=0.33,"Bottom third","Mid-pack")),IF(D14="n.m.","Bottom third (n.m.)","n/a")) -> Bottom third
C15: EBITDA margin | D15: =Agriculture!I8 -> 0.12394847 | E15: =IFERROR(MEDIAN(Agriculture!I12:I15),"n/a") -> 0.1675157 | F15: =IFERROR(D15-E15,"n/a") -> -0.043567232 | G15: =IF(ISNUMBER(D15),1+COUNTIF(Agriculture!I12:I15,">"&D15),"n/a") -> 4 | H15: =IF(ISNUMBER(D15),1+COUNT(Agriculture!I12:I15),"n/a") -> 5 | I15: =IF(ISNUMBER(G15),IF((H15-G15)/(H15-1)>=0.67,"Top third",IF((H15-G15)/(H15-1)<=0.33,"Bottom third","Mid-pack")),IF(D15="n.m.","Bottom third (n.m.)","n/a")) -> Bottom third
C16: Net margin | D16: =Agriculture!K8 -> -0.0089417025 | E16: =IFERROR(MEDIAN(Agriculture!K12:K15),"n/a") -> 0.063985222 | F16: =IFERROR(D16-E16,"n/a") -> -0.072926924 | G16: =IF(ISNUMBER(D16),1+COUNTIF(Agriculture!K12:K15,">"&D16),"n/a") -> 4 | H16: =IF(ISNUMBER(D16),1+COUNT(Agriculture!K12:K15),"n/a") -> 5 | I16: =IF(ISNUMBER(G16),IF((H16-G16)/(H16-1)>=0.67,"Top third",IF((H16-G16)/(H16-1)<=0.33,"Bottom third","Mid-pack")),IF(D16="n.m.","Bottom third (n.m.)","n/a")) -> Bottom third
C17: ROE (NI / avg equity) | D17: =Agriculture!M8 -> -0.020753687 | E17: =IFERROR(MEDIAN(Agriculture!M12:M15),"n/a") -> 0.054616975 | F17: =IFERROR(D17-E17,"n/a") -> -0.075370661 | G17: =IF(ISNUMBER(D17),1+COUNTIF(Agriculture!M12:M15,">"&D17),"n/a") -> 4 | H17: =IF(ISNUMBER(D17),1+COUNT(Agriculture!M12:M15),"n/a") -> 5 | I17: =IF(ISNUMBER(G17),IF((H17-G17)/(H17-1)>=0.67,"Top third",IF((H17-G17)/(H17-1)<=0.33,"Bottom third","Mid-pack")),IF(D17="n.m.","Bottom third (n.m.)","n/a")) -> Bottom third
C18: EBITDA / avg assets | D18: =Agriculture!L8 -> 0.069948875 | E18: =IFERROR(MEDIAN(Agriculture!L12:L15),"n/a") -> 0.086919213 | F18: =IFERROR(D18-E18,"n/a") -> -0.016970338 | G18: =IF(ISNUMBER(D18),1+COUNTIF(Agriculture!L12:L15,">"&D18),"n/a") -> 4 | H18: =IF(ISNUMBER(D18),1+COUNT(Agriculture!L12:L15),"n/a") -> 5 | I18: =IF(ISNUMBER(G18),IF((H18-G18)/(H18-1)>=0.67,"Top third",IF((H18-G18)/(H18-1)<=0.33,"Bottom third","Mid-pack")),IF(D18="n.m.","Bottom third (n.m.)","n/a")) -> Bottom third
C19: Net debt / EBITDA (x) | D19: =Agriculture!R8 -> 4.6767916 | E19: =IFERROR(MEDIAN(Agriculture!R12:R15),"n/a") -> 1.3321827 | F19: =IFERROR(D19-E19,"n/a") -> 3.344609 | G19: =IF(ISNUMBER(D19),1+COUNTIF(Agriculture!R12:R15,"<"&D19),"n/a") -> 4 | H19: =IF(ISNUMBER(D19),1+COUNT(Agriculture!R12:R15),"n/a") -> 4 | I19: =IF(ISNUMBER(G19),IF((H19-G19)/(H19-1)>=0.67,"Top third",IF((H19-G19)/(H19-1)<=0.33,"Bottom third","Mid-pack")),IF(D19="n.m.","Bottom third (n.m.)","n/a")) -> Bottom third
C20: Interest cover (EBIT / interest, x) | D20: =Agriculture!S8 -> 1.5878553 | E20: =IFERROR(MEDIAN(Agriculture!S12:S15),"n/a") -> 9.9984965 | F20: =IFERROR(D20-E20,"n/a") -> -8.4106412 | G20: =IF(ISNUMBER(D20),1+COUNTIF(Agriculture!S12:S15,">"&D20),"n/a") -> 4 | H20: =IF(ISNUMBER(D20),1+COUNT(Agriculture!S12:S15),"n/a") -> 5 | I20: =IF(ISNUMBER(G20),IF((H20-G20)/(H20-1)>=0.67,"Top third",IF((H20-G20)/(H20-1)<=0.33,"Bottom third","Mid-pack")),IF(D20="n.m.","Bottom third (n.m.)","n/a")) -> Bottom third
C21: OCF / EBITDA (cash conversion) | D21: =Agriculture!V8 -> 0.72425249 | E21: =IFERROR(MEDIAN(Agriculture!V12:V15),"n/a") -> 0.72113505 | F21: =IFERROR(D21-E21,"n/a") -> 0.0031174422 | G21: =IF(ISNUMBER(D21),1+COUNTIF(Agriculture!V12:V15,">"&D21),"n/a") -> 2 | H21: =IF(ISNUMBER(D21),1+COUNT(Agriculture!V12:V15),"n/a") -> 4 | I21: =IF(ISNUMBER(G21),IF((H21-G21)/(H21-1)>=0.67,"Top third",IF((H21-G21)/(H21-1)<=0.33,"Bottom third","Mid-pack")),IF(D21="n.m.","Bottom third (n.m.)","n/a")) -> Mid-pack
C22: FCF margin | D22: =Agriculture!X8 -> 0.01817754 | E22: =IFERROR(MEDIAN(Agriculture!X12:X15),"n/a") -> -0.0029318466 | F22: =IFERROR(D22-E22,"n/a") -> 0.021109386 | G22: =IF(ISNUMBER(D22),1+COUNTIF(Agriculture!X12:X15,">"&D22),"n/a") -> 3 | H22: =IF(ISNUMBER(D22),1+COUNT(Agriculture!X12:X15),"n/a") -> 5 | I22: =IF(ISNUMBER(G22),IF((H22-G22)/(H22-1)>=0.67,"Top third",IF((H22-G22)/(H22-1)<=0.33,"Bottom third","Mid-pack")),IF(D22="n.m.","Bottom third (n.m.)","n/a")) -> Mid-pack
A23: ADAMA | B23: Crop-protection & seeds peers | C23: Revenue growth FY25 | D23: =Agriculture!F9 -> -0.018429841 | E23: =IFERROR(MEDIAN(Agriculture!F12:F15),"n/a") -> 0.049982705 | F23: =IFERROR(D23-E23,"n/a") -> -0.068412546 | G23: =IF(ISNUMBER(D23),1+COUNTIF(Agriculture!F12:F15,">"&D23),"n/a") -> 4 | H23: =IF(ISNUMBER(D23),1+COUNT(Agriculture!F12:F15),"n/a") -> 5 | I23: =IF(ISNUMBER(G23),IF((H23-G23)/(H23-1)>=0.67,"Top third",IF((H23-G23)/(H23-1)<=0.33,"Bottom third","Mid-pack")),IF(D23="n.m.","Bottom third (n.m.)","n/a")) -> Bottom third
C24: EBITDA margin | D24: =Agriculture!I9 -> 0.11881538 | E24: =IFERROR(MEDIAN(Agriculture!I12:I15),"n/a") -> 0.1675157 | F24: =IFERROR(D24-E24,"n/a") -> -0.048700319 | G24: =IF(ISNUMBER(D24),1+COUNTIF(Agriculture!I12:I15,">"&D24),"n/a") -> 4 | H24: =IF(ISNUMBER(D24),1+COUNT(Agriculture!I12:I15),"n/a") -> 5 | I24: =IF(ISNUMBER(G24),IF((H24-G24)/(H24-1)>=0.67,"Top third",IF((H24-G24)/(H24-1)<=0.33,"Bottom third","Mid-pack")),IF(D24="n.m.","Bottom third (n.m.)","n/a")) -> Bottom third
C25: Net margin | D25: =Agriculture!K9 -> -0.036128311 | E25: =IFERROR(MEDIAN(Agriculture!K12:K15),"n/a") -> 0.063985222 | F25: =IFERROR(D25-E25,"n/a") -> -0.10011353 | G25: =IF(ISNUMBER(D25),1+COUNTIF(Agriculture!K12:K15,">"&D25),"n/a") -> 4 | H25: =IF(ISNUMBER(D25),1+COUNT(Agriculture!K12:K15),"n/a") -> 5 | I25: =IF(ISNUMBER(G25),IF((H25-G25)/(H25-1)>=0.67,"Top third",IF((H25-G25)/(H25-1)<=0.33,"Bottom third","Mid-pack")),IF(D25="n.m.","Bottom third (n.m.)","n/a")) -> Bottom third
C26: ROE (NI / avg equity) | D26: =Agriculture!M9 -> -0.057195435 | E26: =IFERROR(MEDIAN(Agriculture!M12:M15),"n/a") -> 0.054616975 | F26: =IFERROR(D26-E26,"n/a") -> -0.11181241 | G26: =IF(ISNUMBER(D26),1+COUNTIF(Agriculture!M12:M15,">"&D26),"n/a") -> 4 | H26: =IF(ISNUMBER(D26),1+COUNT(Agriculture!M12:M15),"n/a") -> 5 | I26: =IF(ISNUMBER(G26),IF((H26-G26)/(H26-1)>=0.67,"Top third",IF((H26-G26)/(H26-1)<=0.33,"Bottom third","Mid-pack")),IF(D26="n.m.","Bottom third (n.m.)","n/a")) -> Bottom third
C27: EBITDA / avg assets | D27: =Agriculture!L9 -> 0.069811845 | E27: =IFERROR(MEDIAN(Agriculture!L12:L15),"n/a") -> 0.086919213 | F27: =IFERROR(D27-E27,"n/a") -> -0.017107368 | G27: =IF(ISNUMBER(D27),1+COUNTIF(Agriculture!L12:L15,">"&D27),"n/a") -> 4 | H27: =IF(ISNUMBER(D27),1+COUNT(Agriculture!L12:L15),"n/a") -> 5 | I27: =IF(ISNUMBER(G27),IF((H27-G27)/(H27-1)>=0.67,"Top third",IF((H27-G27)/(H27-1)<=0.33,"Bottom third","Mid-pack")),IF(D27="n.m.","Bottom third (n.m.)","n/a")) -> Bottom third
C28: Net debt / EBITDA (x) | D28: =Agriculture!R9 -> 4.1294722 | E28: =IFERROR(MEDIAN(Agriculture!R12:R15),"n/a") -> 1.3321827 | F28: =IFERROR(D28-E28,"n/a") -> 2.7972896 | G28: =IF(ISNUMBER(D28),1+COUNTIF(Agriculture!R12:R15,"<"&D28),"n/a") -> 4 | H28: =IF(ISNUMBER(D28),1+COUNT(Agriculture!R12:R15),"n/a") -> 4 | I28: =IF(ISNUMBER(G28),IF((H28-G28)/(H28-1)>=0.67,"Top third",IF((H28-G28)/(H28-1)<=0.33,"Bottom third","Mid-pack")),IF(D28="n.m.","Bottom third (n.m.)","n/a")) -> Bottom third
C29: Interest cover (EBIT / interest, x) | D29: =Agriculture!S9 -> 1.3074426 | E29: =IFERROR(MEDIAN(Agriculture!S12:S15),"n/a") -> 9.9984965 | F29: =IFERROR(D29-E29,"n/a") -> -8.691054 | G29: =IF(ISNUMBER(D29),1+COUNTIF(Agriculture!S12:S15,">"&D29),"n/a") -> 4 | H29: =IF(ISNUMBER(D29),1+COUNT(Agriculture!S12:S15),"n/a") -> 5 | I29: =IF(ISNUMBER(G29),IF((H29-G29)/(H29-1)>=0.67,"Top third",IF((H29-G29)/(H29-1)<=0.33,"Bottom third","Mid-pack")),IF(D29="n.m.","Bottom third (n.m.)","n/a")) -> Bottom third
C30: OCF / EBITDA (cash conversion) | D30: =Agriculture!V9 -> 1.1772667 | E30: =IFERROR(MEDIAN(Agriculture!V12:V15),"n/a") -> 0.72113505 | F30: =IFERROR(D30-E30,"n/a") -> 0.4561316 | G30: =IF(ISNUMBER(D30),1+COUNTIF(Agriculture!V12:V15,">"&D30),"n/a") -> 1 | H30: =IF(ISNUMBER(D30),1+COUNT(Agriculture!V12:V15),"n/a") -> 4 | I30: =IF(ISNUMBER(G30),IF((H30-G30)/(H30-1)>=0.67,"Top third",IF((H30-G30)/(H30-1)<=0.33,"Bottom third","Mid-pack")),IF(D30="n.m.","Bottom third (n.m.)","n/a")) -> Top third
C31: FCF margin | D31: =Agriculture!X9 -> 0.097946918 | E31: =IFERROR(MEDIAN(Agriculture!X12:X15),"n/a") -> -0.0029318466 | F31: =IFERROR(D31-E31,"n/a") -> 0.10087876 | G31: =IF(ISNUMBER(D31),1+COUNTIF(Agriculture!X12:X15,">"&D31),"n/a") -> 2 | H31: =IF(ISNUMBER(D31),1+COUNT(Agriculture!X12:X15),"n/a") -> 5 | I31: =IF(ISNUMBER(G31),IF((H31-G31)/(H31-1)>=0.67,"Top third",IF((H31-G31)/(H31-1)<=0.33,"Bottom third","Mid-pack")),IF(D31="n.m.","Bottom third (n.m.)","n/a")) -> Top third
A32: Yangnong Chemical | B32: Crop-protection & seeds peers | C32: Revenue growth FY25 | D32: =Agriculture!F10 -> 0.13758373 | E32: =IFERROR(MEDIAN(Agriculture!F12:F15),"n/a") -> 0.049982705 | F32: =IFERROR(D32-E32,"n/a") -> 0.087601026 | G32: =IF(ISNUMBER(D32),1+COUNTIF(Agriculture!F12:F15,">"&D32),"n/a") -> 2 | H32: =IF(ISNUMBER(D32),1+COUNT(Agriculture!F12:F15),"n/a") -> 5 | I32: =IF(ISNUMBER(G32),IF((H32-G32)/(H32-1)>=0.67,"Top third",IF((H32-G32)/(H32-1)<=0.33,"Bottom third","Mid-pack")),IF(D32="n.m.","Bottom third (n.m.)","n/a")) -> Top third
C33: EBITDA margin | D33: =Agriculture!I10 -> 0.25800367 | E33: =IFERROR(MEDIAN(Agriculture!I12:I15),"n/a") -> 0.1675157 | F33: =IFERROR(D33-E33,"n/a") -> 0.090487971 | G33: =IF(ISNUMBER(D33),1+COUNTIF(Agriculture!I12:I15,">"&D33),"n/a") -> 1 | H33: =IF(ISNUMBER(D33),1+COUNT(Agriculture!I12:I15),"n/a") -> 5 | I33: =IF(ISNUMBER(G33),IF((H33-G33)/(H33-1)>=0.67,"Top third",IF((H33-G33)/(H33-1)<=0.33,"Bottom third","Mid-pack")),IF(D33="n.m.","Bottom third (n.m.)","n/a")) -> Top third
C34: Net margin | D34: =Agriculture!K10 -> 0.10838565 | E34: =IFERROR(MEDIAN(Agriculture!K12:K15),"n/a") -> 0.063985222 | F34: =IFERROR(D34-E34,"n/a") -> 0.044400424 | G34: =IF(ISNUMBER(D34),1+COUNTIF(Agriculture!K12:K15,">"&D34),"n/a") -> 1 | H34: =IF(ISNUMBER(D34),1+COUNT(Agriculture!K12:K15),"n/a") -> 5 | I34: =IF(ISNUMBER(G34),IF((H34-G34)/(H34-1)>=0.67,"Top third",IF((H34-G34)/(H34-1)<=0.33,"Bottom third","Mid-pack")),IF(D34="n.m.","Bottom third (n.m.)","n/a")) -> Top third
C35: ROE (NI / avg equity) | D35: =Agriculture!M10 -> 0.1168737 | E35: =IFERROR(MEDIAN(Agriculture!M12:M15),"n/a") -> 0.054616975 | F35: =IFERROR(D35-E35,"n/a") -> 0.062256728 | G35: =IF(ISNUMBER(D35),1+COUNTIF(Agriculture!M12:M15,">"&D35),"n/a") -> 2 | H35: =IF(ISNUMBER(D35),1+COUNT(Agriculture!M12:M15),"n/a") -> 5 | I35: =IF(ISNUMBER(G35),IF((H35-G35)/(H35-1)>=0.67,"Top third",IF((H35-G35)/(H35-1)<=0.33,"Bottom third","Mid-pack")),IF(D35="n.m.","Bottom third (n.m.)","n/a")) -> Top third
C36: EBITDA / avg assets | D36: =Agriculture!L10 -> 0.17085077 | E36: =IFERROR(MEDIAN(Agriculture!L12:L15),"n/a") -> 0.086919213 | F36: =IFERROR(D36-E36,"n/a") -> 0.083931556 | G36: =IF(ISNUMBER(D36),1+COUNTIF(Agriculture!L12:L15,">"&D36),"n/a") -> 1 | H36: =IF(ISNUMBER(D36),1+COUNT(Agriculture!L12:L15),"n/a") -> 5 | I36: =IF(ISNUMBER(G36),IF((H36-G36)/(H36-1)>=0.67,"Top third",IF((H36-G36)/(H36-1)<=0.33,"Bottom third","Mid-pack")),IF(D36="n.m.","Bottom third (n.m.)","n/a")) -> Top third
C37: Net debt / EBITDA (x) | D37: =Agriculture!R10 -> -0.13738427 | E37: =IFERROR(MEDIAN(Agriculture!R12:R15),"n/a") -> 1.3321827 | F37: =IFERROR(D37-E37,"n/a") -> -1.4695669 | G37: =IF(ISNUMBER(D37),1+COUNTIF(Agriculture!R12:R15,"<"&D37),"n/a") -> 2 | H37: =IF(ISNUMBER(D37),1+COUNT(Agriculture!R12:R15),"n/a") -> 4 | I37: =IF(ISNUMBER(G37),IF((H37-G37)/(H37-1)>=0.67,"Top third",IF((H37-G37)/(H37-1)<=0.33,"Bottom third","Mid-pack")),IF(D37="n.m.","Bottom third (n.m.)","n/a")) -> Mid-pack
C38: Interest cover (EBIT / interest, x) | D38: =Agriculture!S10 -> 35.282383 | E38: =IFERROR(MEDIAN(Agriculture!S12:S15),"n/a") -> 9.9984965 | F38: =IFERROR(D38-E38,"n/a") -> 25.283887 | G38: =IF(ISNUMBER(D38),1+COUNTIF(Agriculture!S12:S15,">"&D38),"n/a") -> 1 | H38: =IF(ISNUMBER(D38),1+COUNT(Agriculture!S12:S15),"n/a") -> 5 | I38: =IF(ISNUMBER(G38),IF((H38-G38)/(H38-1)>=0.67,"Top third",IF((H38-G38)/(H38-1)<=0.33,"Bottom third","Mid-pack")),IF(D38="n.m.","Bottom third (n.m.)","n/a")) -> Top third
C39: OCF / EBITDA (cash conversion) | D39: =Agriculture!V10 -> 0.72380293 | E39: =IFERROR(MEDIAN(Agriculture!V12:V15),"n/a") -> 0.72113505 | F39: =IFERROR(D39-E39,"n/a") -> 0.0026678849 | G39: =IF(ISNUMBER(D39),1+COUNTIF(Agriculture!V12:V15,">"&D39),"n/a") -> 2 | H39: =IF(ISNUMBER(D39),1+COUNT(Agriculture!V12:V15),"n/a") -> 4 | I39: =IF(ISNUMBER(G39),IF((H39-G39)/(H39-1)>=0.67,"Top third",IF((H39-G39)/(H39-1)<=0.33,"Bottom third","Mid-pack")),IF(D39="n.m.","Bottom third (n.m.)","n/a")) -> Mid-pack
C40: FCF margin | D40: =Agriculture!X10 -> 0.1057587 | E40: =IFERROR(MEDIAN(Agriculture!X12:X15),"n/a") -> -0.0029318466 | F40: =IFERROR(D40-E40,"n/a") -> 0.10869054 | G40: =IF(ISNUMBER(D40),1+COUNTIF(Agriculture!X12:X15,">"&D40),"n/a") -> 2 | H40: =IF(ISNUMBER(D40),1+COUNT(Agriculture!X12:X15),"n/a") -> 5 | I40: =IF(ISNUMBER(G40),IF((H40-G40)/(H40-1)>=0.67,"Top third",IF((H40-G40)/(H40-1)<=0.33,"Bottom third","Mid-pack")),IF(D40="n.m.","Bottom third (n.m.)","n/a")) -> Top third
A41: Sinofert | B41: Crop-nutrition peers | C41: Revenue growth FY25 | D41: =Agriculture!F11 -> 0.093969655 | E41: =IFERROR(MEDIAN(Agriculture!F16:F19),"n/a") -> 0.029705638 | F41: =IFERROR(D41-E41,"n/a") -> 0.064264017 | G41: =IF(ISNUMBER(D41),1+COUNTIF(Agriculture!F16:F19,">"&D41),"n/a") -> 1 | H41: =IF(ISNUMBER(D41),1+COUNT(Agriculture!F16:F19),"n/a") -> 5 | I41: =IF(ISNUMBER(G41),IF((H41-G41)/(H41-1)>=0.67,"Top third",IF((H41-G41)/(H41-1)<=0.33,"Bottom third","Mid-pack")),IF(D41="n.m.","Bottom third (n.m.)","n/a")) -> Top third
C42: EBITDA margin | D42: =Agriculture!I11 -> 0.085335083 | E42: =IFERROR(MEDIAN(Agriculture!I16:I19),"n/a") -> 0.2180772 | F42: =IFERROR(D42-E42,"n/a") -> -0.13274212 | G42: =IF(ISNUMBER(D42),1+COUNTIF(Agriculture!I16:I19,">"&D42),"n/a") -> 5 | H42: =IF(ISNUMBER(D42),1+COUNT(Agriculture!I16:I19),"n/a") -> 5 | I42: =IF(ISNUMBER(G42),IF((H42-G42)/(H42-1)>=0.67,"Top third",IF((H42-G42)/(H42-1)<=0.33,"Bottom third","Mid-pack")),IF(D42="n.m.","Bottom third (n.m.)","n/a")) -> Bottom third
C43: Net margin | D43: =Agriculture!K11 -> 0.054734912 | E43: =IFERROR(MEDIAN(Agriculture!K16:K19),"n/a") -> 0.099496016 | F43: =IFERROR(D43-E43,"n/a") -> -0.044761105 | G43: =IF(ISNUMBER(D43),1+COUNTIF(Agriculture!K16:K19,">"&D43),"n/a") -> 4 | H43: =IF(ISNUMBER(D43),1+COUNT(Agriculture!K16:K19),"n/a") -> 5 | I43: =IF(ISNUMBER(G43),IF((H43-G43)/(H43-1)>=0.67,"Top third",IF((H43-G43)/(H43-1)<=0.33,"Bottom third","Mid-pack")),IF(D43="n.m.","Bottom third (n.m.)","n/a")) -> Bottom third
C44: ROE (NI / avg equity) | D44: =Agriculture!M11 -> 0.11528546 | E44: =IFERROR(MEDIAN(Agriculture!M16:M19),"n/a") -> 0.14545728 | F44: =IFERROR(D44-E44,"n/a") -> -0.030171818 | G44: =IF(ISNUMBER(D44),1+COUNTIF(Agriculture!M16:M19,">"&D44),"n/a") -> 3 | H44: =IF(ISNUMBER(D44),1+COUNT(Agriculture!M16:M19),"n/a") -> 5 | I44: =IF(ISNUMBER(G44),IF((H44-G44)/(H44-1)>=0.67,"Top third",IF((H44-G44)/(H44-1)<=0.33,"Bottom third","Mid-pack")),IF(D44="n.m.","Bottom third (n.m.)","n/a")) -> Mid-pack
C45: EBITDA / avg assets | D45: =Agriculture!L11 -> 0.088218377 | E45: =IFERROR(MEDIAN(Agriculture!L16:L19),"n/a") -> 0.13345425 | F45: =IFERROR(D45-E45,"n/a") -> -0.045235869 | G45: =IF(ISNUMBER(D45),1+COUNTIF(Agriculture!L16:L19,">"&D45),"n/a") -> 4 | H45: =IF(ISNUMBER(D45),1+COUNT(Agriculture!L16:L19),"n/a") -> 5 | I45: =IF(ISNUMBER(G45),IF((H45-G45)/(H45-1)>=0.67,"Top third",IF((H45-G45)/(H45-1)<=0.33,"Bottom third","Mid-pack")),IF(D45="n.m.","Bottom third (n.m.)","n/a")) -> Bottom third
C46: Net debt / EBITDA (x) | D46: =Agriculture!R11 -> -0.71581974 | E46: =IFERROR(MEDIAN(Agriculture!R16:R19),"n/a") -> 1.2470565 | F46: =IFERROR(D46-E46,"n/a") -> -1.9628762 | G46: =IF(ISNUMBER(D46),1+COUNTIF(Agriculture!R16:R19,"<"&D46),"n/a") -> 2 | H46: =IF(ISNUMBER(D46),1+COUNT(Agriculture!R16:R19),"n/a") -> 5 | I46: =IF(ISNUMBER(G46),IF((H46-G46)/(H46-1)>=0.67,"Top third",IF((H46-G46)/(H46-1)<=0.33,"Bottom third","Mid-pack")),IF(D46="n.m.","Bottom third (n.m.)","n/a")) -> Top third
C47: Interest cover (EBIT / interest, x) | D47: =Agriculture!S11 -> 33.228157 | E47: =IFERROR(MEDIAN(Agriculture!S16:S19),"n/a") -> 11.999889 | F47: =IFERROR(D47-E47,"n/a") -> 21.228268 | G47: =IF(ISNUMBER(D47),1+COUNTIF(Agriculture!S16:S19,">"&D47),"n/a") -> 2 | H47: =IF(ISNUMBER(D47),1+COUNT(Agriculture!S16:S19),"n/a") -> 5 | I47: =IF(ISNUMBER(G47),IF((H47-G47)/(H47-1)>=0.67,"Top third",IF((H47-G47)/(H47-1)<=0.33,"Bottom third","Mid-pack")),IF(D47="n.m.","Bottom third (n.m.)","n/a")) -> Top third
C48: OCF / EBITDA (cash conversion) | D48: =Agriculture!V11 -> 1.0043452 | E48: =IFERROR(MEDIAN(Agriculture!V16:V19),"n/a") -> 0.77704017 | F48: =IFERROR(D48-E48,"n/a") -> 0.22730507 | G48: =IF(ISNUMBER(D48),1+COUNTIF(Agriculture!V16:V19,">"&D48),"n/a") -> 2 | H48: =IF(ISNUMBER(D48),1+COUNT(Agriculture!V16:V19),"n/a") -> 5 | I48: =IF(ISNUMBER(G48),IF((H48-G48)/(H48-1)>=0.67,"Top third",IF((H48-G48)/(H48-1)<=0.33,"Bottom third","Mid-pack")),IF(D48="n.m.","Bottom third (n.m.)","n/a")) -> Top third
C49: FCF margin | D49: =Agriculture!X11 -> 0.070954415 | E49: =IFERROR(MEDIAN(Agriculture!X16:X19),"n/a") -> 0.10749408 | F49: =IFERROR(D49-E49,"n/a") -> -0.036539667 | G49: =IF(ISNUMBER(D49),1+COUNTIF(Agriculture!X16:X19,">"&D49),"n/a") -> 4 | H49: =IF(ISNUMBER(D49),1+COUNT(Agriculture!X16:X19),"n/a") -> 5 | I49: =IF(ISNUMBER(G49),IF((H49-G49)/(H49-1)>=0.67,"Top third",IF((H49-G49)/(H49-1)<=0.33,"Bottom third","Mid-pack")),IF(D49="n.m.","Bottom third (n.m.)","n/a")) -> Bottom third
A50: Pirelli | B50: All listed peers | C50: Revenue growth FY25 | D50: =Rubber!F8 -> 0.00041825845 | E50: =IFERROR(MEDIAN(Rubber!F10:F16),"n/a") -> 0.0055467355 | F50: =IFERROR(D50-E50,"n/a") -> -0.0051284771 | G50: =IF(ISNUMBER(D50),1+COUNTIF(Rubber!F10:F16,">"&D50),"n/a") -> 5 | H50: =IF(ISNUMBER(D50),1+COUNT(Rubber!F10:F16),"n/a") -> 8 | I50: =IF(ISNUMBER(G50),IF((H50-G50)/(H50-1)>=0.67,"Top third",IF((H50-G50)/(H50-1)<=0.33,"Bottom third","Mid-pack")),IF(D50="n.m.","Bottom third (n.m.)","n/a")) -> Mid-pack
C51: EBITDA margin | D51: =Rubber!I8 -> 0.21617017 | E51: =IFERROR(MEDIAN(Rubber!I10:I16),"n/a") -> 0.15497383 | F51: =IFERROR(D51-E51,"n/a") -> 0.061196342 | G51: =IF(ISNUMBER(D51),1+COUNTIF(Rubber!I10:I16,">"&D51),"n/a") -> 1 | H51: =IF(ISNUMBER(D51),1+COUNT(Rubber!I10:I16),"n/a") -> 8 | I51: =IF(ISNUMBER(G51),IF((H51-G51)/(H51-1)>=0.67,"Top third",IF((H51-G51)/(H51-1)<=0.33,"Bottom third","Mid-pack")),IF(D51="n.m.","Bottom third (n.m.)","n/a")) -> Top third
C52: Net margin | D52: =Rubber!K8 -> 0.078318138 | E52: =IFERROR(MEDIAN(Rubber!K10:K16),"n/a") -> 0.064019698 | F52: =IFERROR(D52-E52,"n/a") -> 0.01429844 | G52: =IF(ISNUMBER(D52),1+COUNTIF(Rubber!K10:K16,">"&D52),"n/a") -> 3 | H52: =IF(ISNUMBER(D52),1+COUNT(Rubber!K10:K16),"n/a") -> 8 | I52: =IF(ISNUMBER(G52),IF((H52-G52)/(H52-1)>=0.67,"Top third",IF((H52-G52)/(H52-1)<=0.33,"Bottom third","Mid-pack")),IF(D52="n.m.","Bottom third (n.m.)","n/a")) -> Top third
C53: ROE (NI / avg equity) | D53: =Rubber!M8 -> 0.085810718 | E53: =IFERROR(MEDIAN(Rubber!M10:M16),"n/a") -> 0.089070678 | F53: =IFERROR(D53-E53,"n/a") -> -0.0032599599 | G53: =IF(ISNUMBER(D53),1+COUNTIF(Rubber!M10:M16,">"&D53),"n/a") -> 5 | H53: =IF(ISNUMBER(D53),1+COUNT(Rubber!M10:M16),"n/a") -> 8 | I53: =IF(ISNUMBER(G53),IF((H53-G53)/(H53-1)>=0.67,"Top third",IF((H53-G53)/(H53-1)<=0.33,"Bottom third","Mid-pack")),IF(D53="n.m.","Bottom third (n.m.)","n/a")) -> Mid-pack
C54: EBITDA / avg assets | D54: =Rubber!L8 -> 0.10836824 | E54: =IFERROR(MEDIAN(Rubber!L10:L16),"n/a") -> 0.11908249 | F54: =IFERROR(D54-E54,"n/a") -> -0.010714248 | G54: =IF(ISNUMBER(D54),1+COUNTIF(Rubber!L10:L16,">"&D54),"n/a") -> 5 | H54: =IF(ISNUMBER(D54),1+COUNT(Rubber!L10:L16),"n/a") -> 8 | I54: =IF(ISNUMBER(G54),IF((H54-G54)/(H54-1)>=0.67,"Top third",IF((H54-G54)/(H54-1)<=0.33,"Bottom third","Mid-pack")),IF(D54="n.m.","Bottom third (n.m.)","n/a")) -> Mid-pack
C55: Net debt / EBITDA (x) | D55: =Rubber!R8 -> 0.97754306 | E55: =IFERROR(MEDIAN(Rubber!R10:R16),"n/a") -> 1.121725 | F55: =IFERROR(D55-E55,"n/a") -> -0.14418195 | G55: =IF(ISNUMBER(D55),1+COUNTIF(Rubber!R10:R16,"<"&D55),"n/a") -> 3 | H55: =IF(ISNUMBER(D55),1+COUNT(Rubber!R10:R16),"n/a") -> 8 | I55: =IF(ISNUMBER(G55),IF((H55-G55)/(H55-1)>=0.67,"Top third",IF((H55-G55)/(H55-1)<=0.33,"Bottom third","Mid-pack")),IF(D55="n.m.","Bottom third (n.m.)","n/a")) -> Top third
C56: Interest cover (EBIT / interest, x) | D56: =Rubber!S8 -> 3.066716 | E56: =IFERROR(MEDIAN(Rubber!S10:S16),"n/a") -> 8.6607374 | F56: =IFERROR(D56-E56,"n/a") -> -5.5940214 | G56: =IF(ISNUMBER(D56),1+COUNTIF(Rubber!S10:S16,">"&D56),"n/a") -> 6 | H56: =IF(ISNUMBER(D56),1+COUNT(Rubber!S10:S16),"n/a") -> 8 | I56: =IF(ISNUMBER(G56),IF((H56-G56)/(H56-1)>=0.67,"Top third",IF((H56-G56)/(H56-1)<=0.33,"Bottom third","Mid-pack")),IF(D56="n.m.","Bottom third (n.m.)","n/a")) -> Bottom third
C57: OCF / EBITDA (cash conversion) | D57: =Rubber!V8 -> 0.89145435 | E57: =IFERROR(MEDIAN(Rubber!V10:V16),"n/a") -> 0.88628452 | F57: =IFERROR(D57-E57,"n/a") -> 0.005169825 | G57: =IF(ISNUMBER(D57),1+COUNTIF(Rubber!V10:V16,">"&D57),"n/a") -> 4 | H57: =IF(ISNUMBER(D57),1+COUNT(Rubber!V10:V16),"n/a") -> 8 | I57: =IF(ISNUMBER(G57),IF((H57-G57)/(H57-1)>=0.67,"Top third",IF((H57-G57)/(H57-1)<=0.33,"Bottom third","Mid-pack")),IF(D57="n.m.","Bottom third (n.m.)","n/a")) -> Mid-pack
C58: FCF margin | D58: =Rubber!X8 -> 0.13694178 | E58: =IFERROR(MEDIAN(Rubber!X10:X16),"n/a") -> 0.0090795214 | F58: =IFERROR(D58-E58,"n/a") -> 0.12786226 | G58: =IF(ISNUMBER(D58),1+COUNTIF(Rubber!X10:X16,">"&D58),"n/a") -> 1 | H58: =IF(ISNUMBER(D58),1+COUNT(Rubber!X10:X16),"n/a") -> 8 | I58: =IF(ISNUMBER(G58),IF((H58-G58)/(H58-1)>=0.67,"Top third",IF((H58-G58)/(H58-1)<=0.33,"Bottom third","Mid-pack")),IF(D58="n.m.","Bottom third (n.m.)","n/a")) -> Top third
A59: Aeolus Tyre (风神股份) | B59: All listed peers | C59: Revenue growth FY25 | D59: =Rubber!F9 -> 0.10514553 | E59: =IFERROR(MEDIAN(Rubber!F10:F16),"n/a") -> 0.0055467355 | F59: =IFERROR(D59-E59,"n/a") -> 0.099598796 | G59: =IF(ISNUMBER(D59),1+COUNTIF(Rubber!F10:F16,">"&D59),"n/a") -> 4 | H59: =IF(ISNUMBER(D59),1+COUNT(Rubber!F10:F16),"n/a") -> 8 | I59: =IF(ISNUMBER(G59),IF((H59-G59)/(H59-1)>=0.67,"Top third",IF((H59-G59)/(H59-1)<=0.33,"Bottom third","Mid-pack")),IF(D59="n.m.","Bottom third (n.m.)","n/a")) -> Mid-pack
C60: EBITDA margin | D60: =Rubber!I9 -> 0.080669785 | E60: =IFERROR(MEDIAN(Rubber!I10:I16),"n/a") -> 0.15497383 | F60: =IFERROR(D60-E60,"n/a") -> -0.074304042 | G60: =IF(ISNUMBER(D60),1+COUNTIF(Rubber!I10:I16,">"&D60),"n/a") -> 6 | H60: =IF(ISNUMBER(D60),1+COUNT(Rubber!I10:I16),"n/a") -> 8 | I60: =IF(ISNUMBER(G60),IF((H60-G60)/(H60-1)>=0.67,"Top third",IF((H60-G60)/(H60-1)<=0.33,"Bottom third","Mid-pack")),IF(D60="n.m.","Bottom third (n.m.)","n/a")) -> Bottom third
C61: Net margin | D61: =Rubber!K9 -> 0.031781017 | E61: =IFERROR(MEDIAN(Rubber!K10:K16),"n/a") -> 0.064019698 | F61: =IFERROR(D61-E61,"n/a") -> -0.032238681 | G61: =IF(ISNUMBER(D61),1+COUNTIF(Rubber!K10:K16,">"&D61),"n/a") -> 6 | H61: =IF(ISNUMBER(D61),1+COUNT(Rubber!K10:K16),"n/a") -> 8 | I61: =IF(ISNUMBER(G61),IF((H61-G61)/(H61-1)>=0.67,"Top third",IF((H61-G61)/(H61-1)<=0.33,"Bottom third","Mid-pack")),IF(D61="n.m.","Bottom third (n.m.)","n/a")) -> Bottom third
C62: ROE (NI / avg equity) | D62: =Rubber!M9 -> 0.069263937 | E62: =IFERROR(MEDIAN(Rubber!M10:M16),"n/a") -> 0.089070678 | F62: =IFERROR(D62-E62,"n/a") -> -0.019806741 | G62: =IF(ISNUMBER(D62),1+COUNTIF(Rubber!M10:M16,">"&D62),"n/a") -> 5 | H62: =IF(ISNUMBER(D62),1+COUNT(Rubber!M10:M16),"n/a") -> 8 | I62: =IF(ISNUMBER(G62),IF((H62-G62)/(H62-1)>=0.67,"Top third",IF((H62-G62)/(H62-1)<=0.33,"Bottom third","Mid-pack")),IF(D62="n.m.","Bottom third (n.m.)","n/a")) -> Mid-pack
C63: EBITDA / avg assets | D63: =Rubber!L9 -> 0.078206033 | E63: =IFERROR(MEDIAN(Rubber!L10:L16),"n/a") -> 0.11908249 | F63: =IFERROR(D63-E63,"n/a") -> -0.040876459 | G63: =IF(ISNUMBER(D63),1+COUNTIF(Rubber!L10:L16,">"&D63),"n/a") -> 5 | H63: =IF(ISNUMBER(D63),1+COUNT(Rubber!L10:L16),"n/a") -> 8 | I63: =IF(ISNUMBER(G63),IF((H63-G63)/(H63-1)>=0.67,"Top third",IF((H63-G63)/(H63-1)<=0.33,"Bottom third","Mid-pack")),IF(D63="n.m.","Bottom third (n.m.)","n/a")) -> Mid-pack
C64: Net debt / EBITDA (x) | D64: =Rubber!R9 -> 0.40205236 | E64: =IFERROR(MEDIAN(Rubber!R10:R16),"n/a") -> 1.121725 | F64: =IFERROR(D64-E64,"n/a") -> -0.71967265 | G64: =IF(ISNUMBER(D64),1+COUNTIF(Rubber!R10:R16,"<"&D64),"n/a") -> 2 | H64: =IF(ISNUMBER(D64),1+COUNT(Rubber!R10:R16),"n/a") -> 8 | I64: =IF(ISNUMBER(G64),IF((H64-G64)/(H64-1)>=0.67,"Top third",IF((H64-G64)/(H64-1)<=0.33,"Bottom third","Mid-pack")),IF(D64="n.m.","Bottom third (n.m.)","n/a")) -> Top third
C65: Interest cover (EBIT / interest, x) | D65: =Rubber!S9 -> 9.8337234 | E65: =IFERROR(MEDIAN(Rubber!S10:S16),"n/a") -> 8.6607374 | F65: =IFERROR(D65-E65,"n/a") -> 1.172986 | G65: =IF(ISNUMBER(D65),1+COUNTIF(Rubber!S10:S16,">"&D65),"n/a") -> 2 | H65: =IF(ISNUMBER(D65),1+COUNT(Rubber!S10:S16),"n/a") -> 8 | I65: =IF(ISNUMBER(G65),IF((H65-G65)/(H65-1)>=0.67,"Top third",IF((H65-G65)/(H65-1)<=0.33,"Bottom third","Mid-pack")),IF(D65="n.m.","Bottom third (n.m.)","n/a")) -> Top third
C66: OCF / EBITDA (cash conversion) | D66: =Rubber!V9 -> 0.8292032 | E66: =IFERROR(MEDIAN(Rubber!V10:V16),"n/a") -> 0.88628452 | F66: =IFERROR(D66-E66,"n/a") -> -0.057081318 | G66: =IF(ISNUMBER(D66),1+COUNTIF(Rubber!V10:V16,">"&D66),"n/a") -> 5 | H66: =IF(ISNUMBER(D66),1+COUNT(Rubber!V10:V16),"n/a") -> 8 | I66: =IF(ISNUMBER(G66),IF((H66-G66)/(H66-1)>=0.67,"Top third",IF((H66-G66)/(H66-1)<=0.33,"Bottom third","Mid-pack")),IF(D66="n.m.","Bottom third (n.m.)","n/a")) -> Mid-pack
C67: FCF margin | D67: =Rubber!X9 -> 0.012007718 | E67: =IFERROR(MEDIAN(Rubber!X10:X16),"n/a") -> 0.0090795214 | F67: =IFERROR(D67-E67,"n/a") -> 0.0029281965 | G67: =IF(ISNUMBER(D67),1+COUNTIF(Rubber!X10:X16,">"&D67),"n/a") -> 4 | H67: =IF(ISNUMBER(D67),1+COUNT(Rubber!X10:X16),"n/a") -> 8 | I67: =IF(ISNUMBER(G67),IF((H67-G67)/(H67-1)>=0.67,"Top third",IF((H67-G67)/(H67-1)<=0.33,"Bottom third","Mid-pack")),IF(D67="n.m.","Bottom third (n.m.)","n/a")) -> Mid-pack

Sheet Energy
A1: Energy - Sinochem Energy vs listed refining / petrochemical peers
A2: Sinochem Energy (中化能源) is the operating arm of Sinochem Corp's petrochemical segment: crude/product trading, 15 mt/y of refining capacity centred on Quanzhou, and fuel retail. FY2025 audited statements.
A3: FY2025, ratios computed from the 'Data' sheet. Amber rows = Sinochem Holdings group entities. Peer statistics exclude Sinochem entities. 'n.m.' = not meaningful (negative EBITDA); 'n/a' = not available.
D5: Scale | F5: Growth | H5: Profitability | M5: Returns | Q5: Leverage & liquidity | V5: Cash generation
A6: Entity | B6: Group | C6: Ccy | D6: Revenue (USD bn) | E6: Total assets (USD bn) | F6: Revenue growth FY25 | G6: EBITDA growth FY25 | H6: Gross margin | I6: Gross margin after taxes & surcharges | J6: EBITDA margin | K6: EBIT margin | L6: Net margin | M6: EBITDA / avg assets | N6: ROE (NI / avg equity) | O6: ROA (NI / avg assets) | P6: Asset turnover (x) | Q6: Liabilities / assets | R6: Debt / equity | S6: Net debt / EBITDA (x) | T6: Interest cover (EBIT / interest, x) | U6: Current ratio (x) | V6: OCF / revenue | W6: OCF / EBITDA (cash conversion) | X6: Capex / revenue | Y6: FCF margin | Z6: Free cash flow (USD bn)
A7: Direction (+1 higher is better, -1 lower is better, 0 informational) | D7: 0 | E7: 0 | F7: 1 | G7: 1 | H7: 1 | I7: 1 | J7: 1 | K7: 1 | L7: 1 | M7: 1 | N7: 1 | O7: 1 | P7: 1 | Q7: -1 | R7: -1 | S7: -1 | T7: 1 | U7: 1 | V7: 1 | W7: 1 | X7: 0 | Y7: 1 | Z7: 1
A8: Sinochem Energy (中化能源) | B8: Sinochem | C8: CNY | D8: =Data!$I$5/Data!$H$5/1000 -> 55.282696 | E8: =Data!$S$5/Data!$H$5/1000 -> 14.789913 | F8: =IFERROR(Data!$I$5/Data!$AD$5-1,"n/a") -> -0.076815097 | G8: =IFERROR(IF(Data!$AI$5<=0,"n.m.",Data!$N$5/Data!$AI$5-1),"n/a") -> 0.56502699 | H8: =IF(Data!$K$5="","n/a",Data!$K$5/Data!$I$5) -> 0.015979637 | I8: =IF(OR(Data!$K$5="",Data!$AC$5=""),"n/a",(Data!$K$5-Data!$AC$5)/Data!$I$5) -> 0.006840394 | J8: =IFERROR(Data!$N$5/Data!$I$5,"n/a") -> 0.012682565 | K8: =IFERROR(Data!$L$5/Data!$I$5,"n/a") -> -0.0010559733 | L8: =IFERROR(Data!$Q$5/Data!$I$5,"n/a") -> -0.0042697433 | M8: =IFERROR(Data!$N$5/AVERAGE(Data!$S$5,Data!$AN$5),"n/a") -> 0.048118216 | N8: =IFERROR(Data!$Q$5/AVERAGE(Data!$U$5,Data!$AP$5),"n/a") -> -0.045469204 | O8: =IFERROR(Data!$Q$5/AVERAGE(Data!$S$5,Data!$AN$5),"n/a") -> -0.016199596 | P8: =IFERROR(Data!$I$5/AVERAGE(Data!$S$5,Data!$AN$5),"n/a") -> 3.7940445 | Q8: =IFERROR(Data!$T$5/Data!$S$5,"n/a") -> 0.64970448 | R8: =IFERROR(Data!$Z$5/Data!$U$5,"n/a") -> 0.76157551 | S8: =IFERROR(IF(Data!$N$5<=0,"n.m.",(Data!$Z$5-Data!$W$5)/Data!$N$5),"n/a") -> 4.4530793 | T8: =IFERROR(IF(Data!$O$5<=0,"n/a",Data!$L$5/Data!$O$5),"n/a") -> -0.38309722 | U8: =IFERROR(Data!$X$5/Data!$Y$5,"n/a") -> 0.91231947 | V8: =IFERROR(Data!$AA$5/Data!$I$5,"n/a") -> 0.016953653 | W8: =IFERROR(IF(Data!$N$5<=0,"n.m.",Data!$AA$5/Data!$N$5),"n/a") -> 1.3367685 | X8: =IFERROR(Data!$AB$5/Data!$I$5,"n/a") -> 0.0038743972 | Y8: =IFERROR((Data!$AA$5-Data!$AB$5)/Data!$I$5,"n/a") -> 0.013079256 | Z8: =(Data!$AA$5-Data!$AB$5)/Data!$H$5/1000 -> 0.72305653
A9: Sinopec Corp | B9: State-owned major | C9: CNY | D9: =Data!$I$6/Data!$H$6/1000 -> 390.45911 | E9: =Data!$S$6/Data!$H$6/1000 -> 302.37298 | F9: =IFERROR(Data!$I$6/Data!$AD$6-1,"n/a") -> -0.094640798 | G9: =IFERROR(IF(Data!$AI$6<=0,"n.m.",Data!$N$6/Data!$AI$6-1),"n/a") -> -0.11455848 | H9: =IF(Data!$K$6="","n/a",Data!$K$6/Data!$I$6) -> 0.15886 | I9: =IF(OR(Data!$K$6="",Data!$AC$6=""),"n/a",(Data!$K$6-Data!$AC$6)/Data!$I$6) -> 0.068172927 | J9: =IFERROR(Data!$N$6/Data!$I$6,"n/a") -> 0.06160657 | K9: =IFERROR(Data!$L$6/Data!$I$6,"n/a") -> 0.019803254 | L9: =IFERROR(Data!$Q$6/Data!$I$6,"n/a") -> 0.012663535 | M9: =IFERROR(Data!$N$6/AVERAGE(Data!$S$6,Data!$AN$6),"n/a") -> 0.080882693 | N9: =IFERROR(Data!$Q$6/AVERAGE(Data!$U$6,Data!$AP$6),"n/a") -> 0.035858428 | O9: =IFERROR(Data!$Q$6/AVERAGE(Data!$S$6,Data!$AN$6),"n/a") -> 0.016625837 | P9: =IFERROR(Data!$I$6/AVERAGE(Data!$S$6,Data!$AN$6),"n/a") -> 1.3128907 | Q9: =IFERROR(Data!$T$6/Data!$S$6,"n/a") -> 0.54084051 | R9: =IFERROR(Data!$Z$6/Data!$U$6,"n/a") -> 0.53818758 | S9: =IFERROR(IF(Data!$N$6<=0,"n.m.",(Data!$Z$6-Data!$W$6)/Data!$N$6),"n/a") -> 2.2180399 | T9: =IFERROR(IF(Data!$O$6<=0,"n/a",Data!$L$6/Data!$O$6),"n/a") -> 2.8640308 | U9: =IFERROR(Data!$X$6/Data!$Y$6,"n/a") -> 0.74831974 | V9: =IFERROR(Data!$AA$6/Data!$I$6,"n/a") -> 0.05837656 | W9: =IFERROR(IF(Data!$N$6<=0,"n.m.",Data!$AA$6/Data!$N$6),"n/a") -> 0.94757037 | X9: =IFERROR(Data!$AB$6/Data!$I$6,"n/a") -> 0.048004676 | Y9: =IFERROR((Data!$AA$6-Data!$AB$6)/Data!$I$6,"n/a") -> 0.010371884 | Z9: =(Data!$AA$6-Data!$AB$6)/Data!$H$6/1000 -> 4.0497966
A10: PetroChina | B10: State-owned major | C10: CNY | D10: =Data!$I$7/Data!$H$7/1000 -> 401.80516 | E10: =Data!$S$7/Data!$H$7/1000 -> 401.66335 | F10: =IFERROR(Data!$I$7/Data!$AD$7-1,"n/a") -> -0.025021265 | G10: =IFERROR(IF(Data!$AI$7<=0,"n.m.",Data!$N$7/Data!$AI$7-1),"n/a") -> -0.029907707 | H10: =IF(Data!$K$7="","n/a",Data!$K$7/Data!$I$7) -> 0.21586828 | I10: =IF(OR(Data!$K$7="",Data!$AC$7=""),"n/a",(Data!$K$7-Data!$AC$7)/Data!$I$7) -> 0.13059035 | J10: =IFERROR(Data!$N$7/Data!$I$7,"n/a") -> 0.16905053 | K10: =IFERROR(Data!$L$7/Data!$I$7,"n/a") -> 0.086100426 | L10: =IFERROR(Data!$Q$7/Data!$I$7,"n/a") -> 0.060047778 | M10: =IFERROR(Data!$N$7/AVERAGE(Data!$S$7,Data!$AN$7),"n/a") -> 0.17243586 | N10: =IFERROR(Data!$Q$7/AVERAGE(Data!$U$7,Data!$AP$7),"n/a") -> 0.097160483 | O10: =IFERROR(Data!$Q$7/AVERAGE(Data!$S$7,Data!$AN$7),"n/a") -> 0.06125027 | P10: =IFERROR(Data!$I$7/AVERAGE(Data!$S$7,Data!$AN$7),"n/a") -> 1.0200256 | Q10: =IFERROR(Data!$T$7/Data!$S$7,"n/a") -> 0.36064227 | R10: =IFERROR(Data!$Z$7/Data!$U$7,"n/a") -> 0.19467559 | S10: =IFERROR(IF(Data!$N$7<=0,"n.m.",(Data!$Z$7-Data!$W$7)/Data!$N$7),"n/a") -> 0.24264414 | T10: =IFERROR(IF(Data!$O$7<=0,"n/a",Data!$L$7/Data!$O$7),"n/a") -> 14.039506 | U10: =IFERROR(Data!$X$7/Data!$Y$7,"n/a") -> 1.109287 | V10: =IFERROR(Data!$AA$7/Data!$I$7,"n/a") -> 0.14400924 | W10: =IFERROR(IF(Data!$N$7<=0,"n.m.",Data!$AA$7/Data!$N$7),"n/a") -> 0.85187097 | X10: =IFERROR(Data!$AB$7/Data!$I$7,"n/a") -> 0.10221406 | Y10: =IFERROR((Data!$AA$7-Data!$AB$7)/Data!$I$7,"n/a") -> 0.041795181 | Z10: =(Data!$AA$7-Data!$AB$7)/Data!$H$7/1000 -> 16.793519
A11: Hengli Petrochemical | B11: Private integrated refiner | C11: CNY | D11: =Data!$I$8/Data!$H$8/1000 -> 28.206944 | E11: =Data!$S$8/Data!$H$8/1000 -> 36.787627 | F11: =IFERROR(Data!$I$8/Data!$AD$8-1,"n/a") -> -0.14937897 | G11: =IFERROR(IF(Data!$AI$8<=0,"n.m.",Data!$N$8/Data!$AI$8-1),"n/a") -> 0.050992897 | H11: =IF(Data!$K$8="","n/a",Data!$K$8/Data!$I$8) -> 0.13187722 | I11: =IF(OR(Data!$K$8="",Data!$AC$8=""),"n/a",(Data!$K$8-Data!$AC$8)/Data!$I$8) -> 0.087275924 | J11: =IFERROR(Data!$N$8/Data!$I$8,"n/a") -> 0.12973111 | K11: =IFERROR(Data!$L$8/Data!$I$8,"n/a") -> 0.068084662 | L11: =IFERROR(Data!$Q$8/Data!$I$8,"n/a") -> 0.035179516 | M11: =IFERROR(Data!$N$8/AVERAGE(Data!$S$8,Data!$AN$8),"n/a") -> 0.097460258 | N11: =IFERROR(Data!$Q$8/AVERAGE(Data!$U$8,Data!$AP$8),"n/a") -> 0.10865859 | O11: =IFERROR(Data!$Q$8/AVERAGE(Data!$S$8,Data!$AN$8),"n/a") -> 0.026428548 | P11: =IFERROR(Data!$I$8/AVERAGE(Data!$S$8,Data!$AN$8),"n/a") -> 0.75124819 | Q11: =IFERROR(Data!$T$8/Data!$S$8,"n/a") -> 0.74532323 | R11: =IFERROR(Data!$Z$8/Data!$U$8,"n/a") -> 2.2703501 | S11: =IFERROR(IF(Data!$N$8<=0,"n.m.",(Data!$Z$8-Data!$W$8)/Data!$N$8),"n/a") -> 4.683778 | T11: =IFERROR(IF(Data!$O$8<=0,"n/a",Data!$L$8/Data!$O$8),"n/a") -> 3.3715043 | U11: =IFERROR(Data!$X$8/Data!$Y$8,"n/a") -> 0.55713189 | V11: =IFERROR(Data!$AA$8/Data!$I$8,"n/a") -> 0.15476755 | W11: =IFERROR(IF(Data!$N$8<=0,"n.m.",Data!$AA$8/Data!$N$8),"n/a") -> 1.1929872 | X11: =IFERROR(Data!$AB$8/Data!$I$8,"n/a") -> 0.035363954 | Y11: =IFERROR((Data!$AA$8-Data!$AB$8)/Data!$I$8,"n/a") -> 0.1194036 | Z11: =(Data!$AA$8-Data!$AB$8)/Data!$H$8/1000 -> 3.3680105
A12: Rongsheng Petrochemical | B12: Private integrated refiner | C12: CNY | D12: =Data!$I$9/Data!$H$9/1000 -> 43.291109 | E12: =Data!$S$9/Data!$H$9/1000 -> 54.233851 | F12: =IFERROR(Data!$I$9/Data!$AD$9-1,"n/a") -> -0.054683624 | G12: =IFERROR(IF(Data!$AI$9<=0,"n.m.",Data!$N$9/Data!$AI$9-1),"n/a") -> 0.079093821 | H12: =IF(Data!$K$9="","n/a",Data!$K$9/Data!$I$9) -> 0.12215167 | I12: =IF(OR(Data!$K$9="",Data!$AC$9=""),"n/a",(Data!$K$9-Data!$AC$9)/Data!$I$9) -> 0.043802905 | J12: =IFERROR(Data!$N$9/Data!$I$9,"n/a") -> 0.085277705 | K12: =IFERROR(Data!$L$9/Data!$I$9,"n/a") -> 0.029024622 | L12: =IFERROR(Data!$Q$9/Data!$I$9,"n/a") -> 0.010526974 | M12: =IFERROR(Data!$N$9/AVERAGE(Data!$S$9,Data!$AN$9),"n/a") -> 0.068853692 | N12: =IFERROR(Data!$Q$9/AVERAGE(Data!$U$9,Data!$AP$9),"n/a") -> 0.03387475 | O12: =IFERROR(Data!$Q$9/AVERAGE(Data!$S$9,Data!$AN$9),"n/a") -> 0.0084995368 | P12: =IFERROR(Data!$I$9/AVERAGE(Data!$S$9,Data!$AN$9),"n/a") -> 0.80740554 | Q12: =IFERROR(Data!$T$9/Data!$S$9,"n/a") -> 0.74913728 | R12: =IFERROR(Data!$Z$9/Data!$U$9,"n/a") -> 2.1457702 | S12: =IFERROR(IF(Data!$N$9<=0,"n.m.",(Data!$Z$9-Data!$W$9)/Data!$N$9),"n/a") -> 7.3948654 | T12: =IFERROR(IF(Data!$O$9<=0,"n/a",Data!$L$9/Data!$O$9),"n/a") -> 1.5366745 | U12: =IFERROR(Data!$X$9/Data!$Y$9,"n/a") -> 0.39336912 | V12: =IFERROR(Data!$AA$9/Data!$I$9,"n/a") -> 0.14712632 | W12: =IFERROR(IF(Data!$N$9<=0,"n.m.",Data!$AA$9/Data!$N$9),"n/a") -> 1.7252613 | X12: =IFERROR(Data!$AB$9/Data!$I$9,"n/a") -> 0.13829799 | Y12: =IFERROR((Data!$AA$9-Data!$AB$9)/Data!$I$9,"n/a") -> 0.0088283343 | Z12: =(Data!$AA$9-Data!$AB$9)/Data!$H$9/1000 -> 0.38218839
A13: Sinopec Shanghai Petrochemical | B13: Refining & petchem pure-play | C13: CNY | D13: =Data!$I$10/Data!$H$10/1000 -> 10.599409 | E13: =Data!$S$10/Data!$H$10/1000 -> 5.9695096 | F13: =IFERROR(Data!$I$10/Data!$AD$10-1,"n/a") -> -0.13278159 | G13: =IFERROR(IF(Data!$AI$10<=0,"n.m.",Data!$N$10/Data!$AI$10-1),"n/a") -> -0.46176695 | H13: =IF(Data!$K$10="","n/a",Data!$K$10/Data!$I$10) -> 0.15852153 | I13: =IF(OR(Data!$K$10="",Data!$AC$10=""),"n/a",(Data!$K$10-Data!$AC$10)/Data!$I$10) -> 0.0062619911 | J13: =IFERROR(Data!$N$10/Data!$I$10,"n/a") -> 0.02953638 | K13: =IFERROR(Data!$L$10/Data!$I$10,"n/a") -> -0.021051614 | L13: =IFERROR(Data!$Q$10/Data!$I$10,"n/a") -> -0.018929218 | M13: =IFERROR(Data!$N$10/AVERAGE(Data!$S$10,Data!$AN$10),"n/a") -> 0.052934177 | N13: =IFERROR(Data!$Q$10/AVERAGE(Data!$U$10,Data!$AP$10),"n/a") -> -0.05865607 | O13: =IFERROR(Data!$Q$10/AVERAGE(Data!$S$10,Data!$AN$10),"n/a") -> -0.033924352 | P13: =IFERROR(Data!$I$10/AVERAGE(Data!$S$10,Data!$AN$10),"n/a") -> 1.7921687 | Q13: =IFERROR(Data!$T$10/Data!$S$10,"n/a") -> 0.44482653 | R13: =IFERROR(Data!$Z$10/Data!$U$10,"n/a") -> 0.11091201 | S13: =IFERROR(IF(Data!$N$10<=0,"n.m.",(Data!$Z$10-Data!$W$10)/Data!$N$10),"n/a") -> -2.2110824 | T13: =IFERROR(IF(Data!$O$10<=0,"n/a",Data!$L$10/Data!$O$10),"n/a") -> -97.435195 | U13: =IFERROR(Data!$X$10/Data!$Y$10,"n/a") -> 0.93334528 | V13: =IFERROR(Data!$AA$10/Data!$I$10,"n/a") -> 0.026379645 | W13: =IFERROR(IF(Data!$N$10<=0,"n.m.",Data!$AA$10/Data!$N$10),"n/a") -> 0.89312382 | X13: =IFERROR(Data!$AB$10/Data!$I$10,"n/a") -> 0.041932562 | Y13: =IFERROR((Data!$AA$10-Data!$AB$10)/Data!$I$10,"n/a") -> -0.015552918 | Z13: =(Data!$AA$10-Data!$AB$10)/Data!$H$10/1000 -> -0.16485173
A15: Peer median - all peers | D15: =IFERROR(MEDIAN(D9:D13),"n/a") -> 43.291109 | E15: =IFERROR(MEDIAN(E9:E13),"n/a") -> 54.233851 | F15: =IFERROR(MEDIAN(F9:F13),"n/a") -> -0.094640798 | G15: =IFERROR(MEDIAN(G9:G13),"n/a") -> -0.029907707 | H15: =IFERROR(MEDIAN(H9:H13),"n/a") -> 0.15852153 | I15: =IFERROR(MEDIAN(I9:I13),"n/a") -> 0.068172927 | J15: =IFERROR(MEDIAN(J9:J13),"n/a") -> 0.085277705 | K15: =IFERROR(MEDIAN(K9:K13),"n/a") -> 0.029024622 | ... Z15: =IFERROR(MEDIAN(Z9:Z13),"n/a") -> 3.3680105
A16: Peer high - all peers | D16: =IFERROR(MAX(D9:D13),"n/a") -> 401.80516 | E16: =IFERROR(MAX(E9:E13),"n/a") -> 401.66335 | F16: =IFERROR(MAX(F9:F13),"n/a") -> -0.025021265 | G16: =IFERROR(MAX(G9:G13),"n/a") -> 0.079093821 | H16: =IFERROR(MAX(H9:H13),"n/a") -> 0.21586828 | I16: =IFERROR(MAX(I9:I13),"n/a") -> 0.13059035 | J16: =IFERROR(MAX(J9:J13),"n/a") -> 0.16905053 | K16: =IFERROR(MAX(K9:K13),"n/a") -> 0.086100426 | ... Z16: =IFERROR(MAX(Z9:Z13),"n/a") -> 16.793519
A17: Peer low - all peers | D17: =IFERROR(MIN(D9:D13),"n/a") -> 10.599409 | E17: =IFERROR(MIN(E9:E13),"n/a") -> 5.9695096 | F17: =IFERROR(MIN(F9:F13),"n/a") -> -0.14937897 | G17: =IFERROR(MIN(G9:G13),"n/a") -> -0.46176695 | H17: =IFERROR(MIN(H9:H13),"n/a") -> 0.12215167 | I17: =IFERROR(MIN(I9:I13),"n/a") -> 0.0062619911 | J17: =IFERROR(MIN(J9:J13),"n/a") -> 0.02953638 | K17: =IFERROR(MIN(K9:K13),"n/a") -> -0.021051614 | ... Z17: =IFERROR(MIN(Z9:Z13),"n/a") -> -0.16485173
A18: Peer median - State-owned majors | D18: =IFERROR(MEDIAN(D9:D10),"n/a") -> 396.13214 | E18: =IFERROR(MEDIAN(E9:E10),"n/a") -> 352.01817 | F18: =IFERROR(MEDIAN(F9:F10),"n/a") -> -0.059831031 | G18: =IFERROR(MEDIAN(G9:G10),"n/a") -> -0.072233096 | H18: =IFERROR(MEDIAN(H9:H10),"n/a") -> 0.18736414 | I18: =IFERROR(MEDIAN(I9:I10),"n/a") -> 0.099381637 | J18: =IFERROR(MEDIAN(J9:J10),"n/a") -> 0.11532855 | K18: =IFERROR(MEDIAN(K9:K10),"n/a") -> 0.05295184 | ... Z18: =IFERROR(MEDIAN(Z9:Z10),"n/a") -> 10.421658
A19: Peer median - Private integrated refiners | D19: =IFERROR(MEDIAN(D11:D12),"n/a") -> 35.749026 | E19: =IFERROR(MEDIAN(E11:E12),"n/a") -> 45.510739 | F19: =IFERROR(MEDIAN(F11:F12),"n/a") -> -0.1020313 | G19: =IFERROR(MEDIAN(G11:G12),"n/a") -> 0.065043359 | H19: =IFERROR(MEDIAN(H11:H12),"n/a") -> 0.12701444 | I19: =IFERROR(MEDIAN(I11:I12),"n/a") -> 0.065539414 | J19: =IFERROR(MEDIAN(J11:J12),"n/a") -> 0.10750441 | K19: =IFERROR(MEDIAN(K11:K12),"n/a") -> 0.048554642 | ... Z19: =IFERROR(MEDIAN(Z11:Z12),"n/a") -> 1.8750995
A21: Anchor (Sinochem Energy (中化能源)) minus all-peer median | D21: =IFERROR(D8-D15,"n/a") -> 11.991587 | E21: =IFERROR(E8-E15,"n/a") -> -39.443938 | F21: =IFERROR(F8-F15,"n/a") -> 0.017825701 | G21: =IFERROR(G8-G15,"n/a") -> 0.5949347 | H21: =IFERROR(H8-H15,"n/a") -> -0.1425419 | I21: =IFERROR(I8-I15,"n/a") -> -0.061332533 | J21: =IFERROR(J8-J15,"n/a") -> -0.07259514 | K21: =IFERROR(K8-K15,"n/a") -> -0.030080595 | ... Z21: =IFERROR(Z8-Z15,"n/a") -> -2.644954

Sheet Agriculture
A1: Agriculture - Syngenta Group entities vs crop-protection / seeds and crop-nutrition peers
A2: Syngenta Group itself discloses only sales and EBITDA publicly (USD 28.4bn / USD 4.4bn in FY2025); full statements exist for Syngenta AG (global CP + Seeds), ADAMA, Yangnong and Sinofert.
A3: FY2025, ratios computed from the 'Data' sheet. Amber rows = Sinochem Holdings group entities. Peer statistics exclude Sinochem entities. 'n.m.' = not meaningful (negative EBITDA); 'n/a' = not available.
D5: Scale | F5: Growth | H5: Profitability | L5: Returns | P5: Leverage & liquidity | U5: Cash generation
A6: Entity | B6: Group | C6: Ccy | D6: Revenue (USD bn) | E6: Total assets (USD bn) | F6: Revenue growth FY25 | G6: EBITDA growth FY25 | H6: Gross margin | I6: EBITDA margin | J6: EBIT margin | K6: Net margin | L6: EBITDA / avg assets | M6: ROE (NI / avg equity) | N6: ROA (NI / avg assets) | O6: Asset turnover (x) | P6: Liabilities / assets | Q6: Debt / equity | R6: Net debt / EBITDA (x) | S6: Interest cover (EBIT / interest, x) | T6: Current ratio (x) | U6: OCF / revenue | V6: OCF / EBITDA (cash conversion) | W6: Capex / revenue | X6: FCF margin | Y6: Free cash flow (USD bn)
A7: Direction (+1 higher is better, -1 lower is better, 0 informational) | D7: 0 | E7: 0 | F7: 1 | G7: 1 | H7: 1 | I7: 1 | J7: 1 | K7: 1 | L7: 1 | M7: 1 | N7: 1 | O7: 1 | P7: -1 | Q7: -1 | R7: -1 | S7: 1 | T7: 1 | U7: 1 | V7: 1 | W7: 0 | X7: 1 | Y7: 1
A8: Syngenta AG (global CP + Seeds) | B8: Sinochem - CP & seeds | C8: USD | D8: =Data!$I$11/Data!$H$11/1000 -> 16.999 | E8: =Data!$S$11/Data!$H$11/1000 -> 30.799 | F8: =IFERROR(Data!$I$11/Data!$AD$11-1,"n/a") -> 0.0010600082 | G8: =IFERROR(IF(Data!$AI$11<=0,"n.m.",Data!$N$11/Data!$AI$11-1),"n/a") -> -0.080715532 | H8: =IF(Data!$K$11="","n/a",Data!$K$11/Data!$I$11) -> 0.39519972 | I8: =IFERROR(Data!$N$11/Data!$I$11,"n/a") -> 0.12394847 | J8: =IFERROR(Data!$L$11/Data!$I$11,"n/a") -> 0.07229837 | K8: =IFERROR(Data!$Q$11/Data!$I$11,"n/a") -> -0.0089417025 | L8: =IFERROR(Data!$N$11/AVERAGE(Data!$S$11,Data!$AN$11),"n/a") -> 0.069948875 | M8: =IFERROR(Data!$Q$11/AVERAGE(Data!$U$11,Data!$AP$11),"n/a") -> -0.020753687 | N8: =IFERROR(Data!$Q$11/AVERAGE(Data!$S$11,Data!$AN$11),"n/a") -> -0.0050461457 | O8: =IFERROR(Data!$I$11/AVERAGE(Data!$S$11,Data!$AN$11),"n/a") -> 0.56433836 | P8: =IFERROR(Data!$T$11/Data!$S$11,"n/a") -> 0.76015455 | Q8: =IFERROR(Data!$Z$11/Data!$U$11,"n/a") -> 1.4256126 | R8: =IFERROR(IF(Data!$N$11<=0,"n.m.",(Data!$Z$11-Data!$W$11)/Data!$N$11),"n/a") -> 4.6767916 | S8: =IFERROR(IF(Data!$O$11<=0,"n/a",Data!$L$11/Data!$O$11),"n/a") -> 1.5878553 | T8: =IFERROR(Data!$X$11/Data!$Y$11,"n/a") -> 1.0596506 | U8: =IFERROR(Data!$AA$11/Data!$I$11,"n/a") -> 0.089769986 | V8: =IFERROR(IF(Data!$N$11<=0,"n.m.",Data!$AA$11/Data!$N$11),"n/a") -> 0.72425249 | W8: =IFERROR(Data!$AB$11/Data!$I$11,"n/a") -> 0.071592447 | X8: =IFERROR((Data!$AA$11-Data!$AB$11)/Data!$I$11,"n/a") -> 0.01817754 | Y8: =(Data!$AA$11-Data!$AB$11)/Data!$H$11/1000 -> 0.309
A9: ADAMA | B9: Sinochem - CP (generics) | C9: CNY | D9: =Data!$I$12/Data!$H$12/1000 -> 4.0601187 | E9: =Data!$S$12/Data!$H$12/1000 -> 6.7981431 | F9: =IFERROR(Data!$I$12/Data!$AD$12-1,"n/a") -> -0.018429841 | G9: =IFERROR(IF(Data!$AI$12<=0,"n.m.",Data!$N$12/Data!$AI$12-1),"n/a") -> 0.96135309 | H9: =IF(Data!$K$12="","n/a",Data!$K$12/Data!$I$12) -> 0.26335609 | I9: =IFERROR(Data!$N$12/Data!$I$12,"n/a") -> 0.11881538 | J9: =IFERROR(Data!$L$12/Data!$I$12,"n/a") -> 0.046133982 | K9: =IFERROR(Data!$Q$12/Data!$I$12,"n/a") -> -0.036128311 | L9: =IFERROR(Data!$N$12/AVERAGE(Data!$S$12,Data!$AN$12),"n/a") -> 0.069811845 | M9: =IFERROR(Data!$Q$12/AVERAGE(Data!$U$12,Data!$AP$12),"n/a") -> -0.057195435 | N9: =IFERROR(Data!$Q$12/AVERAGE(Data!$S$12,Data!$AN$12),"n/a") -> -0.021227757 | O9: =IFERROR(Data!$I$12/AVERAGE(Data!$S$12,Data!$AN$12),"n/a") -> 0.58756572 | P9: =IFERROR(Data!$T$12/Data!$S$12,"n/a") -> 0.63735062 | Q9: =IFERROR(Data!$Z$12/Data!$U$12,"n/a") -> 1.0043461 | R9: =IFERROR(IF(Data!$N$12<=0,"n.m.",(Data!$Z$12-Data!$W$12)/Data!$N$12),"n/a") -> 4.1294722 | S9: =IFERROR(IF(Data!$O$12<=0,"n/a",Data!$L$12/Data!$O$12),"n/a") -> 1.3074426 | T9: =IFERROR(Data!$X$12/Data!$Y$12,"n/a") -> 1.1418523 | U9: =IFERROR(Data!$AA$12/Data!$I$12,"n/a") -> 0.13987739 | V9: =IFERROR(IF(Data!$N$12<=0,"n.m.",Data!$AA$12/Data!$N$12),"n/a") -> 1.1772667 | W9: =IFERROR(Data!$AB$12/Data!$I$12,"n/a") -> 0.041930467 | X9: =IFERROR((Data!$AA$12-Data!$AB$12)/Data!$I$12,"n/a") -> 0.097946918 | Y9: =(Data!$AA$12-Data!$AB$12)/Data!$H$12/1000 -> 0.39767611
A10: Yangnong Chemical | B10: Sinochem - CP (AI) | C10: CNY | D10: =Data!$I$13/Data!$H$13/1000 -> 1.6650902 | E10: =Data!$S$13/Data!$H$13/1000 -> 2.5510613 | F10: =IFERROR(Data!$I$13/Data!$AD$13-1,"n/a") -> 0.13758373 | G10: =IFERROR(IF(Data!$AI$13<=0,"n.m.",Data!$N$13/Data!$AI$13-1),"n/a") -> 0.48075406 | H10: =IF(Data!$K$13="","n/a",Data!$K$13/Data!$I$13) -> 0.21992105 | I10: =IFERROR(Data!$N$13/Data!$I$13,"n/a") -> 0.25800367 | J10: =IFERROR(Data!$L$13/Data!$I$13,"n/a") -> 0.12301427 | K10: =IFERROR(Data!$Q$13/Data!$I$13,"n/a") -> 0.10838565 | L10: =IFERROR(Data!$N$13/AVERAGE(Data!$S$13,Data!$AN$13),"n/a") -> 0.17085077 | M10: =IFERROR(Data!$Q$13/AVERAGE(Data!$U$13,Data!$AP$13),"n/a") -> 0.1168737 | N10: =IFERROR(Data!$Q$13/AVERAGE(Data!$S$13,Data!$AN$13),"n/a") -> 0.071773285 | O10: =IFERROR(Data!$I$13/AVERAGE(Data!$S$13,Data!$AN$13),"n/a") -> 0.66220286 | P10: =IFERROR(Data!$T$13/Data!$S$13,"n/a") -> 0.36908817 | Q10: =IFERROR(Data!$Z$13/Data!$U$13,"n/a") -> 0.079383128 | R10: =IFERROR(IF(Data!$N$13<=0,"n.m.",(Data!$Z$13-Data!$W$13)/Data!$N$13),"n/a") -> -0.13738427 | S10: =IFERROR(IF(Data!$O$13<=0,"n/a",Data!$L$13/Data!$O$13),"n/a") -> 35.282383 | T10: =IFERROR(Data!$X$13/Data!$Y$13,"n/a") -> 1.3782997 | U10: =IFERROR(Data!$AA$13/Data!$I$13,"n/a") -> 0.18674381 | V10: =IFERROR(IF(Data!$N$13<=0,"n.m.",Data!$AA$13/Data!$N$13),"n/a") -> 0.72380293 | W10: =IFERROR(Data!$AB$13/Data!$I$13,"n/a") -> 0.080985117 | X10: =IFERROR((Data!$AA$13-Data!$AB$13)/Data!$I$13,"n/a") -> 0.1057587 | Y10: =(Data!$AA$13-Data!$AB$13)/Data!$H$13/1000 -> 0.17609777
A11: Sinofert | B11: Sinochem - fertilizer | C11: CNY | D11: =Data!$I$14/Data!$H$14/1000 -> 3.2631652 | E11: =Data!$S$14/Data!$H$14/1000 -> 3.308788 | F11: =IFERROR(Data!$I$14/Data!$AD$14-1,"n/a") -> 0.093969655 | G11: =IFERROR(IF(Data!$AI$14<=0,"n.m.",Data!$N$14/Data!$AI$14-1),"n/a") -> 0.30584267 | H11: =IF(Data!$K$14="","n/a",Data!$K$14/Data!$I$14) -> 0.12437368 | I11: =IFERROR(Data!$N$14/Data!$I$14,"n/a") -> 0.085335083 | J11: =IFERROR(Data!$L$14/Data!$I$14,"n/a") -> 0.064394886 | K11: =IFERROR(Data!$Q$14/Data!$I$14,"n/a") -> 0.054734912 | L11: =IFERROR(Data!$N$14/AVERAGE(Data!$S$14,Data!$AN$14),"n/a") -> 0.088218377 | M11: =IFERROR(Data!$Q$14/AVERAGE(Data!$U$14,Data!$AP$14),"n/a") -> 0.11528546 | N11: =IFERROR(Data!$Q$14/AVERAGE(Data!$S$14,Data!$AN$14),"n/a") -> 0.05658429 | O11: =IFERROR(Data!$I$14/AVERAGE(Data!$S$14,Data!$AN$14),"n/a") -> 1.0337879 | P11: =IFERROR(Data!$T$14/Data!$S$14,"n/a") -> 0.51440152 | Q11: =IFERROR(Data!$Z$14/Data!$U$14,"n/a") -> 0.13158875 | R11: =IFERROR(IF(Data!$N$14<=0,"n.m.",(Data!$Z$14-Data!$W$14)/Data!$N$14),"n/a") -> -0.71581974 | S11: =IFERROR(IF(Data!$O$14<=0,"n/a",Data!$L$14/Data!$O$14),"n/a") -> 33.228157 | T11: =IFERROR(Data!$X$14/Data!$Y$14,"n/a") -> 1.2378762 | U11: =IFERROR(Data!$AA$14/Data!$I$14,"n/a") -> 0.085705885 | V11: =IFERROR(IF(Data!$N$14<=0,"n.m.",Data!$AA$14/Data!$N$14),"n/a") -> 1.0043452 | W11: =IFERROR(Data!$AB$14/Data!$I$14,"n/a") -> 0.01475147 | X11: =IFERROR((Data!$AA$14-Data!$AB$14)/Data!$I$14,"n/a") -> 0.070954415 | Y11: =(Data!$AA$14-Data!$AB$14)/Data!$H$14/1000 -> 0.23153598
A12: Corteva | B12: CP & seeds peer | C12: USD | D12: =Data!$I$15/Data!$H$15/1000 -> 17.401 | E12: =Data!$S$15/Data!$H$15/1000 -> 42.845 | F12: =IFERROR(Data!$I$15/Data!$AD$15-1,"n/a") -> 0.029157795 | G12: =IFERROR(IF(Data!$AI$15<=0,"n.m.",Data!$N$15/Data!$AI$15-1),"n/a") -> 0.12285192 | H12: =IF(Data!$K$15="","n/a",Data!$K$15/Data!$I$15) -> 0.47290386 | I12: =IFERROR(Data!$N$15/Data!$I$15,"n/a") -> 0.17648411 | J12: =IFERROR(Data!$L$15/Data!$I$15,"n/a") -> 0.10735015 | K12: =IFERROR(Data!$Q$15/Data!$I$15,"n/a") -> 0.063502098 | L12: =IFERROR(Data!$N$15/AVERAGE(Data!$S$15,Data!$AN$15),"n/a") -> 0.073407434 | M12: =IFERROR(Data!$Q$15/AVERAGE(Data!$U$15,Data!$AP$15),"n/a") -> 0.045646067 | N12: =IFERROR(Data!$Q$15/AVERAGE(Data!$S$15,Data!$AN$15),"n/a") -> 0.02641329 | O12: =IFERROR(Data!$I$15/AVERAGE(Data!$S$15,Data!$AN$15),"n/a") -> 0.41594359 | P12: =IFERROR(Data!$T$15/Data!$S$15,"n/a") -> 0.43083207 | Q12: =IFERROR(Data!$Z$15/Data!$U$15,"n/a") -> 0.10579841 | R12: =IFERROR(IF(Data!$N$15<=0,"n.m.",(Data!$Z$15-Data!$W$15)/Data!$N$15),"n/a") -> -0.63204168 | S12: =IFERROR(IF(Data!$O$15<=0,"n/a",Data!$L$15/Data!$O$15),"n/a") -> 10.377778 | T12: =IFERROR(Data!$X$15/Data!$Y$15,"n/a") -> 1.4296907 | U12: =IFERROR(Data!$AA$15/Data!$I$15,"n/a") -> 0.19573588 | V12: =IFERROR(IF(Data!$N$15<=0,"n.m.",Data!$AA$15/Data!$N$15),"n/a") -> 1.109085 | W12: =IFERROR(Data!$AB$15/Data!$I$15,"n/a") -> 0.033963565 | X12: =IFERROR((Data!$AA$15-Data!$AB$15)/Data!$I$15,"n/a") -> 0.16177231 | Y12: =(Data!$AA$15-Data!$AB$15)/Data!$H$15/1000 -> 2.815
A13: FMC Corp | B13: CP & seeds peer | C13: USD | D13: =Data!$I$16/Data!$H$16/1000 -> 3.4674 | E13: =Data!$S$16/Data!$H$16/1000 -> 9.6872 | F13: =IFERROR(Data!$I$16/Data!$AD$16-1,"n/a") -> -0.18339182 | G13: =IFERROR(IF(Data!$AI$16<=0,"n.m.",Data!$N$16/Data!$AI$16-1),"n/a") -> -3.1304921 | H13: =IF(Data!$K$16="","n/a",Data!$K$16/Data!$I$16) -> 0.37001788 | I13: =IFERROR(Data!$N$16/Data!$I$16,"n/a") -> -0.41953625 | J13: =IFERROR(Data!$L$16/Data!$I$16,"n/a") -> -0.46960258 | K13: =IFERROR(Data!$Q$16/Data!$I$16,"n/a") -> -0.64526735 | L13: =IFERROR(Data!$N$16/AVERAGE(Data!$S$16,Data!$AN$16),"n/a") -> -0.13633233 | M13: =IFERROR(Data!$Q$16/AVERAGE(Data!$U$16,Data!$AP$16),"n/a") -> -0.67720992 | N13: =IFERROR(Data!$Q$16/AVERAGE(Data!$S$16,Data!$AN$16),"n/a") -> -0.20968581 | O13: =IFERROR(Data!$I$16/AVERAGE(Data!$S$16,Data!$AN$16),"n/a") -> 0.32495958 | P13: =IFERROR(Data!$T$16/Data!$S$16,"n/a") -> 0.78333265 | Q13: =IFERROR(Data!$Z$16/Data!$U$16,"n/a") -> 1.9414455 | R13: =IFERROR(IF(Data!$N$16<=0,"n.m.",(Data!$Z$16-Data!$W$16)/Data!$N$16),"n/a") -> n.m. | S13: =IFERROR(IF(Data!$O$16<=0,"n/a",Data!$L$16/Data!$O$16),"n/a") -> -6.7959098 | T13: =IFERROR(Data!$X$16/Data!$Y$16,"n/a") -> 1.3205336 | U13: =IFERROR(Data!$AA$16/Data!$I$16,"n/a") -> -0.0017880833 | V13: =IFERROR(IF(Data!$N$16<=0,"n.m.",Data!$AA$16/Data!$N$16),"n/a") -> n.m. | W13: =IFERROR(Data!$AB$16/Data!$I$16,"n/a") -> 0.027772971 | X13: =IFERROR((Data!$AA$16-Data!$AB$16)/Data!$I$16,"n/a") -> -0.029561054 | Y13: =(Data!$AA$16-Data!$AB$16)/Data!$H$16/1000 -> -0.1025
A14: Jiangshan Agrochemical | B14: CP & seeds peer | C14: CNY | D14: =Data!$I$17/Data!$H$17/1000 -> 0.81584921 | E14: =Data!$S$17/Data!$H$17/1000 -> 1.3648573 | F14: =IFERROR(Data!$I$17/Data!$AD$17-1,"n/a") -> 0.070807614 | G14: =IFERROR(IF(Data!$AI$17<=0,"n.m.",Data!$N$17/Data!$AI$17-1),"n/a") -> 0.24554065 | H14: =IF(Data!$K$17="","n/a",Data!$K$17/Data!$I$17) -> 0.17363965 | I14: =IFERROR(Data!$N$17/Data!$I$17,"n/a") -> 0.15854729 | J14: =IFERROR(Data!$L$17/Data!$I$17,"n/a") -> 0.11663496 | K14: =IFERROR(Data!$Q$17/Data!$I$17,"n/a") -> 0.090522333 | L14: =IFERROR(Data!$N$17/AVERAGE(Data!$S$17,Data!$AN$17),"n/a") -> 0.10043099 | M14: =IFERROR(Data!$Q$17/AVERAGE(Data!$U$17,Data!$AP$17),"n/a") -> 0.12758959 | N14: =IFERROR(Data!$Q$17/AVERAGE(Data!$S$17,Data!$AN$17),"n/a") -> 0.057340922 | O14: =IFERROR(Data!$I$17/AVERAGE(Data!$S$17,Data!$AN$17),"n/a") -> 0.63344503 | P14: =IFERROR(Data!$T$17/Data!$S$17,"n/a") -> 0.55620711 | Q14: =IFERROR(Data!$Z$17/Data!$U$17,"n/a") -> 0.55742967 | R14: =IFERROR(IF(Data!$N$17<=0,"n.m.",(Data!$Z$17-Data!$W$17)/Data!$N$17),"n/a") -> 1.6612416 | S14: =IFERROR(IF(Data!$O$17<=0,"n/a",Data!$L$17/Data!$O$17),"n/a") -> 27.694264 | T14: =IFERROR(Data!$X$17/Data!$Y$17,"n/a") -> 1.018195 | U14: =IFERROR(Data!$AA$17/Data!$I$17,"n/a") -> 0.050791678 | V14: =IFERROR(IF(Data!$N$17<=0,"n.m.",Data!$AA$17/Data!$N$17),"n/a") -> 0.32035665 | W14: =IFERROR(Data!$AB$17/Data!$I$17,"n/a") -> 0.21912304 | X14: =IFERROR((Data!$AA$17-Data!$AB$17)/Data!$I$17,"n/a") -> -0.16833136 | Y14: =(Data!$AA$17-Data!$AB$17)/Data!$H$17/1000 -> -0.13733301
A15: Lier Chemical | B15: CP & seeds peer | C15: CNY | D15: =Data!$I$18/Data!$H$18/1000 -> 1.2635368 | E15: =Data!$S$18/Data!$H$18/1000 -> 2.2616906 | F15: =IFERROR(Data!$I$18/Data!$AD$18-1,"n/a") -> 0.23210223 | G15: =IFERROR(IF(Data!$AI$18<=0,"n.m.",Data!$N$18/Data!$AI$18-1),"n/a") -> 0.4929644 | H15: =IF(Data!$K$18="","n/a",Data!$K$18/Data!$I$18) -> 0.1891497 | I15: =IFERROR(Data!$N$18/Data!$I$18,"n/a") -> 0.19961569 | J15: =IFERROR(Data!$L$18/Data!$I$18,"n/a") -> 0.089486347 | K15: =IFERROR(Data!$Q$18/Data!$I$18,"n/a") -> 0.064468346 | L15: =IFERROR(Data!$N$18/AVERAGE(Data!$S$18,Data!$AN$18),"n/a") -> 0.11318677 | M15: =IFERROR(Data!$Q$18/AVERAGE(Data!$U$18,Data!$AP$18),"n/a") -> 0.063587882 | N15: =IFERROR(Data!$Q$18/AVERAGE(Data!$S$18,Data!$AN$18),"n/a") -> 0.036555062 | O15: =IFERROR(Data!$I$18/AVERAGE(Data!$S$18,Data!$AN$18),"n/a") -> 0.56702343 | P15: =IFERROR(Data!$T$18/Data!$S$18,"n/a") -> 0.42603726 | Q15: =IFERROR(Data!$Z$18/Data!$U$18,"n/a") -> 0.36719622 | R15: =IFERROR(IF(Data!$N$18<=0,"n.m.",(Data!$Z$18-Data!$W$18)/Data!$N$18),"n/a") -> 1.3321827 | S15: =IFERROR(IF(Data!$O$18<=0,"n/a",Data!$L$18/Data!$O$18),"n/a") -> 9.6192153 | T15: =IFERROR(Data!$X$18/Data!$Y$18,"n/a") -> 1.3109117 | U15: =IFERROR(Data!$AA$18/Data!$I$18,"n/a") -> 0.14394987 | V15: =IFERROR(IF(Data!$N$18<=0,"n.m.",Data!$AA$18/Data!$N$18),"n/a") -> 0.72113505 | W15: =IFERROR(Data!$AB$18/Data!$I$18,"n/a") -> 0.12025251 | X15: =IFERROR((Data!$AA$18-Data!$AB$18)/Data!$I$18,"n/a") -> 0.023697361 | Y15: =(Data!$AA$18-Data!$AB$18)/Data!$H$18/1000 -> 0.029942488
A16: Nutrien | B16: Crop-nutrition peer | C16: USD | D16: =Data!$I$19/Data!$H$19/1000 -> 26.885 | E16: =Data!$S$19/Data!$H$19/1000 -> 52.301 | F16: =IFERROR(Data!$I$19/Data!$AD$19-1,"n/a") -> 0.035153242 | G16: =IFERROR(IF(Data!$AI$19<=0,"n.m.",Data!$N$19/Data!$AI$19-1),"n/a") -> 0.45530393 | H16: =IF(Data!$K$19="","n/a",Data!$K$19/Data!$I$19) -> 0.31047052 | I16: =IFERROR(Data!$N$19/Data!$I$19,"n/a") -> 0.2270783 | J16: =IFERROR(Data!$L$19/Data!$I$19,"n/a") -> 0.13896225 | K16: =IFERROR(Data!$Q$19/Data!$I$19,"n/a") -> 0.085437977 | L16: =IFERROR(Data!$N$19/AVERAGE(Data!$S$19,Data!$AN$19),"n/a") -> 0.11724489 | M16: =IFERROR(Data!$Q$19/AVERAGE(Data!$U$19,Data!$AP$19),"n/a") -> 0.092236031 | N16: =IFERROR(Data!$Q$19/AVERAGE(Data!$S$19,Data!$AN$19),"n/a") -> 0.04411327 | O16: =IFERROR(Data!$I$19/AVERAGE(Data!$S$19,Data!$AN$19),"n/a") -> 0.51631922 | P16: =IFERROR(Data!$T$19/Data!$S$19,"n/a") -> 0.51501883 | Q16: =IFERROR(Data!$Z$19/Data!$U$19,"n/a") -> 0.47384191 | R16: =IFERROR(IF(Data!$N$19<=0,"n.m.",(Data!$Z$19-Data!$W$19)/Data!$N$19),"n/a") -> 1.8538903 | S16: =IFERROR(IF(Data!$O$19<=0,"n/a",Data!$L$19/Data!$O$19),"n/a") -> 5.4381368 | T16: =IFERROR(Data!$X$19/Data!$Y$19,"n/a") -> 1.3358391 | U16: =IFERROR(Data!$AA$19/Data!$I$19,"n/a") -> 0.14904222 | V16: =IFERROR(IF(Data!$N$19<=0,"n.m.",Data!$AA$19/Data!$N$19),"n/a") -> 0.65634726 | W16: =IFERROR(Data!$AB$19/Data!$I$19,"n/a") -> 0.074576902 | X16: =IFERROR((Data!$AA$19-Data!$AB$19)/Data!$I$19,"n/a") -> 0.074465315 | Y16: =(Data!$AA$19-Data!$AB$19)/Data!$H$19/1000 -> 2.002
A17: Mosaic | B17: Crop-nutrition peer | C17: USD | D17: =Data!$I$20/Data!$H$20/1000 -> 12.0524 | E17: =Data!$S$20/Data!$H$20/1000 -> 24.4801 | F17: =IFERROR(Data!$I$20/Data!$AD$20-1,"n/a") -> 0.083576078 | G17: =IFERROR(IF(Data!$AI$20<=0,"n.m.",Data!$N$20/Data!$AI$20-1),"n/a") -> 0.13624772 | H17: =IF(Data!$K$20="","n/a",Data!$K$20/Data!$I$20) -> 0.1578026 | I17: =IFERROR(Data!$N$20/Data!$I$20,"n/a") -> 0.15527198 | J17: =IFERROR(Data!$L$20/Data!$I$20,"n/a") -> 0.068160698 | K17: =IFERROR(Data!$Q$20/Data!$I$20,"n/a") -> 0.047741529 | L17: =IFERROR(Data!$N$20/AVERAGE(Data!$S$20,Data!$AN$20),"n/a") -> 0.078955196 | M17: =IFERROR(Data!$Q$20/AVERAGE(Data!$U$20,Data!$AP$20),"n/a") -> 0.048253798 | N17: =IFERROR(Data!$Q$20/AVERAGE(Data!$S$20,Data!$AN$20),"n/a") -> 0.024276381 | O17: =IFERROR(Data!$I$20/AVERAGE(Data!$S$20,Data!$AN$20),"n/a") -> 0.5084961 | P17: =IFERROR(Data!$T$20/Data!$S$20,"n/a") -> 0.50023897 | Q17: =IFERROR(Data!$Z$20/Data!$U$20,"n/a") -> 0.41309607 | R17: =IFERROR(IF(Data!$N$20<=0,"n.m.",(Data!$Z$20-Data!$W$20)/Data!$N$20),"n/a") -> 2.5527947 | S17: =IFERROR(IF(Data!$O$20<=0,"n/a",Data!$L$20/Data!$O$20),"n/a") -> 3.4016563 | T17: =IFERROR(Data!$X$20/Data!$Y$20,"n/a") -> 1.3150296 | U17: =IFERROR(Data!$AA$20/Data!$I$20,"n/a") -> 0.068434503 | V17: =IFERROR(IF(Data!$N$20<=0,"n.m.",Data!$AA$20/Data!$N$20),"n/a") -> 0.44073955 | W17: =IFERROR(Data!$AB$20/Data!$I$20,"n/a") -> 0.11279081 | X17: =IFERROR((Data!$AA$20-Data!$AB$20)/Data!$I$20,"n/a") -> -0.044356311 | Y17: =(Data!$AA$20-Data!$AB$20)/Data!$H$20/1000 -> -0.5346
A18: Yuntianhua | B18: Crop-nutrition peer | C18: CNY | D18: =Data!$I$21/Data!$H$21/1000 -> 6.7912644 | E18: =Data!$S$21/Data!$H$21/1000 -> 7.0616451 | F18: =IFERROR(Data!$I$21/Data!$AD$21-1,"n/a") -> -0.21473614 | G18: =IFERROR(IF(Data!$AI$21<=0,"n.m.",Data!$N$21/Data!$AI$21-1),"n/a") -> -0.051394255 | H18: =IF(Data!$K$21="","n/a",Data!$K$21/Data!$I$21) -> 0.20213773 | I18: =IFERROR(Data!$N$21/Data!$I$21,"n/a") -> 0.20907611 | J18: =IFERROR(Data!$L$21/Data!$I$21,"n/a") -> 0.14213834 | K18: =IFERROR(Data!$Q$21/Data!$I$21,"n/a") -> 0.11355406 | L18: =IFERROR(Data!$N$21/AVERAGE(Data!$S$21,Data!$AN$21),"n/a") -> 0.1987309 | M18: =IFERROR(Data!$Q$21/AVERAGE(Data!$U$21,Data!$AP$21),"n/a") -> 0.21472254 | N18: =IFERROR(Data!$Q$21/AVERAGE(Data!$S$21,Data!$AN$21),"n/a") -> 0.10793533 | O18: =IFERROR(Data!$I$21/AVERAGE(Data!$S$21,Data!$AN$21),"n/a") -> 0.95051941 | P18: =IFERROR(Data!$T$21/Data!$S$21,"n/a") -> 0.47171889 | Q18: =IFERROR(Data!$Z$21/Data!$U$21,"n/a") -> 0.43098386 | R18: =IFERROR(IF(Data!$N$21<=0,"n.m.",(Data!$Z$21-Data!$W$21)/Data!$N$21),"n/a") -> 0.64022272 | S18: =IFERROR(IF(Data!$O$21<=0,"n/a",Data!$L$21/Data!$O$21),"n/a") -> 18.561641 | T18: =IFERROR(Data!$X$21/Data!$Y$21,"n/a") -> 0.84972303 | U18: =IFERROR(Data!$AA$21/Data!$I$21,"n/a") -> 0.18769454 | V18: =IFERROR(IF(Data!$N$21<=0,"n.m.",Data!$AA$21/Data!$N$21),"n/a") -> 0.89773309 | W18: =IFERROR(Data!$AB$21/Data!$I$21,"n/a") -> 0.047171694 | X18: =IFERROR((Data!$AA$21-Data!$AB$21)/Data!$I$21,"n/a") -> 0.14052285 | Y18: =(Data!$AA$21-Data!$AB$21)/Data!$H$21/1000 -> 0.95432782
A19: Salt Lake Potash (青海盐湖) | B19: Crop-nutrition peer | C19: CNY | D19: =Data!$I$22/Data!$H$22/1000 -> 2.1743925 | E19: =Data!$S$22/Data!$H$22/1000 -> 8.5795921 | F19: =IFERROR(Data!$I$22/Data!$AD$22-1,"n/a") -> 0.024258034 | G19: =IFERROR(IF(Data!$AI$22<=0,"n.m.",Data!$N$22/Data!$AI$22-1),"n/a") -> 0.21404045 | H19: =IF(Data!$K$22="","n/a",Data!$K$22/Data!$I$22) -> 0.57855137 | I19: =IFERROR(Data!$N$22/Data!$I$22,"n/a") -> 0.51628237 | J19: =IFERROR(Data!$L$22/Data!$I$22,"n/a") -> 0.45031199 | K19: =IFERROR(Data!$Q$22/Data!$I$22,"n/a") -> 0.57715181 | L19: =IFERROR(Data!$N$22/AVERAGE(Data!$S$22,Data!$AN$22),"n/a") -> 0.1496636 | M19: =IFERROR(Data!$Q$22/AVERAGE(Data!$U$22,Data!$AP$22),"n/a") -> 0.19867853 | N19: =IFERROR(Data!$Q$22/AVERAGE(Data!$S$22,Data!$AN$22),"n/a") -> 0.16730887 | O19: =IFERROR(Data!$I$22/AVERAGE(Data!$S$22,Data!$AN$22),"n/a") -> 0.28988711 | P19: =IFERROR(Data!$T$22/Data!$S$22,"n/a") -> 0.17489351 | Q19: =IFERROR(Data!$Z$22/Data!$U$22,"n/a") -> 0.025381152 | R19: =IFERROR(IF(Data!$N$22<=0,"n.m.",(Data!$Z$22-Data!$W$22)/Data!$N$22),"n/a") -> -2.8905036 | S19: =IFERROR(IF(Data!$O$22<=0,"n/a",Data!$L$22/Data!$O$22),"n/a") -> 347.57735 | T19: =IFERROR(Data!$X$22/Data!$Y$22,"n/a") -> 4.8589045 | U19: =IFERROR(Data!$AA$22/Data!$I$22,"n/a") -> 0.65548681 | V19: =IFERROR(IF(Data!$N$22<=0,"n.m.",Data!$AA$22/Data!$N$22),"n/a") -> 1.2696285 | W19: =IFERROR(Data!$AB$22/Data!$I$22,"n/a") -> 0.10589369 | X19: =IFERROR((Data!$AA$22-Data!$AB$22)/Data!$I$22,"n/a") -> 0.54959312 | Y19: =(Data!$AA$22-Data!$AB$22)/Data!$H$22/1000 -> 1.1950311
A21: Peer median - all peers | D21: =IFERROR(MEDIAN(D12:D19),"n/a") -> 5.1293322 | E21: =IFERROR(MEDIAN(E12:E19),"n/a") -> 9.133396 | F21: =IFERROR(MEDIAN(F12:F19),"n/a") -> 0.032155519 | G21: =IFERROR(MEDIAN(G12:G19),"n/a") -> 0.17514409 | H21: =IFERROR(MEDIAN(H12:H19),"n/a") -> 0.25630413 | I21: =IFERROR(MEDIAN(I12:I19),"n/a") -> 0.1880499 | J21: =IFERROR(MEDIAN(J12:J19),"n/a") -> 0.11199256 | K21: =IFERROR(MEDIAN(K12:K19),"n/a") -> 0.074953161 | ... Y21: =IFERROR(MEDIAN(Y12:Y19),"n/a") -> 0.49213515
A22: Peer high - all peers | D22: =IFERROR(MAX(D12:D19),"n/a") -> 26.885 | E22: =IFERROR(MAX(E12:E19),"n/a") -> 52.301 | F22: =IFERROR(MAX(F12:F19),"n/a") -> 0.23210223 | G22: =IFERROR(MAX(G12:G19),"n/a") -> 0.4929644 | H22: =IFERROR(MAX(H12:H19),"n/a") -> 0.57855137 | I22: =IFERROR(MAX(I12:I19),"n/a") -> 0.51628237 | J22: =IFERROR(MAX(J12:J19),"n/a") -> 0.45031199 | K22: =IFERROR(MAX(K12:K19),"n/a") -> 0.57715181 | ... Y22: =IFERROR(MAX(Y12:Y19),"n/a") -> 2.815
A23: Peer low - all peers | D23: =IFERROR(MIN(D12:D19),"n/a") -> 0.81584921 | E23: =IFERROR(MIN(E12:E19),"n/a") -> 1.3648573 | F23: =IFERROR(MIN(F12:F19),"n/a") -> -0.21473614 | G23: =IFERROR(MIN(G12:G19),"n/a") -> -3.1304921 | H23: =IFERROR(MIN(H12:H19),"n/a") -> 0.1578026 | I23: =IFERROR(MIN(I12:I19),"n/a") -> -0.41953625 | J23: =IFERROR(MIN(J12:J19),"n/a") -> -0.46960258 | K23: =IFERROR(MIN(K12:K19),"n/a") -> -0.64526735 | ... Y23: =IFERROR(MIN(Y12:Y19),"n/a") -> -0.5346
A24: Peer median - Crop-protection & seeds peers | D24: =IFERROR(MEDIAN(D12:D15),"n/a") -> 2.3654684 | E24: =IFERROR(MEDIAN(E12:E15),"n/a") -> 5.9744453 | F24: =IFERROR(MEDIAN(F12:F15),"n/a") -> 0.049982705 | G24: =IFERROR(MEDIAN(G12:G15),"n/a") -> 0.18419628 | H24: =IFERROR(MEDIAN(H12:H15),"n/a") -> 0.27958379 | I24: =IFERROR(MEDIAN(I12:I15),"n/a") -> 0.1675157 | J24: =IFERROR(MEDIAN(J12:J15),"n/a") -> 0.09841825 | K24: =IFERROR(MEDIAN(K12:K15),"n/a") -> 0.063985222 | ... Y24: =IFERROR(MEDIAN(Y12:Y15),"n/a") -> -0.036278756
A25: Peer median - Crop-nutrition peers | D25: =IFERROR(MEDIAN(D16:D19),"n/a") -> 9.4218322 | E25: =IFERROR(MEDIAN(E16:E19),"n/a") -> 16.529846 | F25: =IFERROR(MEDIAN(F16:F19),"n/a") -> 0.029705638 | G25: =IFERROR(MEDIAN(G16:G19),"n/a") -> 0.17514409 | H25: =IFERROR(MEDIAN(H16:H19),"n/a") -> 0.25630413 | I25: =IFERROR(MEDIAN(I16:I19),"n/a") -> 0.2180772 | J25: =IFERROR(MEDIAN(J16:J19),"n/a") -> 0.14055029 | K25: =IFERROR(MEDIAN(K16:K19),"n/a") -> 0.099496016 | ... Y25: =IFERROR(MEDIAN(Y16:Y19),"n/a") -> 1.0746795
A27: Anchor (Syngenta AG (global CP + Seeds)) minus all-peer median | D27: =IFERROR(D8-D21,"n/a") -> 11.869668 | E27: =IFERROR(E8-E21,"n/a") -> 21.665604 | F27: =IFERROR(F8-F21,"n/a") -> -0.03109551 | G27: =IFERROR(G8-G21,"n/a") -> -0.25585962 | H27: =IFERROR(H8-H21,"n/a") -> 0.13889559 | I27: =IFERROR(I8-I21,"n/a") -> -0.064101431 | J27: =IFERROR(J8-J21,"n/a") -> -0.039694188 | K27: =IFERROR(K8-K21,"n/a") -> -0.083894864 | ... Y27: =IFERROR(Y8-Y21,"n/a") -> -0.18313515

Sheet Rubber
A1: Rubber & tyres - Pirelli / Aeolus vs global and Chinese tyre peers and a natural-rubber producer
A2: Sinochem's rubber & tyre exposure is held through the ChemChina line (China National Tire & Rubber): Pirelli (Sinochem holds ~34.1% via Marco Polo International Italy; Pirelli's accounts state no entity controls it) and Aeolus Tyre.
A3: FY2025, ratios computed from the 'Data' sheet. Amber rows = Sinochem Holdings group entities. Peer statistics exclude Sinochem entities. 'n.m.' = not meaningful (negative EBITDA); 'n/a' = not available.
D5: Scale | F5: Growth | H5: Profitability | L5: Returns | P5: Leverage & liquidity | U5: Cash generation
A6: Entity | B6: Group | C6: Ccy | D6: Revenue (USD bn) | E6: Total assets (USD bn) | F6: Revenue growth FY25 | G6: EBITDA growth FY25 | H6: Gross margin | I6: EBITDA margin | J6: EBIT margin | K6: Net margin | L6: EBITDA / avg assets | M6: ROE (NI / avg equity) | N6: ROA (NI / avg assets) | O6: Asset turnover (x) | P6: Liabilities / assets | Q6: Debt / equity | R6: Net debt / EBITDA (x) | S6: Interest cover (EBIT / interest, x) | T6: Current ratio (x) | U6: OCF / revenue | V6: OCF / EBITDA (cash conversion) | W6: Capex / revenue | X6: FCF margin | Y6: Free cash flow (USD bn)
A7: Direction (+1 higher is better, -1 lower is better, 0 informational) | D7: 0 | E7: 0 | F7: 1 | G7: 1 | H7: 1 | I7: 1 | J7: 1 | K7: 1 | L7: 1 | M7: 1 | N7: 1 | O7: 1 | P7: -1 | Q7: -1 | R7: -1 | S7: 1 | T7: 1 | U7: 1 | V7: 1 | W7: 0 | X7: 1 | Y7: 1
A8: Pirelli | B8: Sinochem - premium tyres | C8: EUR | D8: =Data!$I$23/Data!$H$23/1000 -> 7.6480327 | E8: =Data!$S$23/Data!$H$23/1000 -> 15.071313 | F8: =IFERROR(Data!$I$23/Data!$AD$23-1,"n/a") -> 0.00041825845 | G8: =IFERROR(IF(Data!$AI$23<=0,"n.m.",Data!$N$23/Data!$AI$23-1),"n/a") -> -0.0073775657 | H8: =IF(Data!$K$23="","n/a",Data!$K$23/Data!$I$23) -> n/a | I8: =IFERROR(Data!$N$23/Data!$I$23,"n/a") -> 0.21617017 | J8: =IFERROR(Data!$L$23/Data!$I$23,"n/a") -> 0.13152042 | K8: =IFERROR(Data!$Q$23/Data!$I$23,"n/a") -> 0.078318138 | L8: =IFERROR(Data!$N$23/AVERAGE(Data!$S$23,Data!$AN$23),"n/a") -> 0.10836824 | M8: =IFERROR(Data!$Q$23/AVERAGE(Data!$U$23,Data!$AP$23),"n/a") -> 0.085810718 | N8: =IFERROR(Data!$Q$23/AVERAGE(Data!$S$23,Data!$AN$23),"n/a") -> 0.039261658 | O8: =IFERROR(Data!$I$23/AVERAGE(Data!$S$23,Data!$AN$23),"n/a") -> 0.5013099 | P8: =IFERROR(Data!$T$23/Data!$S$23,"n/a") -> 0.51646458 | Q8: =IFERROR(Data!$Z$23/Data!$U$23,"n/a") -> 0.45809424 | R8: =IFERROR(IF(Data!$N$23<=0,"n.m.",(Data!$Z$23-Data!$W$23)/Data!$N$23),"n/a") -> 0.97754306 | S8: =IFERROR(IF(Data!$O$23<=0,"n/a",Data!$L$23/Data!$O$23),"n/a") -> 3.066716 | T8: =IFERROR(Data!$X$23/Data!$Y$23,"n/a") -> 1.4485278 | U8: =IFERROR(Data!$AA$23/Data!$I$23,"n/a") -> 0.19270584 | V8: =IFERROR(IF(Data!$N$23<=0,"n.m.",Data!$AA$23/Data!$N$23),"n/a") -> 0.89145435 | W8: =IFERROR(Data!$AB$23/Data!$I$23,"n/a") -> 0.055764056 | X8: =IFERROR((Data!$AA$23-Data!$AB$23)/Data!$I$23,"n/a") -> 0.13694178 | Y8: =(Data!$AA$23-Data!$AB$23)/Data!$H$23/1000 -> 1.0473352
A9: Aeolus Tyre (风神股份) | B9: Sinochem - truck & bus tyres | C9: CNY | D9: =Data!$I$24/Data!$H$24/1000 -> 1.0399049 | E9: =Data!$S$24/Data!$H$24/1000 -> 1.1178089 | F9: =IFERROR(Data!$I$24/Data!$AD$24-1,"n/a") -> 0.10514553 | G9: =IFERROR(IF(Data!$AI$24<=0,"n.m.",Data!$N$24/Data!$AI$24-1),"n/a") -> -0.043712553 | H9: =IF(Data!$K$24="","n/a",Data!$K$24/Data!$I$24) -> 0.1480473 | I9: =IFERROR(Data!$N$24/Data!$I$24,"n/a") -> 0.080669785 | J9: =IFERROR(Data!$L$24/Data!$I$24,"n/a") -> 0.039105511 | K9: =IFERROR(Data!$Q$24/Data!$I$24,"n/a") -> 0.031781017 | L9: =IFERROR(Data!$N$24/AVERAGE(Data!$S$24,Data!$AN$24),"n/a") -> 0.078206033 | M9: =IFERROR(Data!$Q$24/AVERAGE(Data!$U$24,Data!$AP$24),"n/a") -> 0.069263937 | N9: =IFERROR(Data!$Q$24/AVERAGE(Data!$S$24,Data!$AN$24),"n/a") -> 0.030810387 | O9: =IFERROR(Data!$I$24/AVERAGE(Data!$S$24,Data!$AN$24),"n/a") -> 0.9694588 | P9: =IFERROR(Data!$T$24/Data!$S$24,"n/a") -> 0.55839016 | Q9: =IFERROR(Data!$Z$24/Data!$U$24,"n/a") -> 0.37480205 | R9: =IFERROR(IF(Data!$N$24<=0,"n.m.",(Data!$Z$24-Data!$W$24)/Data!$N$24),"n/a") -> 0.40205236 | S9: =IFERROR(IF(Data!$O$24<=0,"n/a",Data!$L$24/Data!$O$24),"n/a") -> 9.8337234 | T9: =IFERROR(Data!$X$24/Data!$Y$24,"n/a") -> 1.1636201 | U9: =IFERROR(Data!$AA$24/Data!$I$24,"n/a") -> 0.066891644 | V9: =IFERROR(IF(Data!$N$24<=0,"n.m.",Data!$AA$24/Data!$N$24),"n/a") -> 0.8292032 | W9: =IFERROR(Data!$AB$24/Data!$I$24,"n/a") -> 0.054883926 | X9: =IFERROR((Data!$AA$24-Data!$AB$24)/Data!$I$24,"n/a") -> 0.012007718 | Y9: =(Data!$AA$24-Data!$AB$24)/Data!$H$24/1000 -> 0.012486885
A10: Michelin | B10: Global major | C10: EUR | D10: =Data!$I$25/Data!$H$25/1000 -> 29.336343 | E10: =Data!$S$25/Data!$H$25/1000 -> 39.523702 | F10: =IFERROR(Data!$I$25/Data!$AD$25-1,"n/a") -> -0.044165778 | G10: =IFERROR(IF(Data!$AI$25<=0,"n.m.",Data!$N$25/Data!$AI$25-1),"n/a") -> -0.066103164 | H10: =IF(Data!$K$25="","n/a",Data!$K$25/Data!$I$25) -> 0.27004463 | I10: =IFERROR(Data!$N$25/Data!$I$25,"n/a") -> 0.16578178 | J10: =IFERROR(Data!$L$25/Data!$I$25,"n/a") -> 0.091028009 | K10: =IFERROR(Data!$Q$25/Data!$I$25,"n/a") -> 0.064019698 | L10: =IFERROR(Data!$N$25/AVERAGE(Data!$S$25,Data!$AN$25),"n/a") -> 0.11908249 | M10: =IFERROR(Data!$Q$25/AVERAGE(Data!$U$25,Data!$AP$25),"n/a") -> 0.090656497 | N10: =IFERROR(Data!$Q$25/AVERAGE(Data!$S$25,Data!$AN$25),"n/a") -> 0.045985906 | O10: =IFERROR(Data!$I$25/AVERAGE(Data!$S$25,Data!$AN$25),"n/a") -> 0.71830869 | P10: =IFERROR(Data!$T$25/Data!$S$25,"n/a") -> 0.48380833 | Q10: =IFERROR(Data!$Z$25/Data!$U$25,"n/a") -> 0.36761452 | R10: =IFERROR(IF(Data!$N$25<=0,"n.m.",(Data!$Z$25-Data!$W$25)/Data!$N$25),"n/a") -> 0.64237642 | S10: =IFERROR(IF(Data!$O$25<=0,"n/a",Data!$L$25/Data!$O$25),"n/a") -> 9.1 | T10: =IFERROR(Data!$X$25/Data!$Y$25,"n/a") -> 1.9020392 | U10: =IFERROR(Data!$AA$25/Data!$I$25,"n/a") -> 0.14692982 | V10: =IFERROR(IF(Data!$N$25<=0,"n.m.",Data!$AA$25/Data!$N$25),"n/a") -> 0.88628452 | W10: =IFERROR(Data!$AB$25/Data!$I$25,"n/a") -> 0.0776008 | X10: =IFERROR((Data!$AA$25-Data!$AB$25)/Data!$I$25,"n/a") -> 0.069329024 | Y10: =(Data!$AA$25-Data!$AB$25)/Data!$H$25/1000 -> 2.03386
A11: Bridgestone | B11: Global major | C11: JPY | D11: =Data!$I$26/Data!$H$26/1000 -> 29.602304 | E11: =Data!$S$26/Data!$H$26/1000 -> 38.412271 | F11: =IFERROR(Data!$I$26/Data!$AD$26-1,"n/a") -> -0.00014536931 | G11: =IFERROR(IF(Data!$AI$26<=0,"n.m.",Data!$N$26/Data!$AI$26-1),"n/a") -> -0.071913892 | H11: =IF(Data!$K$26="","n/a",Data!$K$26/Data!$I$26) -> 0.3852989 | I11: =IFERROR(Data!$N$26/Data!$I$26,"n/a") -> 0.16581419 | J11: =IFERROR(Data!$L$26/Data!$I$26,"n/a") -> 0.08606866 | K11: =IFERROR(Data!$Q$26/Data!$I$26,"n/a") -> 0.075471864 | L11: =IFERROR(Data!$N$26/AVERAGE(Data!$S$26,Data!$AN$26),"n/a") -> 0.12805366 | M11: =IFERROR(Data!$Q$26/AVERAGE(Data!$U$26,Data!$AP$26),"n/a") -> 0.089070678 | N11: =IFERROR(Data!$Q$26/AVERAGE(Data!$S$26,Data!$AN$26),"n/a") -> 0.05828481 | O11: =IFERROR(Data!$I$26/AVERAGE(Data!$S$26,Data!$AN$26),"n/a") -> 0.77227204 | P11: =IFERROR(Data!$T$26/Data!$S$26,"n/a") -> 0.35280464 | Q11: =IFERROR(Data!$Z$26/Data!$U$26,"n/a") -> 0.22232255 | R11: =IFERROR(IF(Data!$N$26<=0,"n.m.",(Data!$Z$26-Data!$W$26)/Data!$N$26),"n/a") -> 0.15413239 | S11: =IFERROR(IF(Data!$O$26<=0,"n/a",Data!$L$26/Data!$O$26),"n/a") -> 8.6607374 | T11: =IFERROR(Data!$X$26/Data!$Y$26,"n/a") -> 2.550369 | U11: =IFERROR(Data!$AA$26/Data!$I$26,"n/a") -> 0.14910242 | V11: =IFERROR(IF(Data!$N$26<=0,"n.m.",Data!$AA$26/Data!$N$26),"n/a") -> 0.89921385 | W11: =IFERROR(Data!$AB$26/Data!$I$26,"n/a") -> 0.064828561 | X11: =IFERROR((Data!$AA$26-Data!$AB$26)/Data!$I$26,"n/a") -> 0.084273856 | Y11: =(Data!$AA$26-Data!$AB$26)/Data!$H$26/1000 -> 2.4947003
A12: Goodyear | B12: Global major | C12: USD | D12: =Data!$I$27/Data!$H$27/1000 -> 18.28 | E12: =Data!$S$27/Data!$H$27/1000 -> 18.208 | F12: =IFERROR(Data!$I$27/Data!$AD$27-1,"n/a") -> -0.031677084 | G12: =IFERROR(IF(Data!$AI$27<=0,"n.m.",Data!$N$27/Data!$AI$27-1),"n/a") -> -0.52411022 | H12: =IF(Data!$K$27="","n/a",Data!$K$27/Data!$I$27) -> 0.18440919 | I12: =IFERROR(Data!$N$27/Data!$I$27,"n/a") -> 0.045350109 | J12: =IFERROR(Data!$L$27/Data!$I$27,"n/a") -> -0.011816193 | K12: =IFERROR(Data!$Q$27/Data!$I$27,"n/a") -> -0.092997812 | L12: =IFERROR(Data!$N$27/AVERAGE(Data!$S$27,Data!$AN$27),"n/a") -> 0.042372665 | M12: =IFERROR(Data!$Q$27/AVERAGE(Data!$U$27,Data!$AP$27),"n/a") -> -0.41332361 | N12: =IFERROR(Data!$Q$27/AVERAGE(Data!$S$27,Data!$AN$27),"n/a") -> -0.086892075 | O12: =IFERROR(Data!$I$27/AVERAGE(Data!$S$27,Data!$AN$27),"n/a") -> 0.93434537 | P12: =IFERROR(Data!$T$27/Data!$S$27,"n/a") -> 0.81310413 | Q12: =IFERROR(Data!$Z$27/Data!$U$27,"n/a") -> 1.8213341 | R12: =IFERROR(IF(Data!$N$27<=0,"n.m.",(Data!$Z$27-Data!$W$27)/Data!$N$27),"n/a") -> 6.5102533 | S12: =IFERROR(IF(Data!$O$27<=0,"n/a",Data!$L$27/Data!$O$27),"n/a") -> -0.48539326 | T12: =IFERROR(Data!$X$27/Data!$Y$27,"n/a") -> 1.0642878 | U12: =IFERROR(Data!$AA$27/Data!$I$27,"n/a") -> 0.043544858 | V12: =IFERROR(IF(Data!$N$27<=0,"n.m.",Data!$AA$27/Data!$N$27),"n/a") -> 0.960193 | W12: =IFERROR(Data!$AB$27/Data!$I$27,"n/a") -> 0.045185996 | X12: =IFERROR((Data!$AA$27-Data!$AB$27)/Data!$I$27,"n/a") -> -0.0016411379 | Y12: =(Data!$AA$27-Data!$AB$27)/Data!$H$27/1000 -> -0.03
A13: Linglong Tire | B13: China tyre producer | C13: CNY | D13: =Data!$I$28/Data!$H$28/1000 -> 3.4566079 | E13: =Data!$S$28/Data!$H$28/1000 -> 6.6454068 | F13: =IFERROR(Data!$I$28/Data!$AD$28-1,"n/a") -> 0.11715596 | G13: =IFERROR(IF(Data!$AI$28<=0,"n.m.",Data!$N$28/Data!$AI$28-1),"n/a") -> -0.21228923 | H13: =IF(Data!$K$28="","n/a",Data!$K$28/Data!$I$28) -> 0.17030546 | I13: =IFERROR(Data!$N$28/Data!$I$28,"n/a") -> 0.12533062 | J13: =IFERROR(Data!$L$28/Data!$I$28,"n/a") -> 0.049225802 | K13: =IFERROR(Data!$Q$28/Data!$I$28,"n/a") -> 0.055545176 | L13: =IFERROR(Data!$N$28/AVERAGE(Data!$S$28,Data!$AN$28),"n/a") -> 0.065392172 | M13: =IFERROR(Data!$Q$28/AVERAGE(Data!$U$28,Data!$AP$28),"n/a") -> 0.061112913 | N13: =IFERROR(Data!$Q$28/AVERAGE(Data!$S$28,Data!$AN$28),"n/a") -> 0.028981103 | O13: =IFERROR(Data!$I$28/AVERAGE(Data!$S$28,Data!$AN$28),"n/a") -> 0.52175734 | P13: =IFERROR(Data!$T$28/Data!$S$28,"n/a") -> 0.51222584 | Q13: =IFERROR(Data!$Z$28/Data!$U$28,"n/a") -> 0.61335603 | R13: =IFERROR(IF(Data!$N$28<=0,"n.m.",(Data!$Z$28-Data!$W$28)/Data!$N$28),"n/a") -> 3.5103268 | S13: =IFERROR(IF(Data!$O$28<=0,"n/a",Data!$L$28/Data!$O$28),"n/a") -> 4.1699783 | T13: =IFERROR(Data!$X$28/Data!$Y$28,"n/a") -> 0.88982745 | U13: =IFERROR(Data!$AA$28/Data!$I$28,"n/a") -> 0.080707136 | V13: =IFERROR(IF(Data!$N$28<=0,"n.m.",Data!$AA$28/Data!$N$28),"n/a") -> 0.64395384 | W13: =IFERROR(Data!$AB$28/Data!$I$28,"n/a") -> 0.071627615 | X13: =IFERROR((Data!$AA$28-Data!$AB$28)/Data!$I$28,"n/a") -> 0.0090795214 | Y13: =(Data!$AA$28-Data!$AB$28)/Data!$H$28/1000 -> 0.031384346
A14: Sailun Group | B14: China tyre producer | C14: CNY | D14: =Data!$I$29/Data!$H$29/1000 -> 5.160953 | E14: =Data!$S$29/Data!$H$29/1000 -> 6.5605837 | F14: =IFERROR(Data!$I$29/Data!$AD$29-1,"n/a") -> 0.1569079 | G14: =IFERROR(IF(Data!$AI$29<=0,"n.m.",Data!$N$29/Data!$AI$29-1),"n/a") -> -0.016906064 | H14: =IF(Data!$K$29="","n/a",Data!$K$29/Data!$I$29) -> 0.2468242 | I14: =IFERROR(Data!$N$29/Data!$I$29,"n/a") -> 0.18111561 | J14: =IFERROR(Data!$L$29/Data!$I$29,"n/a") -> 0.12478239 | K14: =IFERROR(Data!$Q$29/Data!$I$29,"n/a") -> 0.098302928 | L14: =IFERROR(Data!$N$29/AVERAGE(Data!$S$29,Data!$AN$29),"n/a") -> 0.15309068 | M14: =IFERROR(Data!$Q$29/AVERAGE(Data!$U$29,Data!$AP$29),"n/a") -> 0.16466645 | N14: =IFERROR(Data!$Q$29/AVERAGE(Data!$S$29,Data!$AN$29),"n/a") -> 0.083092023 | O14: =IFERROR(Data!$I$29/AVERAGE(Data!$S$29,Data!$AN$29),"n/a") -> 0.84526499 | P14: =IFERROR(Data!$T$29/Data!$S$29,"n/a") -> 0.50060018 | Q14: =IFERROR(Data!$Z$29/Data!$U$29,"n/a") -> 0.516081 | R14: =IFERROR(IF(Data!$N$29<=0,"n.m.",(Data!$Z$29-Data!$W$29)/Data!$N$29),"n/a") -> 1.121725 | S14: =IFERROR(IF(Data!$O$29<=0,"n/a",Data!$L$29/Data!$O$29),"n/a") -> 9.673225 | T14: =IFERROR(Data!$X$29/Data!$Y$29,"n/a") -> 1.1272312 | U14: =IFERROR(Data!$AA$29/Data!$I$29,"n/a") -> 0.11357764 | V14: =IFERROR(IF(Data!$N$29<=0,"n.m.",Data!$AA$29/Data!$N$29),"n/a") -> 0.62710026 | W14: =IFERROR(Data!$AB$29/Data!$I$29,"n/a") -> 0.13094352 | X14: =IFERROR((Data!$AA$29-Data!$AB$29)/Data!$I$29,"n/a") -> -0.01736588 | Y14: =(Data!$AA$29-Data!$AB$29)/Data!$H$29/1000 -> -0.089624492
A15: Zhongce Rubber | B15: China tyre producer | C15: CNY | D15: =Data!$I$30/Data!$H$30/1000 -> 6.306106 | E15: =Data!$S$30/Data!$H$30/1000 -> 7.3251593 | F15: =IFERROR(Data!$I$30/Data!$AD$30-1,"n/a") -> 0.14524131 | G15: =IFERROR(IF(Data!$AI$30<=0,"n.m.",Data!$N$30/Data!$AI$30-1),"n/a") -> 0.15036301 | H15: =IF(Data!$K$30="","n/a",Data!$K$30/Data!$I$30) -> 0.19657896 | I15: =IFERROR(Data!$N$30/Data!$I$30,"n/a") -> 0.15497383 | J15: =IFERROR(Data!$L$30/Data!$I$30,"n/a") -> 0.10626676 | K15: =IFERROR(Data!$Q$30/Data!$I$30,"n/a") -> 0.092255712 | L15: =IFERROR(Data!$N$30/AVERAGE(Data!$S$30,Data!$AN$30),"n/a") -> 0.14358294 | M15: =IFERROR(Data!$Q$30/AVERAGE(Data!$U$30,Data!$AP$30),"n/a") -> 0.19614659 | N15: =IFERROR(Data!$Q$30/AVERAGE(Data!$S$30,Data!$AN$30),"n/a") -> 0.085474731 | O15: =IFERROR(Data!$I$30/AVERAGE(Data!$S$30,Data!$AN$30),"n/a") -> 0.92649798 | P15: =IFERROR(Data!$T$30/Data!$S$30,"n/a") -> 0.52486327 | Q15: =IFERROR(Data!$Z$30/Data!$U$30,"n/a") -> 0.51838585 | R15: =IFERROR(IF(Data!$N$30<=0,"n.m.",(Data!$Z$30-Data!$W$30)/Data!$N$30),"n/a") -> 1.0937127 | S15: =IFERROR(IF(Data!$O$30<=0,"n/a",Data!$L$30/Data!$O$30),"n/a") -> 14.566166 | T15: =IFERROR(Data!$X$30/Data!$Y$30,"n/a") -> 1.0768435 | U15: =IFERROR(Data!$AA$30/Data!$I$30,"n/a") -> 0.042348858 | V15: =IFERROR(IF(Data!$N$30<=0,"n.m.",Data!$AA$30/Data!$N$30),"n/a") -> 0.27326458 | W15: =IFERROR(Data!$AB$30/Data!$I$30,"n/a") -> 0.077986166 | X15: =IFERROR((Data!$AA$30-Data!$AB$30)/Data!$I$30,"n/a") -> -0.035637308 | Y15: =(Data!$AA$30-Data!$AB$30)/Data!$H$30/1000 -> -0.22473264
A16: Hainan Rubber | B16: Natural rubber | C16: CNY | D16: =Data!$I$31/Data!$H$31/1000 -> 5.9246952 | E16: =Data!$S$31/Data!$H$31/1000 -> 4.7459624 | F16: =IFERROR(Data!$I$31/Data!$AD$31-1,"n/a") -> 0.0055467355 | G16: =IFERROR(IF(Data!$AI$31<=0,"n.m.",Data!$N$31/Data!$AI$31-1),"n/a") -> 0.047173868 | H16: =IF(Data!$K$31="","n/a",Data!$K$31/Data!$I$31) -> 0.025153045 | I16: =IFERROR(Data!$N$31/Data!$I$31,"n/a") -> 0.023294942 | J16: =IFERROR(Data!$L$31/Data!$I$31,"n/a") -> 0.0037256773 | K16: =IFERROR(Data!$Q$31/Data!$I$31,"n/a") -> -0.0074175456 | L16: =IFERROR(Data!$N$31/AVERAGE(Data!$S$31,Data!$AN$31),"n/a") -> 0.028150486 | M16: =IFERROR(Data!$Q$31/AVERAGE(Data!$U$31,Data!$AP$31),"n/a") -> -0.029347637 | N16: =IFERROR(Data!$Q$31/AVERAGE(Data!$S$31,Data!$AN$31),"n/a") -> -0.0089636417 | O16: =IFERROR(Data!$I$31/AVERAGE(Data!$S$31,Data!$AN$31),"n/a") -> 1.2084377 | P16: =IFERROR(Data!$T$31/Data!$S$31,"n/a") -> 0.7028933 | Q16: =IFERROR(Data!$Z$31/Data!$U$31,"n/a") -> 1.7140812 | R16: =IFERROR(IF(Data!$N$31<=0,"n.m.",(Data!$Z$31-Data!$W$31)/Data!$N$31),"n/a") -> 12.157031 | S16: =IFERROR(IF(Data!$O$31<=0,"n/a",Data!$L$31/Data!$O$31),"n/a") -> 0.23191332 | T16: =IFERROR(Data!$X$31/Data!$Y$31,"n/a") -> 0.92327617 | U16: =IFERROR(Data!$AA$31/Data!$I$31,"n/a") -> 0.059303975 | V16: =IFERROR(IF(Data!$N$31<=0,"n.m.",Data!$AA$31/Data!$N$31),"n/a") -> 2.5457876 | W16: =IFERROR(Data!$AB$31/Data!$I$31,"n/a") -> 0.014571555 | X16: =IFERROR((Data!$AA$31-Data!$AB$31)/Data!$I$31,"n/a") -> 0.044732419 | Y16: =(Data!$AA$31-Data!$AB$31)/Data!$H$31/1000 -> 0.26502595
A18: Peer median - all peers | D18: =IFERROR(MEDIAN(D10:D16),"n/a") -> 6.306106 | E18: =IFERROR(MEDIAN(E10:E16),"n/a") -> 7.3251593 | F18: =IFERROR(MEDIAN(F10:F16),"n/a") -> 0.0055467355 | G18: =IFERROR(MEDIAN(G10:G16),"n/a") -> -0.066103164 | H18: =IFERROR(MEDIAN(H10:H16),"n/a") -> 0.19657896 | I18: =IFERROR(MEDIAN(I10:I16),"n/a") -> 0.15497383 | J18: =IFERROR(MEDIAN(J10:J16),"n/a") -> 0.08606866 | K18: =IFERROR(MEDIAN(K10:K16),"n/a") -> 0.064019698 | ... Y18: =IFERROR(MEDIAN(Y10:Y16),"n/a") -> 0.031384346
A19: Peer high - all peers | D19: =IFERROR(MAX(D10:D16),"n/a") -> 29.602304 | E19: =IFERROR(MAX(E10:E16),"n/a") -> 39.523702 | F19: =IFERROR(MAX(F10:F16),"n/a") -> 0.1569079 | G19: =IFERROR(MAX(G10:G16),"n/a") -> 0.15036301 | H19: =IFERROR(MAX(H10:H16),"n/a") -> 0.3852989 | I19: =IFERROR(MAX(I10:I16),"n/a") -> 0.18111561 | J19: =IFERROR(MAX(J10:J16),"n/a") -> 0.12478239 | K19: =IFERROR(MAX(K10:K16),"n/a") -> 0.098302928 | ... Y19: =IFERROR(MAX(Y10:Y16),"n/a") -> 2.4947003
A20: Peer low - all peers | D20: =IFERROR(MIN(D10:D16),"n/a") -> 3.4566079 | E20: =IFERROR(MIN(E10:E16),"n/a") -> 4.7459624 | F20: =IFERROR(MIN(F10:F16),"n/a") -> -0.044165778 | G20: =IFERROR(MIN(G10:G16),"n/a") -> -0.52411022 | H20: =IFERROR(MIN(H10:H16),"n/a") -> 0.025153045 | I20: =IFERROR(MIN(I10:I16),"n/a") -> 0.023294942 | J20: =IFERROR(MIN(J10:J16),"n/a") -> -0.011816193 | K20: =IFERROR(MIN(K10:K16),"n/a") -> -0.092997812 | ... Y20: =IFERROR(MIN(Y10:Y16),"n/a") -> -0.22473264
A21: Peer median - Global majors | D21: =IFERROR(MEDIAN(D10:D12),"n/a") -> 29.336343 | E21: =IFERROR(MEDIAN(E10:E12),"n/a") -> 38.412271 | F21: =IFERROR(MEDIAN(F10:F12),"n/a") -> -0.031677084 | G21: =IFERROR(MEDIAN(G10:G12),"n/a") -> -0.071913892 | H21: =IFERROR(MEDIAN(H10:H12),"n/a") -> 0.27004463 | I21: =IFERROR(MEDIAN(I10:I12),"n/a") -> 0.16578178 | J21: =IFERROR(MEDIAN(J10:J12),"n/a") -> 0.08606866 | K21: =IFERROR(MEDIAN(K10:K12),"n/a") -> 0.064019698 | ... Y21: =IFERROR(MEDIAN(Y10:Y12),"n/a") -> 2.03386
A22: Peer median - China tyre producers | D22: =IFERROR(MEDIAN(D13:D15),"n/a") -> 5.160953 | E22: =IFERROR(MEDIAN(E13:E15),"n/a") -> 6.6454068 | F22: =IFERROR(MEDIAN(F13:F15),"n/a") -> 0.14524131 | G22: =IFERROR(MEDIAN(G13:G15),"n/a") -> -0.016906064 | H22: =IFERROR(MEDIAN(H13:H15),"n/a") -> 0.19657896 | I22: =IFERROR(MEDIAN(I13:I15),"n/a") -> 0.15497383 | J22: =IFERROR(MEDIAN(J13:J15),"n/a") -> 0.10626676 | K22: =IFERROR(MEDIAN(K13:K15),"n/a") -> 0.092255712 | ... Y22: =IFERROR(MEDIAN(Y13:Y15),"n/a") -> -0.089624492
A24: Anchor (Pirelli) minus all-peer median | D24: =IFERROR(D8-D18,"n/a") -> 1.3419267 | E24: =IFERROR(E8-E18,"n/a") -> 7.7461533 | F24: =IFERROR(F8-F18,"n/a") -> -0.0051284771 | G24: =IFERROR(G8-G18,"n/a") -> 0.058725599 | H24: =IFERROR(H8-H18,"n/a") -> n/a | I24: =IFERROR(I8-I18,"n/a") -> 0.061196342 | J24: =IFERROR(J8-J18,"n/a") -> 0.045451757 | K24: =IFERROR(K8-K18,"n/a") -> 0.01429844 | ... Y24: =IFERROR(Y8-Y18,"n/a") -> 1.0159509

Sheet H1-2026 momentum
A1: Latest interim read-through: H1 2026 vs H1 2025 (cumulative six months, reporting currency, millions)
A2: Available for China A-share companies and Sinofert from their H1 2026 reports (published Aug 2026). Sinochem Energy, Syngenta AG and Pirelli interim items are in 'Group context'.
A4: Entity | B4: Sector | C4: Role | D4: Revenue H1-26 | E4: Revenue H1-25 | F4: Revenue YoY | G4: Net income H1-26 | H4: Net income H1-25 | I4: Net income change | J4: Net margin H1-26 | K4: Net margin H1-25
A5: Sinopec Corp | B5: Energy | C5: Peer | D5: 1436561 | E5: 1409052 | F5: =IFERROR(D5/E5-1,"n/a") -> 0.019523055 | G5: 29993 | H5: 23560 | I5: =G5-H5 -> 6433 | J5: =IFERROR(G5/D5,"n/a") -> 0.020878334 | K5: =IFERROR(H5/E5,"n/a") -> 0.016720462
A6: PetroChina | B6: Energy | C6: Peer | D6: 1527491 | E6: 1450021 | F6: =IFERROR(D6/E6-1,"n/a") -> 0.053426812 | G6: 115111 | H6: 94844 | I6: =G6-H6 -> 20267 | J6: =IFERROR(G6/D6,"n/a") -> 0.075359527 | K6: =IFERROR(H6/E6,"n/a") -> 0.065408708
A7: Hengli Petrochemical | B7: Energy | C7: Peer | D7: 98257.702 | E7: 103943.52 | F7: =IFERROR(D7/E7-1,"n/a") -> -0.05470107 | G7: 7204.218 | H7: 3050.933 | I7: =G7-H7 -> 4153.285 | J7: =IFERROR(G7/D7,"n/a") -> 0.073319626 | K7: =IFERROR(H7/E7,"n/a") -> 0.029351833
A8: Rongsheng Petrochemical | B8: Energy | C8: Peer | D8: 129406.71 | E8: 148629.35 | F8: =IFERROR(D8/E8-1,"n/a") -> -0.12933271 | G8: 9259.822 | H8: 1666.254 | I8: =G8-H8 -> 7593.568 | J8: =IFERROR(G8/D8,"n/a") -> 0.071555963 | K8: =IFERROR(H8/E8,"n/a") -> 0.0112108
A9: Sinopec Shanghai Petrochemical | B9: Energy | C9: Peer | D9: 38991.994 | E9: 39523.226 | F9: =IFERROR(D9/E9-1,"n/a") -> -0.013441008 | G9: 283.394 | H9: -460.914 | I9: =G9-H9 -> 744.308 | J9: =IFERROR(G9/D9,"n/a") -> 0.0072680048 | K9: =IFERROR(H9/E9,"n/a") -> -0.011661852
A10: ADAMA | B10: Agriculture | C10: Sinochem | D10: 14476.54 | E10: 15024.2 | F10: =IFERROR(D10/E10-1,"n/a") -> -0.036451858 | G10: 432.567 | H10: -80.352 | I10: =G10-H10 -> 512.919 | J10: =IFERROR(G10/D10,"n/a") -> 0.029880552 | K10: =IFERROR(H10/E10,"n/a") -> -0.0053481716
A11: Yangnong Chemical | B11: Agriculture | C11: Sinochem | D11: 6605.877 | E11: 6233.521 | F11: =IFERROR(D11/E11-1,"n/a") -> 0.059734458 | G11: 790.096 | H11: 806.171 | I11: =G11-H11 -> -16.075 | J11: =IFERROR(G11/D11,"n/a") -> 0.11960501 | K11: =IFERROR(H11/E11,"n/a") -> 0.12932835
A12: Sinofert | B12: Agriculture | C12: Sinochem | D12: 16280.966 | E12: 14714.813 | F12: =IFERROR(D12/E12-1,"n/a") -> 0.10643377 | G12: 1164.797 | H12: 1107.657 | I12: =G12-H12 -> 57.14 | J12: =IFERROR(G12/D12,"n/a") -> 0.071543482 | K12: =IFERROR(H12/E12,"n/a") -> 0.075274963
A13: Jiangshan Agrochemical | B13: Agriculture | C13: Peer | D13: 3760.004 | E13: 3359.091 | F13: =IFERROR(D13/E13-1,"n/a") -> 0.11935163 | G13: 357.804 | H13: 337.352 | I13: =G13-H13 -> 20.452 | J13: =IFERROR(G13/D13,"n/a") -> 0.095160537 | K13: =IFERROR(H13/E13,"n/a") -> 0.10042955
A14: Lier Chemical | B14: Agriculture | C14: Peer | D14: 4815.947 | E14: 4506.893 | F14: =IFERROR(D14/E14-1,"n/a") -> 0.068573627 | G14: 294.234 | H14: 327.278 | I14: =G14-H14 -> -33.044 | J14: =IFERROR(G14/D14,"n/a") -> 0.061095772 | K14: =IFERROR(H14/E14,"n/a") -> 0.072617211
A15: Yuntianhua | B15: Agriculture | C15: Peer | D15: 22820.982 | E15: 25055.713 | F15: =IFERROR(D15/E15-1,"n/a") -> -0.089190477 | G15: 3134.07 | H15: 3046.242 | I15: =G15-H15 -> 87.828 | J15: =IFERROR(G15/D15,"n/a") -> 0.13733283 | K15: =IFERROR(H15/E15,"n/a") -> 0.12157874
A16: Salt Lake Potash (青海盐湖) | B16: Agriculture | C16: Peer | D16: 13052.166 | E16: 7256.07 | F16: =IFERROR(D16/E16-1,"n/a") -> 0.79879273 | G16: 7250.13 | H16: 2862.478 | I16: =G16-H16 -> 4387.652 | J16: =IFERROR(G16/D16,"n/a") -> 0.55547332 | K16: =IFERROR(H16/E16,"n/a") -> 0.39449426
... A21: Hainan Rubber | B21: Rubber | C21: Peer | D21: 15122.869 | E21: 20271.943 | F21: =IFERROR(D21/E21-1,"n/a") -> -0.25400002 | G21: -268.504 | H21: -257.954 | I21: =G21-H21 -> -10.55 | J21: =IFERROR(G21/D21,"n/a") -> -0.017754832 | K21: =IFERROR(H21/E21,"n/a") -> -0.012724681
A23: Source: Eastmoney F10 (H1 2026 and H1 2025 cumulative income statements as filed). Sinochem Energy has not published an H1 2026 statement that I could locate; see 'Group context' for Sinochem Corp Q1 2026.

Sheet Group context
A1: Group context - what is disclosed at Sinochem level
A2: Sinochem Holdings (中国中化控股) is unlisted and does not publish a consolidated sector split. The tables below are the disclosed building blocks. RMB 100m (亿元) unless stated.
A4: 1. 中国中化股份有限公司 (Sinochem Corp, main financing platform of Sinochem Holdings) - consolidated
A5: Item (RMB 100m) | B5: FY2023 | C5: FY2024 | D5: FY2025 | E5: Q1 2026
A6: Revenue | B6: 6170.73 | C6: 6083.8 | D6: 5649.67 | E6: 1195.77
A7: Gross margin (%) | B7: 4.93 | C7: 4.72 | D7: 4.61 | E7: 5.42
A8: Operating business profit | B8: 31.68 | C8: 32.88 | D8: 13.62 | E8: 5.41
A9: Asset impairment loss | B9: -70.59 | C9: -46.16 | D9: -31.45 | E9: -0.95
A10: Investment income | B10: 54.12 | C10: 121.87 | D10: 73.13 | E10: 2
A11: Fair-value change gain/(loss) | B11: -4.93 | C11: -18.42 | D11: 42.47 | E11: 27.55
A12: Total profit | B12: 3.5 | C12: 86.59 | D12: 86.68 | E12: 42.19
A13: Total assets | B13: 8565.46 | C13: 9187.36 | D13: 9685.5 | E13: 10241.52
A14: Total debt | B14: 4110.07 | C14: 4632.81 | D14: 4839.4 | E14: 5656.67
A15: Total liabilities | B15: 5781.43 | C15: 6078.22 | D15: 6120.83 | E15: 6492.67
A16: Owner's equity (incl. RMB 98bn perpetuals at 1Q25) | B16: 2784.03 | C16: 3109.14 | D16: 3564.67 | E16: 3748.85
A17: Total capitalisation ratio (%) | B17: 66.56 | C17: 68.56 | D17: 68.21 | E17: 69.87
A18: Operating cash flow | B18: 269.02 | C18: 92.57 | D18: 193.67 | E18: -172.41
A19: Total debt / EBITDA (x) | B19: 20.23 | C19: 14.12 | D19: 15.28
A20: EBITDA interest cover (x) | B20: 1.79 | C20: 2.44 | D20: 2.52
A21: Source: 中诚信国际 2026 tracking rating report for 中国中化股份有限公司 (SSE, 2026-06-23), table 7; 2025 report for FY2023 comparatives.
A23: 2. Sinochem Corp segment revenue and gross margin (RMB 100m, %)
A24: Segment | B24: Rev FY2023 | C24: GM% FY2023 | D24: Rev FY2024 | E24: GM% FY2024 | F24: Rev FY2025 | G24: GM% FY2025
A25: Petrochemicals (石油化工) | B25: 4573.07 | C25: 2.9 | D25: 4300.8 | E25: 2.17 | F25: 3959.51 | G25: 1.81
A26: Materials science (材料科学) | B26: 547 | C26: 4.88 | D26: 817.95 | E26: 6.86 | F26: 745.79 | G26: 7.65
A27: Urban operations (城市运营) | B27: 716.66 | C27: 12.22 | D27: 590.47 | E27: 14.57 | F27: 593.71 | G27: 15.86
A28: Source: same rating reports, table 6. Agriculture and rubber/tyre sit in the ChemChina line, outside Sinochem Corp's consolidation.
A30: 3. Sinochem Energy (中化能源) revenue by segment (RMB 100m)
A31: Segment | B31: FY2023 | C31: FY2024 | D31: FY2025
A32: Oil trading & services | B32: 3418.87 | C32: 3048.98 | D32: 2736.92
A33: Oil products & chemicals sales | B33: 1796.1 | C33: 1725.78 | D33: 1606.52
A34: Refining & chemicals | B34: 822.12 | C34: 734.93 | D34: 612.66
A35: Storage & logistics | B35: 17.7 | C35: 17.76 | D35: 24.2
A36: Other | B36: 11.24 | C36: 8.1 | D36: 7.61
A37: Inter-segment elimination | B37: -1483.96 | C37: -1266.53 | D37: -1046.8
A38: Total revenue | B38: 4582.06 | C38: 4269.03 | D38: 3941.1
A39: Net profit/(loss) | C39: -31.82 | D39: -16.83
A40: Source: rating report table 1 (Sinochem Energy annual reports); FY2025 net loss ties to audited statements (RMB -1,682.7m).
A42: 4. Syngenta Group headline (USD bn) - consolidated, unaudited
A43: Item | B43: FY2024 | C43: FY2025 | D43: H1 2025 | E43: H1 2026
A44: Sales | B44: 28.8 | C44: 28.4 | E44: 12.2
A45: EBITDA | B45: 3.9 | C45: 4.4 | E45: 2.4
A46: EBITDA margin (%) | B46: 13.5 | C46: 15.4 | D46: 18.6 | E46: 19.5
A47: Syngenta Crop Protection sales | B47: 13.2 | C47: 13.7 | E47: 6.6
A48: Seeds sales | B48: 4.8 | C48: 4.8
A49: ADAMA sales | B49: 4.1 | C49: 4.1
A50: Syngenta Group China sales | B50: 9.2 | C50: 8.3
A51: Source: Syngenta Group FY2025 results (2026-03-31) and H1 2026 results (2026-08-27). Sinofert was transferred to Sinochem Hong Kong on 23 Dec 2025 and is not consolidated from Jan 2026; H1 2026 is like-for-like.
A53: 5. Pirelli - latest data points (EUR m)
A54: Item | B54: FY2024 | C54: FY2025 | D54: H1 2025 | E54: H1 2026
A55: Revenue | B55: 6773.3 | C55: 6776.2 | D55: 3498.6 | E55: 3494.5
A56: Adjusted EBIT | B56: 1060.5 | C56: 1081.4 | E56: 557.8
A57: Net income | B57: 501.1 | C57: 530.7 | E57: 299
A58: Net financial position (debt) | B58: 1925.8 | C58: 1102 | E58: 1915.9
A59: Source: Pirelli FY2025 and H1 2026 results releases. H1 2026 net income was +13.3% year on year. Directors Zhang Haitao, Xi Xiaohong and Wang Kun voted against the H1 2026 report over its declaration of control by MTP S.p.A. Sinochem (via MPI Italy) held ~34.1% at Dec 2025 (AR 2025).

Sheet Data
A1: Standardised financial inputs (millions of reporting currency)
A2: Blue = hard-coded from filings; black = formula. EBIT = operating profit before financing as reported (China GAAP: operating profit + net finance expense); EBITDA = EBIT + D&A with no add-back for impairments/one-offs; Debt = borrowings + bonds + lease liabilities; Capex = cash paid for PP&E and intangibles.
I3: FY2025 (year to 31-Dec-2025) | AD3: FY2024 (year to 31-Dec-2024)
A4: Key | B4: Entity | C4: Sector | D4: Sub-segment | E4: Role | F4: Currency | G4: Listing / ownership | H4: LC per USD | I4: Revenue | J4: Cost of sales | K4: Gross profit | L4: EBIT | M4: D&A | N4: EBITDA | O4: Interest expense | P4: Pre-tax profit | Q4: Net income | R4: Net income (parent) | S4: Total assets | T4: Total liabilities | U4: Total equity | V4: Parent equity | W4: Cash | X4: Current assets | Y4: Current liabilities | Z4: Debt (incl. leases) | AA4: Operating cash flow | AB4: Capex | AC4: Taxes & surcharges | AD4: Revenue | AE4: Cost of sales | AF4: Gross profit | AG4: EBIT | AH4: D&A | AI4: EBITDA | AJ4: Interest expense | AK4: Pre-tax profit | AL4: Net income | AM4: Net income (parent) | AN4: Total assets | AO4: Total liabilities | AP4: Total equity | AQ4: Parent equity | AR4: Cash | AS4: Current assets | AT4: Current liabilities | AU4: Debt (incl. leases) | AV4: Operating cash flow | AW4: Capex | AX4: Taxes & surcharges | AY4: Notes | AZ4: Source
A5: SCE | B5: Sinochem Energy (中化能源) | C5: Energy | D5: Trading, refining & marketing | E5: Sinochem | F5: CNY | G5: Unlisted (bond issuer) | H5: =VLOOKUP(F5,FX!$A$5:$B$8,2,FALSE()) -> 7.129 | I5: 394110.34 | J5: 387812.6 | K5: =IF(J5="","",I5-J5) -> 6297.74 | L5: -416.17 | M5: 5414.5 | N5: =L5+M5 -> 4998.33 | O5: 1086.33 | P5: -937.97 | Q5: -1682.75 | R5: -1730.96 | S5: 105437.29 | T5: 68503.08 | U5: 36934.21 | V5: 35684.15 | W5: 5870.23 | X5: 51155.55 | Y5: 56071.97 | Z5: 28128.19 | AA5: 6681.61 | AB5: 1526.94 | AC5: 3601.87 | AD5: 426902.93 | AE5: 418942.94 | AF5: =IF(AE5="","",AD5-AE5) -> 7959.99 | AG5: -2219.46 | AH5: 5413.226 | AI5: =AG5+AH5 -> 3193.766 | AJ5: 1127.09 | AK5: -2923.94 | AL5: -3182.19 | AM5: -3265.62 | AN5: 102314.8 | AO5: 65231.89 | AP5: 37082.92 | AQ5: 35817.85 | AR5: 3431.37 | AS5: 47001.62 | AT5: 52991.94 | AU5: 26254.21 | AV5: 4793.61 | AW5: 2433.08 | AX5: 5582.96 | AY5: Operating arm of Sinochem Corp's petrochemical segment; 15 mt/y refining capacity centred on Quanzhou | AZ5: Audited FY2025 consolidated FS (天职国际), SSE bond disclosure
A6: SNP | B6: Sinopec Corp | C6: Energy | D6: Integrated major | E6: Peer | F6: CNY | G6: 600028.SH / 0386.HK | H6: =VLOOKUP(F6,FX!$A$5:$B$8,2,FALSE()) -> 7.129 | I6: 2783583 | J6: 2341383 | K6: =IF(J6="","",I6-J6) -> 442200 | L6: 55124 | M6: 116363 | N6: =L6+M6 -> 171487 | O6: 19247 | P6: 43184 | Q6: 35250 | R6: 31809 | S6: 2155617 | T6: 1165845 | U6: 989772 | V6: 830324 | W6: 152318 | X6: 522741 | Y6: 698553 | Z6: 532683 | AA6: 162496 | AB6: 133625 | AC6: 252435 | AD6: 3074562 | AE6: 2598935 | AF6: =IF(AE6="","",AD6-AE6) -> 475627 | AG6: 83431 | AH6: 110243 | AI6: =AG6+AH6 -> 193674 | AJ6: 18601 | AK6: 70513 | AL6: 57547 | AM6: 50313 | AN6: 2084771 | AO6: 1108478 | AP6: 976293 | AQ6: 819922 | AR6: 146799 | AS6: 524515 | AT6: 673237 | AU6: 478233 | AV6: 149360 | AW6: 139206 | AX6: 267315 | AZ6: Eastmoney F10 (filed annual reports)
A7: PTR | B7: PetroChina | C7: Energy | D7: Integrated major | E7: Peer | F7: CNY | G7: 601857.SH / 0857.HK | H7: =VLOOKUP(F7,FX!$A$5:$B$8,2,FALSE()) -> 7.129 | I7: 2864469 | J7: 2246121 | K7: =IF(J7="","",I7-J7) -> 618348 | L7: 246632 | M7: 237608 | N7: =L7+M7 -> 484240 | O7: 17567 | P7: 226149 | Q7: 172005 | R7: 157302 | S7: 2863458 | T7: 1032684 | U7: 1830774 | V7: 1617287 | W7: 238909 | X7: 599269 | Y7: 540229 | Z7: 356407 | AA7: 412510 | AB7: 292789 | AC7: 244276 | AD7: 2937981 | AE7: 2275223 | AF7: =IF(AE7="","",AD7-AE7) -> 662758 | AG7: 267838 | AH7: 231331 | AI7: =AG7+AH7 -> 499169 | AJ7: 20731 | AK7: 241502 | AL7: 183747 | AM7: 164676 | AN7: 2753007 | AO7: 1043144 | AP7: 1709863 | AQ7: 1515371 | AR7: 216246 | AS7: 590844 | AT7: 637317 | AU7: 355752 | AV7: 406532 | AW7: 302651 | AX7: 266012 | AZ7: Eastmoney F10 (filed annual reports)
A8: HLP | B8: Hengli Petrochemical | C8: Energy | D8: Private integrated refining-chemicals | E8: Peer | F8: CNY | G8: 600346.SH | H8: =VLOOKUP(F8,FX!$A$5:$B$8,2,FALSE()) -> 7.129 | I8: 201087.3 | J8: 174568.47 | K8: =IF(J8="","",I8-J8) -> 26518.834 | L8: 13690.961 | M8: 12396.317 | N8: =L8+M8 -> 26087.278 | O8: 4060.787 | P8: 9420.392 | Q8: 7074.154 | R8: 7074.582 | S8: 262258.99 | T8: 195467.72 | U8: 66791.271 | V8: 66773.314 | W8: 29452.553 | X8: 71169.625 | Y8: 127742.87 | Z8: 151639.57 | AA8: 31121.789 | AB8: 7111.242 | AC8: 8968.754 | AD8: 236400.58 | AE8: 212983.33 | AF8: =IF(AE8="","",AD8-AE8) -> 23417.244 | AG8: 13783.138 | AH8: 11038.417 | AI8: =AG8+AH8 -> 24821.555 | AJ8: 4342.84 | AK8: 8819.786 | AL8: 7053.007 | AM8: 7043.568 | AN8: 273082.87 | AO8: 209665.31 | AP8: 63417.563 | AQ8: 63399.177 | AR8: 30836.641 | AS8: 73269.556 | AT8: 130879.31 | AU8: 166517.34 | AV8: 22732.565 | AW8: 21814.134 | AX8: 6423.608 | AZ8: Eastmoney F10 (filed annual reports)
A9: RSP | B9: Rongsheng Petrochemical | C9: Energy | D9: Private integrated refining-chemicals | E9: Peer | F9: CNY | G9: 002493.SZ | H9: =VLOOKUP(F9,FX!$A$5:$B$8,2,FALSE()) -> 7.129 | I9: 308622.32 | J9: 270923.59 | K9: =IF(J9="","",I9-J9) -> 37698.731 | L9: 8957.646 | M9: 17360.957 | N9: =L9+M9 -> 26318.603 | O9: 5829.241 | P9: 3290.172 | Q9: 3248.859 | R9: 848.314 | S9: 386633.12 | T9: 289641.28 | U9: 96991.839 | V9: 43593.523 | W9: 13499.669 | X9: 64953.645 | Y9: 165121.36 | Z9: 208122.2 | AA9: 45406.467 | AB9: 42681.846 | AC9: 24180.177 | AD9: 326475.16 | AE9: 288990.54 | AF9: =IF(AE9="","",AD9-AE9) -> 37484.619 | AG9: 9135.613 | AH9: 15253.928 | AI9: =AG9+AH9 -> 24389.541 | AJ9: 7077.036 | AK9: 1905.717 | AL9: 2125.32 | AM9: 724.485 | AN9: 377845.94 | AO9: 283021.81 | AP9: 94824.13 | AQ9: 43859.172 | AR9: 14833.385 | AS9: 78302.92 | AT9: 161555.86 | AU9: 202103.43 | AV9: 34609.127 | AW9: 31582.216 | AX9: 24897.44 | AZ9: Eastmoney F10 (filed annual reports)
A10: SSP | B10: Sinopec Shanghai Petrochemical | C10: Energy | D10: Refining & petrochemicals | E10: Peer | F10: CNY | G10: 600688.SH / 0338.HK | H10: =VLOOKUP(F10,FX!$A$5:$B$8,2,FALSE()) -> 7.129 | I10: 75563.186 | J10: 63584.794 | K10: =IF(J10="","",I10-J10) -> 11978.392 | L10: -1590.727 | M10: 3822.59 | N10: =L10+M10 -> 2231.863 | O10: 16.326 | P10: -1488.866 | Q10: -1430.352 | R10: -1432.595 | S10: 42556.634 | T10: 18930.32 | U10: 23626.314 | V10: 23132.313 | W10: 7555.275 | X10: 15176.605 | Y10: 16260.44 | Z10: 2620.442 | AA10: 1993.33 | AB10: 3168.558 | AC10: 11505.216 | AD10: 87132.82 | AE10: 72045.29 | AF10: =IF(AE10="","",AD10-AE10) -> 15087.53 | AG10: 294.81 | AH10: 3851.838 | AI10: =AG10+AH10 -> 4146.648 | AJ10: 114.987 | AK10: 428.835 | AL10: 322.517 | AM10: 316.5 | AN10: 41769.339 | AO10: 16624.844 | AP10: 25144.495 | AQ10: 25040.254 | AR10: 12096.477 | AS10: 20633.139 | AT10: 16289.047 | AU10: 1569.976 | AV10: 7740.447 | AW10: 1905.621 | AX10: 12777.797 | AZ10: Eastmoney F10 (filed annual reports)
A11: SYN | B11: Syngenta AG (global CP + Seeds) | C11: Agriculture | D11: Crop protection & seeds | E11: Sinochem | F11: USD | G11: Unlisted (Syngenta Group sub.) | H11: =VLOOKUP(F11,FX!$A$5:$B$8,2,FALSE()) -> 1 | I11: 16999 | J11: 10281 | K11: =IF(J11="","",I11-J11) -> 6718 | L11: 1229 | M11: 878 | N11: =L11+M11 -> 2107 | O11: 774 | P11: 613 | Q11: -152 | R11: -156 | S11: 30799 | T11: 23412 | U11: 7387 | V11: 7352 | W11: 677 | X11: 14922 | Y11: 14082 | Z11: 10531 | AA11: 1526 | AB11: 1217 | AD11: 16981 | AE11: 10887 | AF11: =IF(AE11="","",AD11-AE11) -> 6094 | AG11: 1431 | AH11: 861 | AI11: =AG11+AH11 -> 2292 | AJ11: 903 | AK11: 694 | AL11: 261 | AM11: 269 | AN11: 29445 | AO11: 22184 | AP11: 7261 | AQ11: 7246 | AR11: 1025 | AS11: 15100 | AT11: 12208 | AU11: 10792 | AV11: 2571 | AW11: 1364 | AY11: Excludes ADAMA, Syngenta Group China, Yangnong, Sinofert; includes $792m litigation provisions in 2025 | AZ11: Syngenta AG Financial Report 2025 (IFRS)
A12: ADM | B12: ADAMA | C12: Agriculture | D12: Crop protection (generics) | E12: Sinochem | F12: CNY | G12: 000553.SZ | H12: =VLOOKUP(F12,FX!$A$5:$B$8,2,FALSE()) -> 7.129 | I12: 28944.586 | J12: 21321.853 | K12: =IF(J12="","",I12-J12) -> 7622.733 | L12: 1335.329 | M12: 2103.733 | N12: =L12+M12 -> 3439.062 | O12: 1021.329 | P12: -699.598 | Q12: -1045.719 | R12: -1045.719 | S12: 48463.962 | T12: 30888.536 | U12: 17575.426 | V12: 17575.426 | W12: 3450.3 | X12: 25561.185 | Y12: 22385.719 | Z12: 17651.811 | AA12: 4048.693 | AB12: 1213.66 | AC12: 102.238 | AD12: 29488.046 | AE12: 22748.925 | AF12: =IF(AE12="","",AD12-AE12) -> 6739.121 | AG12: -412.258 | AH12: 2165.671 | AI12: =AG12+AH12 -> 1753.413 | AJ12: 1054.856 | AK12: -2124.302 | AL12: -2903.204 | AM12: -2903.204 | AN12: 50059.777 | AO12: 31068.683 | AP12: 18991.094 | AQ12: 18991.094 | AR12: 3630.608 | AS12: 25917.39 | AT12: 18013.457 | AU12: 16076.63 | AV12: 3760.631 | AW12: 1423.51 | AX12: 100.327 | AY12: Syngenta Group sub. | AZ12: Eastmoney F10 (filed annual reports)
A13: YNG | B13: Yangnong Chemical | C13: Agriculture | D13: Crop protection (AI & intermediates) | E13: Sinochem | F13: CNY | G13: 600486.SH | H13: =VLOOKUP(F13,FX!$A$5:$B$8,2,FALSE()) -> 7.129 | I13: 11870.428 | J13: 9259.871 | K13: =IF(J13="","",I13-J13) -> 2610.557 | L13: 1460.232 | M13: 1602.382 | N13: =L13+M13 -> 3062.614 | O13: 41.387 | P13: 1511.305 | Q13: 1286.584 | R13: 1285.954 | S13: 18186.516 | T13: 6712.428 | U13: 11474.088 | V13: 11466.923 | W13: 1331.604 | X13: 8577.956 | Y13: 6223.578 | Z13: 910.849 | AA13: 2216.729 | AB13: 961.328 | AC13: 45.565 | AD13: 10434.773 | AE13: 8023.209 | AF13: =IF(AE13="","",AD13-AE13) -> 2411.564 | AG13: 1348.266 | AH13: 720.014 | AI13: =AG13+AH13 -> 2068.28 | AJ13: 64.615 | AK13: 1406.122 | AL13: 1202.956 | AM13: 1202.08 | AN13: 17664.818 | AO13: 7122.252 | AP13: 10542.567 | AQ13: 10535.931 | AR13: 1618.027 | AS13: 7181.951 | AT13: 6628.99 | AU13: 1193.231 | AV13: 2155.313 | AW13: 1835.194 | AX13: 35.29 | AY13: Syngenta Group sub. | AZ13: Eastmoney F10 (filed annual reports)
A14: SIF | B14: Sinofert | C14: Agriculture | D14: Fertilizer distribution | E14: Sinochem | F14: CNY | G14: 0297.HK | H14: =VLOOKUP(F14,FX!$A$5:$B$8,2,FALSE()) -> 7.129 | I14: 23263.105 | J14: 20369.787 | K14: =IF(J14="","",I14-J14) -> 2893.318 | L14: 1498.025 | M14: 487.134 | N14: =L14+M14 -> 1985.159 | O14: 45.083 | P14: 1548.747 | Q14: 1273.304 | R14: 1259.377 | S14: 23588.35 | T14: 12133.883 | U14: 11454.467 | V14: 11223.575 | W14: 2928.295 | X14: 13991.024 | Y14: 11302.442 | Z14: 1507.279 | AA14: 1993.785 | AB14: 343.165 | AD14: 21264.854 | AE14: 18721.016 | AF14: =IF(AE14="","",AD14-AE14) -> 2543.838 | AG14: 1057.943 | AH14: 462.27 | AI14: =AG14+AH14 -> 1520.213 | AJ14: 57.379 | AK14: 1224.01 | AL14: 1074.991 | AM14: 1061.48 | AN14: 21417.216 | AO14: 10782.098 | AP14: 10635.118 | AQ14: 10417.266 | AR14: 3103.537 | AS14: 12390.919 | AT14: 9612.985 | AU14: 1870.216 | AV14: 1042.228 | AW14: 275.603 | AY14: Spun out of Syngenta Group to Sinochem HK on 23 Dec 2025 | AZ14: Eastmoney HK F10 (filed annual reports)
A15: CTV | B15: Corteva | C15: Agriculture | D15: Crop protection & seeds | E15: Peer | F15: USD | G15: CTVA (NYSE) | H15: =VLOOKUP(F15,FX!$A$5:$B$8,2,FALSE()) -> 1 | I15: 17401 | J15: 9172 | K15: =IF(J15="","",I15-J15) -> 8229 | L15: 1868 | M15: 1203 | N15: =L15+M15 -> 3071 | O15: 180 | P15: 1688 | Q15: 1105 | R15: 1094 | S15: 42845 | T15: 18459 | U15: 24386 | V15: 24144 | W15: 4521 | X15: 17335 | Y15: 12125 | Z15: 2580 | AA15: 3406 | AB15: 591 | AD15: 16908 | AE15: 9529 | AF15: =IF(AE15="","",AD15-AE15) -> 7379 | AG15: 1508 | AH15: 1227 | AI15: =AG15+AH15 -> 2735 | AJ15: 233 | AK15: 1275 | AL15: 919 | AM15: 907 | AN15: 40825 | AO15: 16795 | AP15: 24030 | AQ15: 23789 | AR15: 3106 | AS15: 15097 | AT15: 10386 | AU15: 2703 | AV15: 2145 | AW15: 597 | AY15: Pre-separation consolidated FY2025 | AZ15: SEC EDGAR XBRL + Eastmoney US
A16: FMC | B16: FMC Corp | C16: Agriculture | D16: Crop protection | E16: Peer | F16: USD | G16: FMC (NYSE) | H16: =VLOOKUP(F16,FX!$A$5:$B$8,2,FALSE()) -> 1 | I16: 3467.4 | J16: 2184.4 | K16: =IF(J16="","",I16-J16) -> 1283 | L16: -1628.3 | M16: 173.6 | N16: =L16+M16 -> -1454.7 | O16: 239.6 | P16: -1886.6 | Q16: -2237.4 | R16: -2238.9 | S16: 9687.2 | T16: 7588.3 | U16: 2098.9 | V16: 2071.5 | W16: 584.5 | X16: 4959 | Y16: 3755.3 | Z16: 4074.9 | AA16: -6.2 | AB16: 96.3 | AD16: 4246.1 | AE16: 2597.2 | AF16: =IF(AE16="","",AD16-AE16) -> 1648.9 | AG16: 506.5 | AH16: 176.3 | AI16: =AG16+AH16 -> 682.8 | AJ16: 235.8 | AK16: 252.5 | AL16: 341.6 | AM16: 341.1 | AN16: 11653.3 | AO16: 7144.5 | AP16: 4508.8 | AQ16: 4487.5 | AR16: 357.3 | AS16: 4958.3 | AT16: 3019.2 | AU16: 3365.3 | AV16: 736.7 | AW16: 67.9 | AY16: FY2025 net loss of $2.2bn | AZ16: SEC EDGAR XBRL + Eastmoney US
A17: JSA | B17: Jiangshan Agrochemical | C17: Agriculture | D17: Crop protection (AI) | E17: Peer | F17: CNY | G17: 600389.SH | H17: =VLOOKUP(F17,FX!$A$5:$B$8,2,FALSE()) -> 7.129 | I17: 5816.189 | J17: 4806.268 | K17: =IF(J17="","",I17-J17) -> 1009.921 | L17: 678.371 | M17: 243.77 | N17: =L17+M17 -> 922.141 | O17: 24.495 | P17: 658.457 | Q17: 526.495 | R17: 532.601 | S17: 9730.068 | T17: 5411.933 | U17: 4318.134 | V17: 3998.898 | W17: 875.157 | X17: 3820.616 | Y17: 3752.342 | Z17: 2407.056 | AA17: 295.414 | AB17: 1274.461 | AC17: 24.713 | AD17: 5431.591 | AE17: 4644.655 | AF17: =IF(AE17="","",AD17-AE17) -> 786.936 | AG17: 306.985 | AH17: 433.369 | AI17: =AG17+AH17 -> 740.354 | AJ17: 22.054 | AK17: 315.73 | AL17: 227.784 | AM17: 224.399 | AN17: 8633.606 | AO17: 4698.794 | AP17: 3934.812 | AQ17: 3718.442 | AR17: 1132.445 | AS17: 4075.596 | AT17: 3407.786 | AU17: 1611.543 | AV17: 347.242 | AW17: 1255.458 | AX17: 18.878 | AZ17: Eastmoney F10 (filed annual reports)
A18: LCH | B18: Lier Chemical | C18: Agriculture | D18: Crop protection (AI & formulations) | E18: Peer | F18: CNY | G18: 002258.SZ | H18: =VLOOKUP(F18,FX!$A$5:$B$8,2,FALSE()) -> 7.129 | I18: 9007.754 | J18: 7303.94 | K18: =IF(J18="","",I18-J18) -> 1703.814 | L18: 806.071 | M18: 992.018 | N18: =L18+M18 -> 1798.089 | O18: 83.798 | P18: 693.912 | Q18: 580.715 | R18: 478.767 | S18: 16123.592 | T18: 6869.251 | U18: 9254.341 | V18: 7888.607 | W18: 1002.776 | X18: 5481.799 | Y18: 4181.669 | Z18: 3398.159 | AA18: 1296.665 | AB18: 1083.205 | AC18: 53.669 | AD18: 7310.882 | AE18: 6136.417 | AF18: =IF(AE18="","",AD18-AE18) -> 1174.465 | AG18: 382.493 | AH18: 821.882 | AI18: =AG18+AH18 -> 1204.375 | AJ18: 82.218 | AK18: 342.517 | AL18: 298.427 | AM18: 215.337 | AN18: 15648.478 | AO18: 6637.86 | AP18: 9010.617 | AQ18: 7726.588 | AR18: 1450.354 | AS18: 5673.23 | AT18: 4050.465 | AU18: 3368.128 | AV18: 312.504 | AW18: 1182.876 | AX18: 48.628 | AZ18: Eastmoney F10 (filed annual reports)
A19: NTR | B19: Nutrien | C19: Agriculture | D19: Crop nutrition & ag retail | E19: Peer | F19: USD | G19: NTR (NYSE/TSX) | H19: =VLOOKUP(F19,FX!$A$5:$B$8,2,FALSE()) -> 1 | I19: 26885 | J19: 18538 | K19: =IF(J19="","",I19-J19) -> 8347 | L19: 3736 | M19: 2369 | N19: =L19+M19 -> 6105 | O19: 687 | P19: 3049 | Q19: 2297 | R19: 2267 | S19: 52301 | T19: 26936 | U19: 25365 | V19: 25323 | W19: 701 | X19: 14749 | Y19: 11041 | Z19: 12019 | AA19: 4007 | AB19: 2005 | AD19: 25972 | AE19: 18442 | AF19: =IF(AE19="","",AD19-AE19) -> 7530 | AG19: 1856 | AH19: 2339 | AI19: =AG19+AH19 -> 4195 | AJ19: 720 | AK19: 1136 | AL19: 700 | AM19: 674 | AN19: 51840 | AO19: 27398 | AP19: 24442 | AQ19: 24407 | AR19: 853 | AS19: 13792 | AT19: 12045 | AU19: 12807 | AV19: 3535 | AW19: 2154 | AZ19: Nutrien FY2025 audited FS (40-F)
A20: MOS | B20: Mosaic | C20: Agriculture | D20: Crop nutrition | E20: Peer | F20: USD | G20: MOS (NYSE) | H20: =VLOOKUP(F20,FX!$A$5:$B$8,2,FALSE()) -> 1 | I20: 12052.4 | J20: 10150.5 | K20: =IF(J20="","",I20-J20) -> 1901.9 | L20: 821.5 | M20: 1049.9 | N20: =L20+M20 -> 1871.4 | O20: 241.5 | P20: 1212.9 | Q20: 575.4 | R20: 540.7 | S20: 24480.1 | T20: 12245.9 | U20: 12234.2 | V20: 12084.9 | W20: 276.6 | X20: 5237.5 | Y20: 3982.8 | Z20: 5053.9 | AA20: 824.8 | AB20: 1359.4 | AD20: 11122.8 | AE20: 9610.9 | AF20: =IF(AE20="","",AD20-AE20) -> 1511.9 | AG20: 621.5 | AH20: 1025.5 | AI20: =AG20+AH20 -> 1647 | AJ20: 230 | AK20: 315.4 | AL20: 202 | AM20: 174.9 | AN20: 22924 | AO20: 11309.3 | AP20: 11614.7 | AQ20: 11482.4 | AR20: 272.8 | AS20: 4498.3 | AT20: 4171.3 | AU20: 4224.7 | AV20: 1299.2 | AW20: 1251.8 | AZ20: SEC EDGAR XBRL + Eastmoney US
A21: YTH | B21: Yuntianhua | C21: Agriculture | D21: Phosphate fertilizer | E21: Peer | F21: CNY | G21: 600096.SH | H21: =VLOOKUP(F21,FX!$A$5:$B$8,2,FALSE()) -> 7.129 | I21: 48414.924 | J21: 38628.441 | K21: =IF(J21="","",I21-J21) -> 9786.483 | L21: 6881.617 | M21: 3240.787 | N21: =L21+M21 -> 10122.404 | O21: 370.744 | P21: 6495.196 | Q21: 5497.711 | R21: 5156.044 | S21: 50342.468 | T21: 23747.493 | U21: 26594.975 | V21: 24581.339 | W21: 4981.412 | X21: 14815.317 | Y21: 17435.466 | Z21: 11462.005 | AA21: 9087.217 | AB21: 2283.814 | AC21: 1171.457 | AD21: 61654.339 | AE21: 50867.585 | AF21: =IF(AE21="","",AD21-AE21) -> 10786.754 | AG21: 7634.078 | AH21: 3036.745 | AI21: =AG21+AH21 -> 10670.823 | AJ21: 567.441 | AK21: 7057.34 | AL21: 6049.867 | AM21: 5337.308 | AN21: 51527.99 | AO21: 26915.384 | AP21: 24612.606 | AQ21: 22380.325 | AR21: 6947.463 | AS21: 16703.714 | AT21: 15697.054 | AU21: 15842.614 | AV21: 10746.804 | AW21: 1759.181 | AX21: 957.777 | AZ21: Eastmoney F10 (filed annual reports)
A22: SLP | B22: Salt Lake Potash (青海盐湖) | C22: Agriculture | D22: Potash & lithium | E22: Peer | F22: CNY | G22: 000792.SZ | H22: =VLOOKUP(F22,FX!$A$5:$B$8,2,FALSE()) -> 7.129 | I22: 15501.244 | J22: 6532.978 | K22: =IF(J22="","",I22-J22) -> 8968.266 | L22: 6980.396 | M22: 1022.623 | N22: =L22+M22 -> 8003.019 | O22: 20.083 | P22: 7192.442 | Q22: 8946.571 | R22: 8475.535 | S22: 61163.912 | T22: 10697.171 | U22: 50466.74 | V22: 46274.967 | W22: 24413.659 | X22: 39605.514 | Y22: 8151.12 | Z22: 1280.904 | AA22: 10160.861 | AB22: 1641.484 | AC22: 984.451 | AD22: 15134.12 | AE22: 7285.882 | AF22: =IF(AE22="","",AD22-AE22) -> 7848.238 | AG22: 5758.816 | AH22: 833.237 | AI22: =AG22+AH22 -> 6592.053 | AJ22: 134.804 | AK22: 5757.273 | AL22: 4913.959 | AM22: 4663.117 | AN22: 45782.851 | AO22: 6188.817 | AP22: 39594.034 | AQ22: 36574.788 | AR22: 15623.633 | AS22: 27761.402 | AT22: 3787.298 | AU22: 516.063 | AV22: 7819.153 | AW22: 1221.806 | AX22: 1269.367 | AY22: Sinochem Corp holds a 5.73% stake (rating report) | AZ22: Eastmoney F10 (filed annual reports)
A23: PIR | B23: Pirelli | C23: Rubber | D23: Premium / High Value tyres | E23: Sinochem | F23: EUR | G23: PIRC.MI | H23: =VLOOKUP(F23,FX!$A$5:$B$8,2,FALSE()) -> 0.886 | I23: 6776.157 | K23: =IF(J23="","",I23-J23) | L23: 891.203 | M23: 573.6 | N23: =L23+M23 -> 1464.803 | O23: 290.605 | P23: 760.162 | Q23: 530.696 | R23: 497.527 | S23: 13353.183 | T23: 6896.446 | U23: 6456.737 | V23: 6277.848 | W23: 1525.886 | X23: 4134.659 | Y23: 2854.387 | Z23: 2957.794 | AA23: 1305.805 | AB23: 377.866 | AD23: 6773.324 | AF23: =IF(AE23="","",AD23-AE23) | AG23: 902.99 | AH23: 572.7 | AI23: =AG23+AH23 -> 1475.69 | AJ23: 422.911 | AK23: 647.793 | AL23: 501.104 | AM23: 467.981 | AN23: 13680.622 | AO23: 7768.368 | AP23: 5912.254 | AQ23: 5756.071 | AR23: 1502.741 | AS23: 4262.65 | AT23: 3340.409 | AU23: 3829.455 | AV23: 1292.564 | AW23: 403.673 | AY23: Sinochem (via Marco Polo International Italy) holds ~34.1% (Dec 2025); Pirelli's accounts state no entity controls it under IFRS 10 since Apr 2025; no COGS line (by-nature P&L) | AZ23: Pirelli 2025 Annual Report (IFRS)
A24: AEO | B24: Aeolus Tyre (风神股份) | C24: Rubber | D24: Truck & bus radial tyres | E24: Sinochem | F24: CNY | G24: 600469.SH | H24: =VLOOKUP(F24,FX!$A$5:$B$8,2,FALSE()) -> 7.129 | I24: 7413.482 | J24: 6315.936 | K24: =IF(J24="","",I24-J24) -> 1097.546 | L24: 289.908 | M24: 308.136 | N24: =L24+M24 -> 598.044 | O24: 29.481 | P24: 286.983 | Q24: 235.608 | R24: 235.608 | S24: 7968.86 | T24: 4449.733 | U24: 3519.127 | V24: 3519.127 | W24: 1078.531 | X24: 4168.755 | Y24: 3582.574 | Z24: 1318.976 | AA24: 495.9 | AB24: 406.881 | AC24: 73.476 | AD24: 6708.15 | AE24: 5563.258 | AF24: =IF(AE24="","",AD24-AE24) -> 1144.892 | AG24: 331.218 | AH24: 294.163 | AI24: =AG24+AH24 -> 625.381 | AJ24: 30.127 | AK24: 335.629 | AL24: 280.943 | AM24: 280.943 | AN24: 7325.203 | AO24: 4041.136 | AP24: 3284.067 | AQ24: 3284.067 | AR24: 912.752 | AS24: 3821.47 | AT24: 3499.196 | AU24: 1224.263 | AV24: 200.88 | AW24: 154.644 | AX24: 48.635 | AY24: ChemChina / CNTR sub. | AZ24: Eastmoney F10 (filed annual reports)
A25: MIC | B25: Michelin | C25: Rubber | D25: Global tyre major | E25: Peer | F25: EUR | G25: ML.PA | H25: =VLOOKUP(F25,FX!$A$5:$B$8,2,FALSE()) -> 0.886 | I25: 25992 | J25: 18973 | K25: =IF(J25="","",I25-J25) -> 7019 | L25: 2366 | M25: 1943 | N25: =L25+M25 -> 4309 | O25: 260 | P25: 2258 | Q25: 1664 | R25: 1665 | S25: 35018 | T25: 16942 | U25: 18076 | V25: 18072 | W25: 3877 | X25: 14271 | Y25: 7503 | Z25: 6645 | AA25: 3819 | AB25: 2017 | AD25: 27193 | AE25: 19445 | AF25: =IF(AE25="","",AD25-AE25) -> 7748 | AG25: 2631 | AH25: 1983 | AI25: =AG25+AH25 -> 4614 | AJ25: 218 | AK25: 2445 | AL25: 1890 | AM25: 1884 | AN25: 37352 | AO25: 18718 | AP25: 18634 | AQ25: 18625 | AR25: 3936 | AS25: 15339 | AT25: 8710 | AU25: 7439 | AV25: 4336 | AW25: 2250 | AZ25: Michelin 2025 URD (IFRS)
A26: BRI | B26: Bridgestone | C26: Rubber | D26: Global tyre major | E26: Peer | F26: JPY | G26: 5108.T | H26: =VLOOKUP(F26,FX!$A$5:$B$8,2,FALSE()) -> 149.632 | I26: 4429452 | J26: 2722789 | K26: =IF(J26="","",I26-J26) -> 1706663 | L26: 381237 | M26: 353229 | N26: =L26+M26 -> 734466 | O26: 44019 | P26: 354661 | Q26: 334299 | R26: 327264 | S26: 5747705 | T26: 2027817 | U26: 3719888 | V26: 3661793 | W26: 713810 | X26: 2863182 | Y26: 1122654 | Z26: 827015 | AA26: 660442 | AB26: 287155 | AD26: 4430096 | AE26: 2704093 | AF26: =IF(AE26="","",AD26-AE26) -> 1726003 | AG26: 443319 | AH26: 348058 | AI26: =AG26+AH26 -> 791377 | AJ26: 49802 | AK26: 421437 | AL26: 292181 | AM26: 284989 | AN26: 5723517 | AO26: 1937029 | AP26: 3786488 | AQ26: 3731606 | AR26: 706732 | AS26: 2863632 | AT26: 1176243 | AU26: 727721 | AV26: 548844 | AW26: 337293 | AZ26: Bridgestone FY2025 results (IFRS)
A27: GYR | B27: Goodyear | C27: Rubber | D27: Global tyre major | E27: Peer | F27: USD | G27: GT (Nasdaq) | H27: =VLOOKUP(F27,FX!$A$5:$B$8,2,FALSE()) -> 1 | I27: 18280 | J27: 14909 | K27: =IF(J27="","",I27-J27) -> 3371 | L27: -216 | M27: 1045 | N27: =L27+M27 -> 829 | O27: 445 | P27: -133 | Q27: -1700 | R27: -1721 | S27: 18208 | T27: 14805 | U27: 3403 | V27: 3233 | W27: 801 | X27: 7218 | Y27: 6782 | Z27: 6198 | AA27: 796 | AB27: 826 | AD27: 18878 | AE27: 15192 | AF27: =IF(AE27="","",AD27-AE27) -> 3686 | AG27: 693 | AH27: 1049 | AI27: =AG27+AH27 -> 1742 | AJ27: 522 | AK27: 130 | AL27: 35 | AM27: 46 | AN27: 20921 | AO27: 16098 | AP27: 4823 | AQ27: 4681 | AR27: 810 | AS27: 7589 | AT27: 7377 | AU27: 7782 | AV27: 698 | AW27: 1188 | AY27: FY2025 net loss of $1.7bn | AZ27: SEC EDGAR XBRL + Eastmoney US
A28: LLT | B28: Linglong Tire | C28: Rubber | D28: China tyre producer | E28: Peer | F28: CNY | G28: 601966.SH | H28: =VLOOKUP(F28,FX!$A$5:$B$8,2,FALSE()) -> 7.129 | I28: 24642.158 | J28: 20445.464 | K28: =IF(J28="","",I28-J28) -> 4196.694 | L28: 1213.03 | M28: 1875.387 | N28: =L28+M28 -> 3088.417 | O28: 290.896 | P28: 1542.485 | Q28: 1368.753 | R28: 1368.871 | S28: 47375.105 | T28: 24266.753 | U28: 23108.352 | V28: 23099.98 | W28: 3332.294 | X28: 15703.779 | Y28: 17648.117 | Z28: 14173.647 | AA28: 1988.798 | AB28: 1765.059 | AC28: 166.994 | AD28: 22057.939 | AE28: 17191.783 | AF28: =IF(AE28="","",AD28-AE28) -> 4866.156 | AG28: 2300.858 | AH28: 1619.892 | AI28: =AG28+AH28 -> 3920.75 | AJ28: 290.937 | AK28: 1970.606 | AL28: 1752.035 | AM28: 1752.352 | AN28: 47083.204 | AO28: 25397.323 | AP28: 21685.88 | AQ28: 21680.373 | AR28: 3626.469 | AS28: 15890.304 | AT28: 19914.082 | AU28: 15000.148 | AV28: 1937.092 | AW28: 2442.512 | AX28: 140.61 | AZ28: Eastmoney F10 (filed annual reports)
A29: SLG | B29: Sailun Group | C29: Rubber | D29: China tyre producer | E29: Peer | F29: CNY | G29: 601058.SH | H29: =VLOOKUP(F29,FX!$A$5:$B$8,2,FALSE()) -> 7.129 | I29: 36792.434 | J29: 27711.171 | K29: =IF(J29="","",I29-J29) -> 9081.263 | L29: 4591.048 | M29: 2072.636 | N29: =L29+M29 -> 6663.684 | O29: 474.614 | P29: 4175.993 | Q29: 3616.804 | R29: 3522.493 | S29: 46770.401 | T29: 23413.271 | U29: 23357.13 | V29: 21614.62 | W29: 4579.35 | X29: 20701.283 | Y29: 18364.718 | Z29: 12054.171 | AA29: 4178.798 | AB29: 4817.731 | AC29: 118.174 | AD29: 31802.388 | AE29: 23030.342 | AF29: =IF(AE29="","",AD29-AE29) -> 8772.046 | AG29: 5057.087 | AH29: 1721.191 | AI29: =AG29+AH29 -> 6778.278 | AJ29: 387.312 | AK29: 4660.284 | AL29: 4123.497 | AM29: 4062.674 | AN29: 40284.983 | AO29: 19713.262 | AP29: 20571.721 | AQ29: 19509.382 | AR29: 5517.001 | AS29: 19500.01 | AT29: 15732.564 | AU29: 10466.66 | AV29: 2288.785 | AW29: 4024.463 | AX29: 109.875 | AZ29: Eastmoney F10 (filed annual reports)
A30: ZCR | B30: Zhongce Rubber | C30: Rubber | D30: China tyre producer | E30: Peer | F30: CNY | G30: 603049.SH | H30: =VLOOKUP(F30,FX!$A$5:$B$8,2,FALSE()) -> 7.129 | I30: 44956.23 | J30: 36118.781 | K30: =IF(J30="","",I30-J30) -> 8837.449 | L30: 4777.353 | M30: 2189.686 | N30: =L30+M30 -> 6967.039 | O30: 327.976 | P30: 4287.902 | Q30: 4147.469 | R30: 4147.466 | S30: 52221.061 | T30: 27408.917 | U30: 24812.145 | V30: 24811.363 | W30: 5242.326 | X30: 25238.914 | Y30: 23437.867 | Z30: 12862.265 | AA30: 1903.845 | AB30: 3505.964 | AC30: 190.771 | AD30: 39254.81 | AE30: 31606.555 | AF30: =IF(AE30="","",AD30-AE30) -> 7648.255 | AG30: 4076.732 | AH30: 1979.651 | AI30: =AG30+AH30 -> 6056.383 | AJ30: 347.907 | AK30: 3880.524 | AL30: 3787.149 | AM30: 3787.17 | AN30: 44824.439 | AO30: 27347.1 | AP30: 17477.339 | AQ30: 17476.561 | AR30: 4119.42 | AS30: 21707.545 | AT30: 22531.197 | AU30: 12728.383 | AV30: 3041.257 | AW30: 2343.076 | AX30: 184.724 | AZ30: Eastmoney F10 (filed annual reports)
A31: HNR | B31: Hainan Rubber | C31: Rubber | D31: Natural rubber (owns Halcyon Agri stake) | E31: Peer | F31: CNY | G31: 601118.SH | H31: =VLOOKUP(F31,FX!$A$5:$B$8,2,FALSE()) -> 7.129 | I31: 42237.152 | J31: 41174.759 | K31: =IF(J31="","",I31-J31) -> 1062.393 | L31: 157.362 | M31: 826.55 | N31: =L31+M31 -> 983.912 | O31: 678.538 | P31: -128.769 | Q31: -313.296 | R31: -103.031 | S31: 33833.966 | T31: 23781.668 | U31: 10052.298 | V31: 10098.102 | W31: 5269.006 | X31: 13389.953 | Y31: 14502.652 | Z31: 17230.455 | AA31: 2504.831 | AB31: 615.461 | AC31: 134.493 | AD31: 42004.166 | AE31: 40411.157 | AF31: =IF(AE31="","",AD31-AE31) -> 1593.009 | AG31: 132.166 | AH31: 807.422 | AI31: =AG31+AH31 -> 939.588 | AJ31: 743.772 | AK31: 135.082 | AL31: -85.691 | AM31: 103.389 | AN31: 36069.765 | AO31: 24771.383 | AP31: 11298.382 | AQ31: 9846.348 | AR31: 5687.636 | AS31: 15465.796 | AT31: 15193.001 | AU31: 17792.022 | AV31: 1555.28 | AW31: 871.25 | AX31: 132.644 | AY31: Agreed in Nov 2022 to buy 36% of Halcyon Agri from Sinochem International (completion not verified) | AZ31: Eastmoney F10 (filed annual reports)

Sheet FX
A1: Average exchange rates used for USD translation
A2: Local currency per 1 USD, calendar-2025 average (IRS yearly average rates). Edit the blue cells to re-translate every USD figure in the workbook.
A4: Currency | B4: LC per USD (2025 avg) | C4: LC per USD (2024 avg)
A5: USD | B5: 1 | C5: 1
A6: CNY | B6: 7.129 | C6: 7.189
A7: EUR | B7: 0.886 | C7: 0.924
A8: JPY | B8: 149.632 | C8: 151.353
A11: Source: https://www.irs.gov/individuals/international-taxpayers/yearly-average-currency-exchange-rates (tables for 2025 and 2024).

Sheet Sources
A1: Sources
A3: Sinochem Corp 2026 tracking rating report (FY2025, Q1 2026) | B3: http://static.sse.com.cn/disclosure/bond/announcement/company/c/new/2026-06-23/244212_20260623_CREQ.pdf
A4: Sinochem Corp 2025 tracking rating report (FY2024) | B4: http://static.sse.com.cn/disclosure/bond/announcement/company/c/new/2025-06-23/241247_20250623_1DU5.pdf
A5: Sinochem Energy FY2025 audited consolidated statements (天职业字[2026]19618号) | B5: http://static.sse.com.cn/disclosure/bond/announcement/company/c/new/2026-04-30/115421_20260430_T7YL.pdf
A6: Syngenta AG Financial Report 2025 | B6: https://www.syngenta.com/sites/default/files/2026-03/Financial%20Report%202025_0.pdf
A7: Syngenta Group FY2025 results release | B7: https://www.syngentagroup.com/newsroom/2026/syngenta-group-reports-2025-full-year-results
A8: Syngenta Group H1 2026 results | B8: https://www.syngentagroup.com/sites/default/files/2026-08/260827-Syngenta-Group-Q2-H1_EN_2949a0aa.pdf
A9: Pirelli 2025 Annual Report | B9: https://corp-assets.pirelli.com/corporate/Annual_Report_Pirelli_2025_ENG.pdf
A10: Pirelli FY2025 preliminary results release | B10: https://press.pirelli.com/review-of-preliminary-results-to-31-december-2025-and-2026-budget/
A11: Pirelli H1 2026 results release | B11: https://press.pirelli.com/pirelli-board-majority-approves-consolidated-results-to-30-june-2026/
A12: Michelin 2025 Universal Registration Document | B12: https://www.michelin.com/en/publications/group/financial-information-december-31-2025
A13: Bridgestone Consolidated Financial Results FY2025 | B13: https://www.bridgestone.com/ir/library/result/pdf/e_r7_4_results.pdf
A14: Nutrien 2025 audited financial statements (40-F ex. 99.3) | B14: https://www.sec.gov/Archives/edgar/data/1725964/000119312526081326/d56746dex993.htm
... A19: Michelin H1 2026 results | B19: https://www.michelin.com/en/publications/group/financial-information-at-june-30-2026
