Workbook

Sheet README
A1: COFCO Corporation - analysis data pack
A3: Each sheet = one table used in the report. Sources: see the 'source' row and resources/SOURCES.md.
A4: Prepared 13 Oct 2026. Educational analysis; not investment advice.

Sheet group_financials
A1: COFCO Corporation (consolidated) - headline financials, RMB bn
A3: year | B3: total_revenue | C3: total_profit_pre_tax | D3: net_profit | E3: net_profit_to_parent | F3: total_assets | G3: liabilities_to_assets_pct | H3: total_debt | I3: ebitda | J3: debt_to_ebitda_x
A4: 2021 | B4: 664.95 | C4: 23.81 | F4: 686.01 | G4: 70.39 | H4: 224.54 | I4: 39.99 | J4: 5.62
A5: 2022 | B5: 741.44 | C5: 22.85 | F5: 695.57 | G5: 69.01 | H5: 214.36 | I5: 40.26 | J5: 5.32
A6: 2023 | B6: 692.1 | C6: 21.17 | F6: 730.65 | G6: 65.35 | H6: 231.64 | I6: 39.48 | J6: 5.87
A7: 2024 | B7: 619.05 | C7: 11.78 | D7: 5.01 | E7: 1.87 | F7: 693.76 | G7: 63.31
A8: 2025 | B8: 589.06 | C8: 12.05 | D8: 5.89 | E8: 2.41 | F8: 721.6 | G8: 64.55
A10: Source tags: G1, G2, G3
A11: Note: 2021-2023 from Lianhe ratings (as originally reported). 2024-2025 from the 2025 bond annual report; 2024 is restated for an accounting policy change (originally RMB 635.0bn revenue / 8.2bn pre-tax profit). 2024 debt/EBITDA as originally reported: debt 200.6bn, EBITDA 25.9bn, 7.73x.

Sheet group_segments
A1: COFCO Corporation - operating revenue and gross margin by segment, RMB bn
A3: segment | B3: rev_2023 | C3: gm_2023_pct | D3: rev_2024 | E3: gm_2024_pct | F3: rev_2025 | G3: gm_2025_pct
A4: Agri trading & processing (grain, oilseed, sugar, cotton, meat) | B4: 600.66 | C4: 5.43 | D4: 543.2 | E4: 5.87 | F4: 518.25 | G4: 5.82
A5: Food & packaging (China Foods/Coca-Cola, tea, liquor) | B5: 30.48 | C5: 42.79 | D5: 28.36 | E5: 35.39 | F5: 27.95 | G5: 33.71
A6: Hotels & property (Joy City) | B6: 36.9 | C6: 26.42 | D6: 35.91 | E6: 21.41 | F6: 31.02 | G6: 31.17
A7: Finance & other | B7: 4.63 | C7: 14.89 | D7: 2.39 | E7: 36.37 | F7: 2.38 | G7: 35.48
A9: Source tags: G1, G3
A10: Note: Operating revenue excludes insurance/interest income. Mengniu (dairy) is equity-accounted, so it is not in these lines.

Sheet group_segment_gp_2025
A1: COFCO Corporation - 2025 revenue share vs gross-profit share
A3: segment | B3: revenue_bn | C3: gross_profit_bn | D3: revenue_share_pct | E3: gp_share_pct
A4: Agri trading & processing | B4: 518.2 | C4: 30.2 | D4: 89.4 | E4: 60.2
A5: Food & packaging | B5: 27.9 | C5: 9.4 | D5: 4.8 | E5: 18.8
A6: Hotels & property | B6: 31 | C6: 9.7 | D6: 5.4 | E6: 19.3
A7: Finance & other | B7: 2.4 | C7: 0.8 | D7: 0.4 | E7: 1.7
A9: Source tags: G3
A10: Note: Gross profit = revenue - cost of sales by segment (bond annual report table).

Sheet cofco_intl
A1: COFCO International - revenue (US$ bn) and volumes (million tonnes)
A3: year | B3: revenue_usd_bn | C3: volume_mt
A4: 2020 | B4: 33 | C4: 131
A5: 2021 | B5: 48 | C5: 133
A6: 2022 | B6: 53.3 | C6: 127
A7: 2023 | B7: 50.1 | C7: 121.7
A8: 2024 | B8: 38.5 | C8: 108.4
A9: 2025 | B9: 34.5 | C9: 100.4
A11: Source tags: C1, C2, C3, C4
A12: Note: 2020-2021 volume is total traded volume; 2022+ is third-party sales volume. Profit is not disclosed.

Sheet traders
A1: Global grain traders - revenue (US$ bn) and net income (US$ bn)
A3: company | B3: rev_2021 | C3: rev_2022 | D3: rev_2023 | E3: rev_2024 | F3: rev_2025 | G3: ni_2021 | H3: ni_2022 | I3: ni_2023 | J3: ni_2024 | K3: ni_2025
A4: ADM | B4: 85.25 | C4: 101.56 | D4: 93.94 | E4: 85.53 | F4: 80.27 | G4: 2.71 | H4: 4.34 | I4: 3.48 | J4: 1.8 | K4: 1.08
A5: Bunge | B5: 59.15 | C5: 67.23 | D5: 59.54 | E5: 53.11 | F5: 70.33 | G5: 2.08 | H5: 1.61 | I5: 2.24 | J5: 1.14 | K5: 0.82
A6: Louis Dreyfus (LDC) | B6: 49.6 | C6: 59.9 | D6: 50.6 | E6: 50.6 | F6: 53.2 | G6: 0.7 | H6: 1.01 | I6: 1.01 | J6: 0.73 | K6: 0.65
A7: Wilmar | B7: 65.79 | C7: 73.4 | D7: 67.16 | E7: 67.38 | F7: 70.42 | G7: 1.89 | H7: 2.4 | I7: 1.52 | J7: 1.17 | K7: 1.41
A8: COFCO International | B8: 48 | C8: 53.3 | D8: 50.1 | E8: 38.5 | F8: 34.5
A10: Source tags: T1, T2, T3, T4, C1
A11: Note: 2025 and 2024 figures checked against 2025 releases; 2021-2023 compiled from company annual reports. Bunge 2025 includes Viterra from July 2025. Wilmar 2025 net profit includes a US$1.14bn one-off gain; core net profit US$1.28bn.

Sheet soy_imports
A1: China soybean imports, million tonnes (customs)
A3: year | B3: imports_mt
A4: 2019 | B4: 88.51
A5: 2020 | B5: 100.33
A6: 2021 | B6: 96.52
A7: 2022 | B7: 91.08
A8: 2023 | B8: 99.41
A9: 2024 | B9: 105.03
A10: 2025 | B10: 111.83
A12: Source tags: M1
A13: Note: 2025 = 111.83mt (+6.5%), a record. Earlier years from GACC annual releases.

Sheet joycome
A1: COFCO Joycome - key operating and financial data
A3: period | B3: revenue_rmb_bn | C3: profit_before_ba_rmb_bn | D3: profit_after_ba_rmb_bn | E3: hog_asp_rmb_per_kg | F3: hog_volume_m_heads | G3: fresh_pork_kt
A4: 2019 | B4: 11.08 | C4: 0.37 | D4: 1.52 | E4: 16.16 | F4: 1.985 | G4: 146
A5: 2020 | B5: 18.92 | C5: 2.91 | D5: 4.02 | E5: 32.33 | F5: 2.046 | G5: 109
A6: 2021 | B6: 13.23 | C6: 2.35 | D6: -0.48 | E6: 18.26 | F6: 3.437 | G6: 166
A7: 2022 | B7: 12.9 | C7: -0.32 | D7: 0.36 | E7: 17.86 | F7: 4.103 | G7: 231
A8: 2023 | B8: 17.24 | C8: 0.15 | D8: -0.03 | E8: 14.55 | F8: 5.2 | G8: 245
A9: 2024 | B9: 16.33 | C9: 0.28 | D9: 0.55 | E9: 16.53 | F9: 3.56 | G9: 262
A10: 2025 | B10: 18.58 | C10: -0.29 | D10: -0.74 | E10: 13.39 | G10: 341
A11: H1 2025 | B11: 8.96 | C11: 0.2 | D11: 0.32 | E11: 14.59 | G11: 150
A12: H1 2026 | B12: 8.74 | C12: -1.1 | D12: -1.56 | E12: 10.27 | G12: 197
A14: Source tags: J1, J2, J3, J4, J5, J6
A15: Note: Profit for the period (incl. minorities). BA = biological asset fair value adjustment. Hog volume no longer disclosed after 2024.

Sheet joycome_segments
A1: COFCO Joycome - segment results, RMB m
A3: segment | B3: FY2024 | C3: FY2025 | D3: H1_2025 | E3: H1_2026
A4: Hog production | B4: 258.6 | C4: -159.1 | D4: 243.9 | E4: -993.7
A5: Feed | B5: 202.4 | C5: 157.9 | D5: 55.8 | E5: 54.8
A6: Fresh pork | B6: -57.2 | C6: -5.6 | D6: -4.3 | E6: 24.4
A7: Processed meat | B7: 35.5 | C7: 6.1 | D7: 6.2 | E7: -12.2
A8: Meat import | B8: 58.2 | C8: 19.9 | D8: 15.8 | E8: 24
A10: Source tags: J1, J2
A11: Note: Segment results before fair value adjustments, corporate items and finance costs.

Sheet pork_peers
A1: China hog producers - comparison
A3: company | B3: np_2024_rmb_bn | C3: np_2025_rmb_bn | D3: np_H1_2026_rmb_bn | E3: hogs_sold_2025_m | F3: asp_H1_2025 | G3: asp_H1_2026
A4: Muyuan | B4: 17.88 | C4: 15.49 | D4: -6.2 | E4: 77.98 | F4: 14.4 | G4: 10.4
A5: Wens | B5: 9.28 | C5: 5.27 | D5: -4.37 | E5: 40.48 | F5: 14.93 | G5: 10.5
A6: New Hope | B6: 0.47 | C6: -1.78 | E6: 17.55
A7: COFCO Joycome | B7: 0.54 | C7: -0.75 | D7: -1.55 | F7: 14.59 | G7: 10.27
A9: Source tags: P1, P2, P3, J1, J2
A10: Note: Net profit attributable to shareholders (after BA for Joycome). Muyuan H1 2026 = midpoint of its RMB 5.7-6.7bn loss guidance; Muyuan H1 2025 ASP derived from the ~28% decline it reported.

Sheet sow_herd
A1: China breeding sow inventory, million head (NBS / MARA)
A3: date | B3: sows_m | C3: normal_level_m
A4: 2022 peak | B4: 43.9 | C4: 41
A5: End-2024 | B5: 40.79 | C5: 39
A6: End-2025 | B6: 39.61 | C6: 39
A7: Jun-2026 | B7: 37.8 | C7: 37.5
A9: Source tags: J1, J2
A10: Note: Normal-level reserve as quoted by MARA guidance at each date (41.0m pre-2024 guideline). End-2024 derived from the -2.9% change.

Sheet mengniu
A1: China Mengniu Dairy - revenue and profit, RMB bn
A3: period | B3: revenue | C3: np_attrib | D3: np_adjusted | E3: gross_margin_pct
A4: 2019 | B4: 79.03 | C4: 4.11
A5: 2020 | B5: 76.04 | C5: 3.53
A6: 2021 | B6: 88.14 | C6: 5.03
A7: 2022 | B7: 92.59 | C7: 5.3
A8: 2023 | B8: 98.62 | C8: 4.81
A9: 2024 | B9: 88.68 | C9: 0.105 | D9: 4.435 | E9: 39.6
A10: 2025 | B10: 82.24 | C10: 1.545 | D10: 3.96 | E10: 39.9
A11: H1 2025 | B11: 41.57 | C11: 2.046 | E11: 41.7
A12: H1 2026 | B12: 44.79 | C12: 2.371 | E12: 40.8
A14: Source tags: D1, D2, D3, D4
A15: Note: Adjusted profit excludes the Bellamy's impairment (2024: RMB 3.98bn) and associate one-offs (Mengniu's own definition).

Sheet mengniu_segments
A1: Mengniu revenue by segment, RMB m
A3: segment | B3: FY2024 | C3: FY2025 | D3: H1_2025 | E3: H1_2026
A4: Liquid milk | B4: 73066 | C4: 64939 | D4: 32192 | E4: 33865
A5: Ice cream | B5: 5175 | C5: 5393 | D5: 3879 | E5: 4207
A6: Cheese | B6: 4320 | C6: 5266 | D6: 2374 | E6: 3148
A7: Milk formula & others | B7: 6114 | C7: 6647 | D7: 3122 | E7: 3575
A9: Source tags: D1, D2
A10: Note: H1 'Milk formula & others' = total less the three named segments.

Sheet dairy_peers
A1: Mengniu vs Yili - revenue and attributable net profit, RMB bn
A3: year | B3: mengniu_rev | C3: yili_rev | D3: mengniu_np | E3: yili_np
A4: 2019 | B4: 79.03 | C4: 90.22 | D4: 4.11 | E4: 6.93
A5: 2020 | B5: 76.04 | C5: 96.89 | D5: 3.53 | E5: 7.08
A6: 2021 | B6: 88.14 | C6: 110.6 | D6: 5.03 | E6: 8.7
A7: 2022 | B7: 92.59 | C7: 123.17 | D7: 5.3 | E7: 9.43
A8: 2023 | B8: 98.62 | C8: 126.18 | D8: 4.81 | E8: 10.43
A9: 2024 | B9: 88.68 | C9: 115.78 | D9: 0.105 | E9: 8.45
A10: 2025 | B10: 82.24 | C10: 115.93 | D10: 1.545 | E10: 11.57
A12: Source tags: D1, D5, D6
A13: Note: H1 2026: Yili revenue RMB 64.5bn (+4.1%), net profit RMB 5.76bn (-20.0%, goodwill impairment on Ausnutria); Mengniu +7.8% / +15.9%.

Sheet ratios
A1: Computed ratios (live formulas)
A3: Grain traders net margin % | B3: 2021 | C3: 2022 | D3: 2023 | E3: 2024 | F3: 2025
A4: =traders!A4 | B4: =traders!G4/traders!B4*100 | C4: =traders!H4/traders!C4*100 | D4: =traders!I4/traders!D4*100 | E4: =traders!J4/traders!E4*100 | F4: =traders!K4/traders!F4*100
A5: =traders!A5 | B5: =traders!G5/traders!B5*100 | C5: =traders!H5/traders!C5*100 | D5: =traders!I5/traders!D5*100 | E5: =traders!J5/traders!E5*100 | F5: =traders!K5/traders!F5*100
A6: =traders!A6 | B6: =traders!G6/traders!B6*100 | C6: =traders!H6/traders!C6*100 | D6: =traders!I6/traders!D6*100 | E6: =traders!J6/traders!E6*100 | F6: =traders!K6/traders!F6*100
A7: =traders!A7 | B7: =traders!G7/traders!B7*100 | C7: =traders!H7/traders!C7*100 | D7: =traders!I7/traders!D7*100 | E7: =traders!J7/traders!E7*100 | F7: =traders!K7/traders!F7*100
A9: COFCO group pre-tax margin % | B9: 2021 | C9: 2022 | D9: 2023 | E9: 2024 | F9: 2025
A10: COFCO | B10: =group_financials!C4/group_financials!B4*100 | C10: =group_financials!C5/group_financials!B5*100 | D10: =group_financials!C6/group_financials!B6*100 | E10: =group_financials!C7/group_financials!B7*100 | F10: =group_financials!C8/group_financials!B8*100
A12: Joycome profit before BA margin % | B12: 2019 | C12: 2020 | D12: 2021 | E12: 2022 | F12: 2023 | G12: 2024 | H12: 2025 | I12: H1 2025 | J12: H1 2026
A13: Joycome | B13: =joycome!C4/joycome!B4*100 | C13: =joycome!C5/joycome!B5*100 | D13: =joycome!C6/joycome!B6*100 | E13: =joycome!C7/joycome!B7*100 | F13: =joycome!C8/joycome!B8*100 | G13: =joycome!C9/joycome!B9*100 | H13: =joycome!C10/joycome!B10*100 | I13: =joycome!C11/joycome!B11*100 | J13: =joycome!C12/joycome!B12*100

Sheet cycle_scores
A1: sector | B1: 2019 | C1: 2020 | D1: 2021 | E1: 2022 | F1: 2023 | G1: 2024 | H1: 2025 | I1: H1 2026 | J1: 2027E
A2: Grains & oilseeds | B2: 0 | C2: 1 | D2: 2 | E2: 2 | F2: 1 | G2: -1 | H2: -1 | I2: -1 | J2: 0
A3: Pork (Joycome) | B3: 1 | C3: 2 | D3: 0 | E3: -1 | F3: -1 | G3: 1 | H3: -1 | I3: -2 | J3: 1
A4: Dairy (Mengniu) | B4: 1 | C4: 0 | D4: 1 | E4: 1 | F4: 0 | G4: -2 | H4: -1 | I4: 0 | J4: 1
A6: Scale: -2 deep trough, -1 weak, 0 neutral, +1 good, +2 boom. Analyst judgement.
